Workbook

Sheet Tableau de bord
A1: Tableau de bord du mois
A2: Change le mois dans Paramètres (cellule B8). Seules les commandes « Livrée et payée » comptent dans le chiffre d’affaires.
A3: Cellules jaunes : à remplir · cellules grises : calculées automatiquement (ne pas modifier)
A4: Mois affiché | B4: =Paramètres!$B$17 -> 46296 | C4: =Paramètres!B6 -> Pagnes de Fatou
F5: TOP PRODUITS ET SERVICES DU MOIS
A6: Indicateur | B6: Ce mois | C6: Mois précédent | D6: Évolution | F6: Produit / service | G6: Qté | H6: Chiffre d’affaires | I6: Marge brute | J6: Part du CA
A7: Chiffre d’affaires (FCFA) | B7: =SUMIFS(Ventes!$K$6:$K$505,Ventes!$T$6:$T$505,$B$4,Ventes!$M$6:$M$505,"Livrée et payée") -> 150000 | C7: =SUMIFS(Ventes!$K$6:$K$505,Ventes!$T$6:$T$505,Paramètres!$B$18,Ventes!$M$6:$M$505,"Livrée et payée") -> 64000 | D7: =IF(N(C7)=0,"",B7/C7-1) -> 1.34375 | F7: =IF(Catalogue!B6="","",Catalogue!B6) -> Pagne wax 6 yards | G7: =IF(F7="","",SUMIFS(Ventes!$G$6:$G$505,Ventes!$F$6:$F$505,F7,Ventes!$T$6:$T$505,$B$4,Ventes!$M$6:$M$505,"Livrée et payée")) -> 8 | H7: =IF(F7="","",SUMIFS(Ventes!$K$6:$K$505,Ventes!$F$6:$F$505,F7,Ventes!$T$6:$T$505,$B$4,Ventes!$M$6:$M$505,"Livrée et payée")) -> 80000 | I7: =IF(F7="","",SUMIFS(Ventes!$R$6:$R$505,Ventes!$F$6:$F$505,F7,Ventes!$T$6:$T$505,$B$4)) -> 33600 | J7: =IF(OR(F7="",N($B$7)=0),"",H7/$B$7) -> 0.53333333
A8: Nombre de ventes | B8: =COUNTIFS(Ventes!$T$6:$T$505,$B$4,Ventes!$M$6:$M$505,"Livrée et payée") -> 11 | C8: =COUNTIFS(Ventes!$T$6:$T$505,Paramètres!$B$18,Ventes!$M$6:$M$505,"Livrée et payée") -> 6 | D8: =IF(N(C8)=0,"",B8/C8-1) -> 0.83333333 | F8: =IF(Catalogue!B7="","",Catalogue!B7) -> Foulard assorti | G8: =IF(F8="","",SUMIFS(Ventes!$G$6:$G$505,Ventes!$F$6:$F$505,F8,Ventes!$T$6:$T$505,$B$4,Ventes!$M$6:$M$505,"Livrée et payée")) -> 3 | H8: =IF(F8="","",SUMIFS(Ventes!$K$6:$K$505,Ventes!$F$6:$F$505,F8,Ventes!$T$6:$T$505,$B$4,Ventes!$M$6:$M$505,"Livrée et payée")) -> 10500 | I8: =IF(F8="","",SUMIFS(Ventes!$R$6:$R$505,Ventes!$F$6:$F$505,F8,Ventes!$T$6:$T$505,$B$4)) -> 6450 | J8: =IF(OR(F8="",N($B$7)=0),"",H8/$B$7) -> 0.07
A9: Articles ou prestations vendus | B9: =SUMIFS(Ventes!$G$6:$G$505,Ventes!$T$6:$T$505,$B$4,Ventes!$M$6:$M$505,"Livrée et payée") -> 14 | C9: =SUMIFS(Ventes!$G$6:$G$505,Ventes!$T$6:$T$505,Paramètres!$B$18,Ventes!$M$6:$M$505,"Livrée et payée") -> 7 | D9: =IF(N(C9)=0,"",B9/C9-1) -> 1 | F9: =IF(Catalogue!B8="","",Catalogue!B8) -> Pack 3 pagnes | G9: =IF(F9="","",SUMIFS(Ventes!$G$6:$G$505,Ventes!$F$6:$F$505,F9,Ventes!$T$6:$T$505,$B$4,Ventes!$M$6:$M$505,"Livrée et payée")) -> 2 | H9: =IF(F9="","",SUMIFS(Ventes!$K$6:$K$505,Ventes!$F$6:$F$505,F9,Ventes!$T$6:$T$505,$B$4,Ventes!$M$6:$M$505,"Livrée et payée")) -> 52000 | I9: =IF(F9="","",SUMIFS(Ventes!$R$6:$R$505,Ventes!$F$6:$F$505,F9,Ventes!$T$6:$T$505,$B$4)) -> 24200 | J9: =IF(OR(F9="",N($B$7)=0),"",H9/$B$7) -> 0.34666667
A10: Panier moyen (FCFA) | B10: =IF(N(B8)=0,0,B7/B8) -> 13636.364 | C10: =IF(N(C8)=0,0,C7/C8) -> 10666.667 | D10: =IF(N(C10)=0,"",B10/C10-1) -> 0.27840909 | F10: =IF(Catalogue!B9="","",Catalogue!B9) -> Conseil style à domicile | G10: =IF(F10="","",SUMIFS(Ventes!$G$6:$G$505,Ventes!$F$6:$F$505,F10,Ventes!$T$6:$T$505,$B$4,Ventes!$M$6:$M$505,"Livrée et payée")) -> 1 | H10: =IF(F10="","",SUMIFS(Ventes!$K$6:$K$505,Ventes!$F$6:$F$505,F10,Ventes!$T$6:$T$505,$B$4,Ventes!$M$6:$M$505,"Livrée et payée")) -> 7500 | I10: =IF(F10="","",SUMIFS(Ventes!$R$6:$R$505,Ventes!$F$6:$F$505,F10,Ventes!$T$6:$T$505,$B$4)) -> 5500 | J10: =IF(OR(F10="",N($B$7)=0),"",H10/$B$7) -> 0.05
A11: Commandes annulées ou retournées | B11: =COUNTIFS(Ventes!$T$6:$T$505,$B$4,Ventes!$M$6:$M$505,"Annulée")+COUNTIFS(Ventes!$T$6:$T$505,$B$4,Ventes!$M$6:$M$505,"Retournée") -> 1 | C11: =COUNTIFS(Ventes!$T$6:$T$505,Paramètres!$B$18,Ventes!$M$6:$M$505,"Annulée")+COUNTIFS(Ventes!$T$6:$T$505,Paramètres!$B$18,Ventes!$M$6:$M$505,"Retournée") -> 1 | D11: =IF(N(C11)=0,"",B11/C11-1) -> 0 | F11: =IF(Catalogue!B10="","",Catalogue!B10) | G11: =IF(F11="","",SUMIFS(Ventes!$G$6:$G$505,Ventes!$F$6:$F$505,F11,Ventes!$T$6:$T$505,$B$4,Ventes!$M$6:$M$505,"Livrée et payée")) | H11: =IF(F11="","",SUMIFS(Ventes!$K$6:$K$505,Ventes!$F$6:$F$505,F11,Ventes!$T$6:$T$505,$B$4,Ventes!$M$6:$M$505,"Livrée et payée")) | I11: =IF(F11="","",SUMIFS(Ventes!$R$6:$R$505,Ventes!$F$6:$F$505,F11,Ventes!$T$6:$T$505,$B$4)) | J11: =IF(OR(F11="",N($B$7)=0),"",H11/$B$7)
A12: Taux d’annulation | B12: =IF((B8+B11)=0,0,B11/(B8+B11)) -> 0.083333333 | C12: =IF((C8+C11)=0,0,C11/(C8+C11)) -> 0.14285714 | D12: =(B12-C12)*100 -> -5.952381 | F12: =IF(Catalogue!B11="","",Catalogue!B11) | G12: =IF(F12="","",SUMIFS(Ventes!$G$6:$G$505,Ventes!$F$6:$F$505,F12,Ventes!$T$6:$T$505,$B$4,Ventes!$M$6:$M$505,"Livrée et payée")) | H12: =IF(F12="","",SUMIFS(Ventes!$K$6:$K$505,Ventes!$F$6:$F$505,F12,Ventes!$T$6:$T$505,$B$4,Ventes!$M$6:$M$505,"Livrée et payée")) | I12: =IF(F12="","",SUMIFS(Ventes!$R$6:$R$505,Ventes!$F$6:$F$505,F12,Ventes!$T$6:$T$505,$B$4)) | J12: =IF(OR(F12="",N($B$7)=0),"",H12/$B$7)
A13: Dépenses en publicité (FCFA) | B13: =SUMIFS('Suivi pubs'!$E$6:$E$370,'Suivi pubs'!$N$6:$N$370,$B$4) -> 12000 | C13: =SUMIFS('Suivi pubs'!$E$6:$E$370,'Suivi pubs'!$N$6:$N$370,Paramètres!$B$18) -> 6000 | D13: =IF(N(C13)=0,"",B13/C13-1) -> 1 | F13: =IF(Catalogue!B12="","",Catalogue!B12) | G13: =IF(F13="","",SUMIFS(Ventes!$G$6:$G$505,Ventes!$F$6:$F$505,F13,Ventes!$T$6:$T$505,$B$4,Ventes!$M$6:$M$505,"Livrée et payée")) | H13: =IF(F13="","",SUMIFS(Ventes!$K$6:$K$505,Ventes!$F$6:$F$505,F13,Ventes!$T$6:$T$505,$B$4,Ventes!$M$6:$M$505,"Livrée et payée")) | I13: =IF(F13="","",SUMIFS(Ventes!$R$6:$R$505,Ventes!$F$6:$F$505,F13,Ventes!$T$6:$T$505,$B$4)) | J13: =IF(OR(F13="",N($B$7)=0),"",H13/$B$7)
A14: Messages reçus grâce aux pubs | B14: =SUMIFS('Suivi pubs'!$F$6:$F$370,'Suivi pubs'!$N$6:$N$370,$B$4) -> 49 | C14: =SUMIFS('Suivi pubs'!$F$6:$F$370,'Suivi pubs'!$N$6:$N$370,Paramètres!$B$18) -> 12 | D14: =IF(N(C14)=0,"",B14/C14-1) -> 3.0833333 | F14: =IF(Catalogue!B13="","",Catalogue!B13) | G14: =IF(F14="","",SUMIFS(Ventes!$G$6:$G$505,Ventes!$F$6:$F$505,F14,Ventes!$T$6:$T$505,$B$4,Ventes!$M$6:$M$505,"Livrée et payée")) | H14: =IF(F14="","",SUMIFS(Ventes!$K$6:$K$505,Ventes!$F$6:$F$505,F14,Ventes!$T$6:$T$505,$B$4,Ventes!$M$6:$M$505,"Livrée et payée")) | I14: =IF(F14="","",SUMIFS(Ventes!$R$6:$R$505,Ventes!$F$6:$F$505,F14,Ventes!$T$6:$T$505,$B$4)) | J14: =IF(OR(F14="",N($B$7)=0),"",H14/$B$7)
A15: Ventes notées dans le suivi des pubs | B15: =SUMIFS('Suivi pubs'!$G$6:$G$370,'Suivi pubs'!$N$6:$N$370,$B$4) -> 7 | C15: =SUMIFS('Suivi pubs'!$G$6:$G$370,'Suivi pubs'!$N$6:$N$370,Paramètres!$B$18) -> 1 | D15: =IF(N(C15)=0,"",B15/C15-1) -> 6 | F15: =IF(Catalogue!B14="","",Catalogue!B14) | G15: =IF(F15="","",SUMIFS(Ventes!$G$6:$G$505,Ventes!$F$6:$F$505,F15,Ventes!$T$6:$T$505,$B$4,Ventes!$M$6:$M$505,"Livrée et payée")) | H15: =IF(F15="","",SUMIFS(Ventes!$K$6:$K$505,Ventes!$F$6:$F$505,F15,Ventes!$T$6:$T$505,$B$4,Ventes!$M$6:$M$505,"Livrée et payée")) | I15: =IF(F15="","",SUMIFS(Ventes!$R$6:$R$505,Ventes!$F$6:$F$505,F15,Ventes!$T$6:$T$505,$B$4)) | J15: =IF(OR(F15="",N($B$7)=0),"",H15/$B$7)
A16: Coût par message (FCFA) | B16: =IF(N(B14)=0,0,B13/B14) -> 244.89796 | C16: =IF(N(C14)=0,0,C13/C14) -> 500 | D16: =IF(N(C16)=0,"",B16/C16-1) -> -0.51020408 | F16: =IF(Catalogue!B15="","",Catalogue!B15) | G16: =IF(F16="","",SUMIFS(Ventes!$G$6:$G$505,Ventes!$F$6:$F$505,F16,Ventes!$T$6:$T$505,$B$4,Ventes!$M$6:$M$505,"Livrée et payée")) | H16: =IF(F16="","",SUMIFS(Ventes!$K$6:$K$505,Ventes!$F$6:$F$505,F16,Ventes!$T$6:$T$505,$B$4,Ventes!$M$6:$M$505,"Livrée et payée")) | I16: =IF(F16="","",SUMIFS(Ventes!$R$6:$R$505,Ventes!$F$6:$F$505,F16,Ventes!$T$6:$T$505,$B$4)) | J16: =IF(OR(F16="",N($B$7)=0),"",H16/$B$7)
A17: Taux de conversion des pubs | B17: =IF(N(B14)=0,0,B15/B14) -> 0.14285714 | C17: =IF(N(C14)=0,0,C15/C14) -> 0.083333333 | D17: =(B17-C17)*100 -> 5.952381 | F17: =IF(Catalogue!B16="","",Catalogue!B16) | G17: =IF(F17="","",SUMIFS(Ventes!$G$6:$G$505,Ventes!$F$6:$F$505,F17,Ventes!$T$6:$T$505,$B$4,Ventes!$M$6:$M$505,"Livrée et payée")) | H17: =IF(F17="","",SUMIFS(Ventes!$K$6:$K$505,Ventes!$F$6:$F$505,F17,Ventes!$T$6:$T$505,$B$4,Ventes!$M$6:$M$505,"Livrée et payée")) | I17: =IF(F17="","",SUMIFS(Ventes!$R$6:$R$505,Ventes!$F$6:$F$505,F17,Ventes!$T$6:$T$505,$B$4)) | J17: =IF(OR(F17="",N($B$7)=0),"",H17/$B$7)
A18: Coût par vente en pub (FCFA) | B18: =IF(N(B15)=0,0,B13/B15) -> 1714.2857 | C18: =IF(N(C15)=0,0,C13/C15) -> 6000 | D18: =IF(N(C18)=0,"",B18/C18-1) -> -0.71428571 | F18: =IF(Catalogue!B17="","",Catalogue!B17) | G18: =IF(F18="","",SUMIFS(Ventes!$G$6:$G$505,Ventes!$F$6:$F$505,F18,Ventes!$T$6:$T$505,$B$4,Ventes!$M$6:$M$505,"Livrée et payée")) | H18: =IF(F18="","",SUMIFS(Ventes!$K$6:$K$505,Ventes!$F$6:$F$505,F18,Ventes!$T$6:$T$505,$B$4,Ventes!$M$6:$M$505,"Livrée et payée")) | I18: =IF(F18="","",SUMIFS(Ventes!$R$6:$R$505,Ventes!$F$6:$F$505,F18,Ventes!$T$6:$T$505,$B$4)) | J18: =IF(OR(F18="",N($B$7)=0),"",H18/$B$7)
A19: Marge brute (après produits et livraisons) | B19: =SUMIFS(Ventes!$R$6:$R$505,Ventes!$T$6:$T$505,$B$4) -> 69750 | C19: =SUMIFS(Ventes!$R$6:$R$505,Ventes!$T$6:$T$505,Paramètres!$B$18) -> 30950 | D19: =IF(N(C19)=0,"",B19/C19-1) -> 1.2536349 | F19: =IF(Catalogue!B18="","",Catalogue!B18) | G19: =IF(F19="","",SUMIFS(Ventes!$G$6:$G$505,Ventes!$F$6:$F$505,F19,Ventes!$T$6:$T$505,$B$4,Ventes!$M$6:$M$505,"Livrée et payée")) | H19: =IF(F19="","",SUMIFS(Ventes!$K$6:$K$505,Ventes!$F$6:$F$505,F19,Ventes!$T$6:$T$505,$B$4,Ventes!$M$6:$M$505,"Livrée et payée")) | I19: =IF(F19="","",SUMIFS(Ventes!$R$6:$R$505,Ventes!$F$6:$F$505,F19,Ventes!$T$6:$T$505,$B$4)) | J19: =IF(OR(F19="",N($B$7)=0),"",H19/$B$7)
A20: Autres dépenses (FCFA) | B20: =SUMIFS(Dépenses!$D$6:$D$205,Dépenses!$E$6:$E$205,$B$4) -> 12000 | C20: =SUMIFS(Dépenses!$D$6:$D$205,Dépenses!$E$6:$E$205,Paramètres!$B$18) -> 9000 | D20: =IF(N(C20)=0,"",B20/C20-1) -> 0.33333333 | F20: =IF(Catalogue!B19="","",Catalogue!B19) | G20: =IF(F20="","",SUMIFS(Ventes!$G$6:$G$505,Ventes!$F$6:$F$505,F20,Ventes!$T$6:$T$505,$B$4,Ventes!$M$6:$M$505,"Livrée et payée")) | H20: =IF(F20="","",SUMIFS(Ventes!$K$6:$K$505,Ventes!$F$6:$F$505,F20,Ventes!$T$6:$T$505,$B$4,Ventes!$M$6:$M$505,"Livrée et payée")) | I20: =IF(F20="","",SUMIFS(Ventes!$R$6:$R$505,Ventes!$F$6:$F$505,F20,Ventes!$T$6:$T$505,$B$4)) | J20: =IF(OR(F20="",N($B$7)=0),"",H20/$B$7)
A21: BÉNÉFICE NET (FCFA) | B21: =B19-B13-B20 -> 45750 | C21: =C19-C13-C20 -> 15950 | D21: =IF(N(C21)=0,"",B21/C21-1) -> 1.8683386 | F21: =IF(Catalogue!B20="","",Catalogue!B20) | G21: =IF(F21="","",SUMIFS(Ventes!$G$6:$G$505,Ventes!$F$6:$F$505,F21,Ventes!$T$6:$T$505,$B$4,Ventes!$M$6:$M$505,"Livrée et payée")) | H21: =IF(F21="","",SUMIFS(Ventes!$K$6:$K$505,Ventes!$F$6:$F$505,F21,Ventes!$T$6:$T$505,$B$4,Ventes!$M$6:$M$505,"Livrée et payée")) | I21: =IF(F21="","",SUMIFS(Ventes!$R$6:$R$505,Ventes!$F$6:$F$505,F21,Ventes!$T$6:$T$505,$B$4)) | J21: =IF(OR(F21="",N($B$7)=0),"",H21/$B$7)
A22: Marge nette sur le chiffre d’affaires | B22: =IF(N(B7)=0,0,B21/B7) -> 0.305 | C22: =IF(N(C7)=0,0,C21/C7) -> 0.24921875 | D22: =(B22-C22)*100 -> 5.578125 | F22: =IF(Catalogue!B21="","",Catalogue!B21) | G22: =IF(F22="","",SUMIFS(Ventes!$G$6:$G$505,Ventes!$F$6:$F$505,F22,Ventes!$T$6:$T$505,$B$4,Ventes!$M$6:$M$505,"Livrée et payée")) | H22: =IF(F22="","",SUMIFS(Ventes!$K$6:$K$505,Ventes!$F$6:$F$505,F22,Ventes!$T$6:$T$505,$B$4,Ventes!$M$6:$M$505,"Livrée et payée")) | I22: =IF(F22="","",SUMIFS(Ventes!$R$6:$R$505,Ventes!$F$6:$F$505,F22,Ventes!$T$6:$T$505,$B$4)) | J22: =IF(OR(F22="",N($B$7)=0),"",H22/$B$7)
A23: Ventes à de nouveaux clients | B23: =COUNTIFS(Ventes!$T$6:$T$505,$B$4,Ventes!$M$6:$M$505,"Livrée et payée",Ventes!$U$6:$U$505,"Nouveau") -> 2 | C23: =COUNTIFS(Ventes!$T$6:$T$505,Paramètres!$B$18,Ventes!$M$6:$M$505,"Livrée et payée",Ventes!$U$6:$U$505,"Nouveau") -> 5 | D23: =IF(N(C23)=0,"",B23/C23-1) -> -0.6 | F23: =IF(Catalogue!B22="","",Catalogue!B22) | G23: =IF(F23="","",SUMIFS(Ventes!$G$6:$G$505,Ventes!$F$6:$F$505,F23,Ventes!$T$6:$T$505,$B$4,Ventes!$M$6:$M$505,"Livrée et payée")) | H23: =IF(F23="","",SUMIFS(Ventes!$K$6:$K$505,Ventes!$F$6:$F$505,F23,Ventes!$T$6:$T$505,$B$4,Ventes!$M$6:$M$505,"Livrée et payée")) | I23: =IF(F23="","",SUMIFS(Ventes!$R$6:$R$505,Ventes!$F$6:$F$505,F23,Ventes!$T$6:$T$505,$B$4)) | J23: =IF(OR(F23="",N($B$7)=0),"",H23/$B$7)
A24: Ventes à des clients qui rachètent | B24: =COUNTIFS(Ventes!$T$6:$T$505,$B$4,Ventes!$M$6:$M$505,"Livrée et payée",Ventes!$U$6:$U$505,"Fidèle") -> 9 | C24: =COUNTIFS(Ventes!$T$6:$T$505,Paramètres!$B$18,Ventes!$M$6:$M$505,"Livrée et payée",Ventes!$U$6:$U$505,"Fidèle") -> 1 | D24: =IF(N(C24)=0,"",B24/C24-1) -> 8 | F24: =IF(Catalogue!B23="","",Catalogue!B23) | G24: =IF(F24="","",SUMIFS(Ventes!$G$6:$G$505,Ventes!$F$6:$F$505,F24,Ventes!$T$6:$T$505,$B$4,Ventes!$M$6:$M$505,"Livrée et payée")) | H24: =IF(F24="","",SUMIFS(Ventes!$K$6:$K$505,Ventes!$F$6:$F$505,F24,Ventes!$T$6:$T$505,$B$4,Ventes!$M$6:$M$505,"Livrée et payée")) | I24: =IF(F24="","",SUMIFS(Ventes!$R$6:$R$505,Ventes!$F$6:$F$505,F24,Ventes!$T$6:$T$505,$B$4)) | J24: =IF(OR(F24="",N($B$7)=0),"",H24/$B$7)
A25: Avis demandés après livraison | B25: =IF(N(B8)=0,0,COUNTIFS(Ventes!$T$6:$T$505,$B$4,Ventes!$M$6:$M$505,"Livrée et payée",Ventes!$S$6:$S$505,"Oui")/B8) -> 0.63636364 | C25: =IF(N(C8)=0,0,COUNTIFS(Ventes!$T$6:$T$505,Paramètres!$B$18,Ventes!$M$6:$M$505,"Livrée et payée",Ventes!$S$6:$S$505,"Oui")/C8) -> 0.66666667 | D25: =(B25-C25)*100 -> -3.030303 | F25: =IF(Catalogue!B24="","",Catalogue!B24) | G25: =IF(F25="","",SUMIFS(Ventes!$G$6:$G$505,Ventes!$F$6:$F$505,F25,Ventes!$T$6:$T$505,$B$4,Ventes!$M$6:$M$505,"Livrée et payée")) | H25: =IF(F25="","",SUMIFS(Ventes!$K$6:$K$505,Ventes!$F$6:$F$505,F25,Ventes!$T$6:$T$505,$B$4,Ventes!$M$6:$M$505,"Livrée et payée")) | I25: =IF(F25="","",SUMIFS(Ventes!$R$6:$R$505,Ventes!$F$6:$F$505,F25,Ventes!$T$6:$T$505,$B$4)) | J25: =IF(OR(F25="",N($B$7)=0),"",H25/$B$7)
F26: =IF(Catalogue!B25="","",Catalogue!B25) | G26: =IF(F26="","",SUMIFS(Ventes!$G$6:$G$505,Ventes!$F$6:$F$505,F26,Ventes!$T$6:$T$505,$B$4,Ventes!$M$6:$M$505,"Livrée et payée")) | H26: =IF(F26="","",SUMIFS(Ventes!$K$6:$K$505,Ventes!$F$6:$F$505,F26,Ventes!$T$6:$T$505,$B$4,Ventes!$M$6:$M$505,"Livrée et payée")) | I26: =IF(F26="","",SUMIFS(Ventes!$R$6:$R$505,Ventes!$F$6:$F$505,F26,Ventes!$T$6:$T$505,$B$4)) | J26: =IF(OR(F26="",N($B$7)=0),"",H26/$B$7)
A27: OBJECTIFS DU MOIS
A28: Chiffre d’affaires atteint | B28: =IF(N(Paramètres!B9)=0,"",B7/Paramètres!B9) -> 0.5 | F28: VENTES PAR SOURCE (CE MOIS)
A29: Nombre de ventes atteint | B29: =IF(N(Paramètres!B10)=0,"",B8/Paramètres!B10) -> 0.36666667 | F29: Source | G29: Ventes | H29: Chiffre d’affaires | I29: Part du CA
F30: =IF(Paramètres!H6="","",Paramètres!H6) -> Publicité | G30: =IF(F30="","",COUNTIFS(Ventes!$N$6:$N$505,F30,Ventes!$T$6:$T$505,$B$4,Ventes!$M$6:$M$505,"Livrée et payée")) -> 7 | H30: =IF(F30="","",SUMIFS(Ventes!$K$6:$K$505,Ventes!$N$6:$N$505,F30,Ventes!$T$6:$T$505,$B$4,Ventes!$M$6:$M$505,"Livrée et payée")) -> 86000 | I30: =IF(OR(F30="",N($B$7)=0),"",H30/$B$7) -> 0.57333333
A31: ALERTES | F31: =IF(Paramètres!H7="","",Paramètres!H7) -> Publication gratuite | G31: =IF(F31="","",COUNTIFS(Ventes!$N$6:$N$505,F31,Ventes!$T$6:$T$505,$B$4,Ventes!$M$6:$M$505,"Livrée et payée")) -> 0 | H31: =IF(F31="","",SUMIFS(Ventes!$K$6:$K$505,Ventes!$N$6:$N$505,F31,Ventes!$T$6:$T$505,$B$4,Ventes!$M$6:$M$505,"Livrée et payée")) -> 0 | I31: =IF(OR(F31="",N($B$7)=0),"",H31/$B$7) -> 0
A32: Produits à réapprovisionner | B32: =COUNTIF(Catalogue!$V$6:$V$55,"Réapprovisionner") -> 0 | F32: =IF(Paramètres!H8="","",Paramètres!H8) -> Groupe Facebook | G32: =IF(F32="","",COUNTIFS(Ventes!$N$6:$N$505,F32,Ventes!$T$6:$T$505,$B$4,Ventes!$M$6:$M$505,"Livrée et payée")) -> 0 | H32: =IF(F32="","",SUMIFS(Ventes!$K$6:$K$505,Ventes!$N$6:$N$505,F32,Ventes!$T$6:$T$505,$B$4,Ventes!$M$6:$M$505,"Livrée et payée")) -> 0 | I32: =IF(OR(F32="",N($B$7)=0),"",H32/$B$7) -> 0
A33: Produits vendus à perte ou à marge faible | B33: =COUNTIF(Catalogue!$P$6:$P$55,"Vente à perte")+COUNTIF(Catalogue!$P$6:$P$55,"Marge faible (< x2)") -> 0 | F33: =IF(Paramètres!H9="","",Paramètres!H9) -> Marketplace | G33: =IF(F33="","",COUNTIFS(Ventes!$N$6:$N$505,F33,Ventes!$T$6:$T$505,$B$4,Ventes!$M$6:$M$505,"Livrée et payée")) -> 0 | H33: =IF(F33="","",SUMIFS(Ventes!$K$6:$K$505,Ventes!$N$6:$N$505,F33,Ventes!$T$6:$T$505,$B$4,Ventes!$M$6:$M$505,"Livrée et payée")) -> 0 | I33: =IF(OR(F33="",N($B$7)=0),"",H33/$B$7) -> 0
A34: Pubs à couper | B34: =COUNTIF('Synthèse pubs'!$L$6:$L$35,"Couper") -> 2 | F34: =IF(Paramètres!H10="","",Paramètres!H10) -> Direct vidéo | G34: =IF(F34="","",COUNTIFS(Ventes!$N$6:$N$505,F34,Ventes!$T$6:$T$505,$B$4,Ventes!$M$6:$M$505,"Livrée et payée")) -> 1 | H34: =IF(F34="","",SUMIFS(Ventes!$K$6:$K$505,Ventes!$N$6:$N$505,F34,Ventes!$T$6:$T$505,$B$4,Ventes!$M$6:$M$505,"Livrée et payée")) -> 7500 | I34: =IF(OR(F34="",N($B$7)=0),"",H34/$B$7) -> 0.05
A35: Pubs à augmenter | B35: =COUNTIF('Synthèse pubs'!$L$6:$L$35,"Augmenter*") -> 1 | F35: =IF(Paramètres!H11="","",Paramètres!H11) -> Bouche-à-oreille | G35: =IF(F35="","",COUNTIFS(Ventes!$N$6:$N$505,F35,Ventes!$T$6:$T$505,$B$4,Ventes!$M$6:$M$505,"Livrée et payée")) -> 0 | H35: =IF(F35="","",SUMIFS(Ventes!$K$6:$K$505,Ventes!$N$6:$N$505,F35,Ventes!$T$6:$T$505,$B$4,Ventes!$M$6:$M$505,"Livrée et payée")) -> 0 | I35: =IF(OR(F35="",N($B$7)=0),"",H35/$B$7) -> 0
A36: Clients à relancer (plus de 60 jours) | B36: =COUNTIF(Clients!$I$6:$I$305,"À relancer") -> 0 | F36: =IF(Paramètres!H12="","",Paramètres!H12) -> Client fidèle | G36: =IF(F36="","",COUNTIFS(Ventes!$N$6:$N$505,F36,Ventes!$T$6:$T$505,$B$4,Ventes!$M$6:$M$505,"Livrée et payée")) -> 2 | H36: =IF(F36="","",SUMIFS(Ventes!$K$6:$K$505,Ventes!$N$6:$N$505,F36,Ventes!$T$6:$T$505,$B$4,Ventes!$M$6:$M$505,"Livrée et payée")) -> 46000 | I36: =IF(OR(F36="",N($B$7)=0),"",H36/$B$7) -> 0.30666667
A37: Commandes en attente | B37: =COUNTIF(Ventes!$M$6:$M$505,"En attente") -> 1 | F37: =IF(Paramètres!H13="","",Paramètres!H13) -> Statut WhatsApp | G37: =IF(F37="","",COUNTIFS(Ventes!$N$6:$N$505,F37,Ventes!$T$6:$T$505,$B$4,Ventes!$M$6:$M$505,"Livrée et payée")) -> 1 | H37: =IF(F37="","",SUMIFS(Ventes!$K$6:$K$505,Ventes!$N$6:$N$505,F37,Ventes!$T$6:$T$505,$B$4,Ventes!$M$6:$M$505,"Livrée et payée")) -> 10500 | I37: =IF(OR(F37="",N($B$7)=0),"",H37/$B$7) -> 0.07
F38: =IF(Paramètres!H14="","",Paramètres!H14) | G38: =IF(F38="","",COUNTIFS(Ventes!$N$6:$N$505,F38,Ventes!$T$6:$T$505,$B$4,Ventes!$M$6:$M$505,"Livrée et payée")) | H38: =IF(F38="","",SUMIFS(Ventes!$K$6:$K$505,Ventes!$N$6:$N$505,F38,Ventes!$T$6:$T$505,$B$4,Ventes!$M$6:$M$505,"Livrée et payée")) | I38: =IF(OR(F38="",N($B$7)=0),"",H38/$B$7)
F39: =IF(Paramètres!H15="","",Paramètres!H15) | G39: =IF(F39="","",COUNTIFS(Ventes!$N$6:$N$505,F39,Ventes!$T$6:$T$505,$B$4,Ventes!$M$6:$M$505,"Livrée et payée")) | H39: =IF(F39="","",SUMIFS(Ventes!$K$6:$K$505,Ventes!$N$6:$N$505,F39,Ventes!$T$6:$T$505,$B$4,Ventes!$M$6:$M$505,"Livrée et payée")) | I39: =IF(OR(F39="",N($B$7)=0),"",H39/$B$7)

Sheet Accueil
A1: Outil de pilotage · Vendre sur Facebook, gagner plus
A2: Suivi des ventes, des pubs, des produits et services, des clients et du bénéfice, en un seul fichier.
A3: Cellules jaunes : à remplir · cellules grises : calculées automatiquement (ne pas modifier)
B5: Campus des Bâtisseurs · Connecter • Accompagner • Bâtir
B7: Onglet | C7: À quoi il sert
B8: Paramètres | C8: Ton business, le mois suivi, tes objectifs, tes zones de livraison et les listes de choix. À remplir en premier.
B9: Catalogue | C9: Tes produits et services : coûts, prix, marge réelle, plafond de pub par vente, stock et alertes.
B10: Grille produit | C10: Note un produit avant de le lancer (6 critères du chapitre 2). 9 sur 12 ou plus : à tester.
B11: Calcul marge | C11: Simulateur : vrai bénéfice par vente, prix minimum, et calcul rapide d’une pub (coût par vente, décision).
B12: Suivi pubs | C12: Chaque soir : dépensé, messages, ventes de chaque pub. Coût par message, conversion, coût par vente calculés.
B13: Synthèse pubs | C13: Le bilan cumulé de chaque pub et la décision : augmenter, améliorer ou couper (chapitre 8).
B14: Ventes | C14: Le journal de toutes tes commandes : client, produit, paiement, statut, livraison, marge.
B15: Clients | C15: Ta liste de clients : nombre d’achats, montant total, dernière commande, segment (fidèle, VIP, à relancer).
B16: Dépenses | C16: Les autres frais du business : emballages en gros, transport, internet, livreur, matériel.
B17: Tableau de bord | C17: L’aperçu clair du mois : chiffre d’affaires, bénéfice net, pub, conversion, top produits, alertes.
B18: Bilan annuel | C18: Les 12 mois de l’année côte à côte, avec graphique.
... B20: Page pro | C20: La checklist « page pro » en 20 points, avec ton score.
B22: Mode d’emploi en 5 étapes
B23: 1. Remplis Paramètres (année, mois suivi, objectifs, zones de livraison).
B24: 2. Ajoute tes produits et services dans Catalogue. Vérifie que chaque marge est saine.
B25: 3. Chaque soir, note tes pubs dans Suivi pubs et tes commandes dans Ventes.
B26: 4. Une fois par semaine, regarde Synthèse pubs : augmente, améliore ou coupe chaque pub.
B27: 5. En fin de mois, ouvre Tableau de bord, puis Bilan annuel : tes chiffres décident, pas tes émotions.
B29: Règle de comptage : seules les commandes au statut « Livrée et payée » comptent dans le chiffre d’affaires.
B30: Une commande « Annulée » avec une livraison payée par toi est comptée comme une perte (le livreur a été payé pour rien).
B31: Pour un service, indique ton coût de revient (matériel, déplacement, sous-traitance) et choisis « Service » : le stock est ignoré.
B33: campusdesbatisseurs.com · infos@campusdesbatisseurs.com · +221 76 760 22 22 · @campusdesbatisseurs
B35: FICHIER D’EXEMPLE : les données sont fictives (boutique de pagnes de Fatou). Utilise le fichier vierge pour ton business.

Sheet Paramètres
A1: Paramètres
A2: À remplir en premier. Les listes alimentent les menus déroulants des autres onglets.
A3: Cellules jaunes : à remplir · cellules grises : calculées automatiquement (ne pas modifier)
A5: Paramètre | B5: Valeur | D5: Modes de paiement | F5: Statuts de commande | H5: Sources de la vente | J5: Zones de livraison | K5: Tarif livreur (FCFA) | M5: Catégories de dépenses | O5: Types
A6: Nom du business | B6: Pagnes de Fatou | D6: Wave | F6: En attente | H6: Publicité | J6: Dakar Plateau | K6: 1000 | M6: Emballages en gros | O6: Produit
A7: Année suivie | B7: 2026 | D7: Orange Money | F7: Livrée et payée | H7: Publication gratuite | J7: Dakar banlieue | K7: 1500 | M7: Transport / achats | O7: Service
A8: Mois suivi (1 à 12) | B8: 10 | D8: Free Money | F8: Annulée | H8: Groupe Facebook | J8: Pikine / Guédiawaye | K8: 2000 | M8: Internet et crédit
A9: Objectif de chiffre d’affaires mensuel (FCFA) | B9: 300000 | D9: Espèces à la livraison | F9: Retournée | H9: Marketplace | J9: Rufisque | K9: 2500 | M9: Livreur (forfait)
A10: Objectif de nombre de ventes par mois | B10: 30 | D10: Acompte + solde | H10: Direct vidéo | J10: Thiès | K10: 3000 | M10: Matériel
A11: Seuil « augmenter » : coût par vente < marge × | B11: 0.33333333 | D11: Virement bancaire | H11: Bouche-à-oreille | J11: Autres régions | K11: 3500 | M11: Photos / vidéos
A12: Jours minimum avant de décider (pub) | B12: 3 | H12: Client fidèle | M12: Formation
A13: Repère de conversion faible (messages → ventes) | B13: 0.1 | H13: Statut WhatsApp | M13: Autre
A15: Le seuil 1/3 et les 3 jours viennent de la règle de décision du chapitre 8. Le repère de 10 % de conversion est indicatif.
A17: Mois suivi (calculé) | B17: =DATE(B7,B8,1) -> 46296
A18: Mois précédent (calculé) | B18: =DATE(YEAR(B17),MONTH(B17)-1,1) -> 46266

Sheet Catalogue
A1: Catalogue des produits et services
A2: Coût total avant pub = achat + emballage + livraison payée par toi + frais. Marge avant pub = ton plafond de dépense pub par vente (chapitre 8).
A3: Cellules jaunes : à remplir · cellules grises : calculées automatiquement (ne pas modifier)
A5: Réf. | B5: Nom du produit ou service | C5: Type | D5: Catégorie | E5: Coût d’achat / de revient | F5: Emballage | G5: Livraison payée par toi | H5: Frais divers | I5: Prix de vente | J5: Coût total avant pub | K5: Marge avant pub | L5: Taux de marge | M5: Coef. prix / coût | N5: Plafond pub par vente | O5: Seuil « augmenter » | P5: Verdict prix | Q5: Stock initial | R5: Réappro. | S5: Vendus | T5: Stock restant | U5: Stock mini | V5: Alerte stock
A6: P01 | B6: Pagne wax 6 yards | C6: Produit | D6: Mode | E6: 4000 | F6: 200 | G6: 1500 | H6: 100 | I6: 10000 | J6: =IF(I6="","",N(E6)+N(F6)+N(G6)+N(H6)) -> 5800 | K6: =IF(I6="","",I6-J6) -> 4200 | L6: =IF(OR(I6="",N(I6)=0),"",K6/I6) -> 0.42 | M6: =IF(OR(I6="",N(E6)=0),"",I6/E6) -> 2.5 | N6: =IF(I6="","",MAX(0,K6)) -> 4200 | O6: =IF(I6="","",MAX(0,K6*Paramètres!$B$11)) -> 1400 | P6: =IF(I6="","",IF(K6<=0,"Vente à perte",IF(AND(M6<>"",M6<2),"Marge faible (< x2)","Marge saine"))) -> Marge saine | Q6: 30 | R6: 20 | S6: =IF(B6="","",SUMIFS(Ventes!$G$6:$G$505,Ventes!$F$6:$F$505,B6,Ventes!$M$6:$M$505,"Livrée et payée")) -> 10 | T6: =IF(OR(B6="",C6="Service"),"",N(Q6)+N(R6)-N(S6)) -> 40 | U6: 5 | V6: =IF(OR(B6="",C6="Service",Q6=""),"",IF(T6<=N(U6),"Réapprovisionner","OK")) -> OK
A7: P02 | B7: Foulard assorti | C7: Produit | D7: Accessoires | E7: 1200 | F7: 100 | G7: 0 | H7: 50 | I7: 3500 | J7: =IF(I7="","",N(E7)+N(F7)+N(G7)+N(H7)) -> 1350 | K7: =IF(I7="","",I7-J7) -> 2150 | L7: =IF(OR(I7="",N(I7)=0),"",K7/I7) -> 0.61428571 | M7: =IF(OR(I7="",N(E7)=0),"",I7/E7) -> 2.9166667 | N7: =IF(I7="","",MAX(0,K7)) -> 2150 | O7: =IF(I7="","",MAX(0,K7*Paramètres!$B$11)) -> 716.66667 | P7: =IF(I7="","",IF(K7<=0,"Vente à perte",IF(AND(M7<>"",M7<2),"Marge faible (< x2)","Marge saine"))) -> Marge saine | Q7: 40 | R7: 0 | S7: =IF(B7="","",SUMIFS(Ventes!$G$6:$G$505,Ventes!$F$6:$F$505,B7,Ventes!$M$6:$M$505,"Livrée et payée")) -> 6 | T7: =IF(OR(B7="",C7="Service"),"",N(Q7)+N(R7)-N(S7)) -> 34 | U7: 10 | V7: =IF(OR(B7="",C7="Service",Q7=""),"",IF(T7<=N(U7),"Réapprovisionner","OK")) -> OK
A8: P03 | B8: Pack 3 pagnes | C8: Produit | D8: Mode | E8: 12000 | F8: 300 | G8: 1500 | H8: 100 | I8: 27000 | J8: =IF(I8="","",N(E8)+N(F8)+N(G8)+N(H8)) -> 13900 | K8: =IF(I8="","",I8-J8) -> 13100 | L8: =IF(OR(I8="",N(I8)=0),"",K8/I8) -> 0.48518519 | M8: =IF(OR(I8="",N(E8)=0),"",I8/E8) -> 2.25 | N8: =IF(I8="","",MAX(0,K8)) -> 13100 | O8: =IF(I8="","",MAX(0,K8*Paramètres!$B$11)) -> 4366.6667 | P8: =IF(I8="","",IF(K8<=0,"Vente à perte",IF(AND(M8<>"",M8<2),"Marge faible (< x2)","Marge saine"))) -> Marge saine | Q8: 10 | R8: 0 | S8: =IF(B8="","",SUMIFS(Ventes!$G$6:$G$505,Ventes!$F$6:$F$505,B8,Ventes!$M$6:$M$505,"Livrée et payée")) -> 3 | T8: =IF(OR(B8="",C8="Service"),"",N(Q8)+N(R8)-N(S8)) -> 7 | U8: 3 | V8: =IF(OR(B8="",C8="Service",Q8=""),"",IF(T8<=N(U8),"Réapprovisionner","OK")) -> OK
A9: P04 | B9: Conseil style à domicile | C9: Service | D9: Services | E9: 2000 | F9: 0 | G9: 0 | H9: 0 | I9: 7500 | J9: =IF(I9="","",N(E9)+N(F9)+N(G9)+N(H9)) -> 2000 | K9: =IF(I9="","",I9-J9) -> 5500 | L9: =IF(OR(I9="",N(I9)=0),"",K9/I9) -> 0.73333333 | M9: =IF(OR(I9="",N(E9)=0),"",I9/E9) -> 3.75 | N9: =IF(I9="","",MAX(0,K9)) -> 5500 | O9: =IF(I9="","",MAX(0,K9*Paramètres!$B$11)) -> 1833.3333 | P9: =IF(I9="","",IF(K9<=0,"Vente à perte",IF(AND(M9<>"",M9<2),"Marge faible (< x2)","Marge saine"))) -> Marge saine | S9: =IF(B9="","",SUMIFS(Ventes!$G$6:$G$505,Ventes!$F$6:$F$505,B9,Ventes!$M$6:$M$505,"Livrée et payée")) -> 2 | T9: =IF(OR(B9="",C9="Service"),"",N(Q9)+N(R9)-N(S9)) | V9: =IF(OR(B9="",C9="Service",Q9=""),"",IF(T9<=N(U9),"Réapprovisionner","OK"))
J10: =IF(I10="","",N(E10)+N(F10)+N(G10)+N(H10)) | K10: =IF(I10="","",I10-J10) | L10: =IF(OR(I10="",N(I10)=0),"",K10/I10) | M10: =IF(OR(I10="",N(E10)=0),"",I10/E10) | N10: =IF(I10="","",MAX(0,K10)) | O10: =IF(I10="","",MAX(0,K10*Paramètres!$B$11)) | P10: =IF(I10="","",IF(K10<=0,"Vente à perte",IF(AND(M10<>"",M10<2),"Marge faible (< x2)","Marge saine"))) | S10: =IF(B10="","",SUMIFS(Ventes!$G$6:$G$505,Ventes!$F$6:$F$505,B10,Ventes!$M$6:$M$505,"Livrée et payée")) | T10: =IF(OR(B10="",C10="Service"),"",N(Q10)+N(R10)-N(S10)) | V10: =IF(OR(B10="",C10="Service",Q10=""),"",IF(T10<=N(U10),"Réapprovisionner","OK"))
J11: =IF(I11="","",N(E11)+N(F11)+N(G11)+N(H11)) | K11: =IF(I11="","",I11-J11) | L11: =IF(OR(I11="",N(I11)=0),"",K11/I11) | M11: =IF(OR(I11="",N(E11)=0),"",I11/E11) | N11: =IF(I11="","",MAX(0,K11)) | O11: =IF(I11="","",MAX(0,K11*Paramètres!$B$11)) | P11: =IF(I11="","",IF(K11<=0,"Vente à perte",IF(AND(M11<>"",M11<2),"Marge faible (< x2)","Marge saine"))) | S11: =IF(B11="","",SUMIFS(Ventes!$G$6:$G$505,Ventes!$F$6:$F$505,B11,Ventes!$M$6:$M$505,"Livrée et payée")) | T11: =IF(OR(B11="",C11="Service"),"",N(Q11)+N(R11)-N(S11)) | V11: =IF(OR(B11="",C11="Service",Q11=""),"",IF(T11<=N(U11),"Réapprovisionner","OK"))
J12: =IF(I12="","",N(E12)+N(F12)+N(G12)+N(H12)) | K12: =IF(I12="","",I12-J12) | L12: =IF(OR(I12="",N(I12)=0),"",K12/I12) | M12: =IF(OR(I12="",N(E12)=0),"",I12/E12) | N12: =IF(I12="","",MAX(0,K12)) | O12: =IF(I12="","",MAX(0,K12*Paramètres!$B$11)) | P12: =IF(I12="","",IF(K12<=0,"Vente à perte",IF(AND(M12<>"",M12<2),"Marge faible (< x2)","Marge saine"))) | S12: =IF(B12="","",SUMIFS(Ventes!$G$6:$G$505,Ventes!$F$6:$F$505,B12,Ventes!$M$6:$M$505,"Livrée et payée")) | T12: =IF(OR(B12="",C12="Service"),"",N(Q12)+N(R12)-N(S12)) | V12: =IF(OR(B12="",C12="Service",Q12=""),"",IF(T12<=N(U12),"Réapprovisionner","OK"))
J13: =IF(I13="","",N(E13)+N(F13)+N(G13)+N(H13)) | K13: =IF(I13="","",I13-J13) | L13: =IF(OR(I13="",N(I13)=0),"",K13/I13) | M13: =IF(OR(I13="",N(E13)=0),"",I13/E13) | N13: =IF(I13="","",MAX(0,K13)) | O13: =IF(I13="","",MAX(0,K13*Paramètres!$B$11)) | P13: =IF(I13="","",IF(K13<=0,"Vente à perte",IF(AND(M13<>"",M13<2),"Marge faible (< x2)","Marge saine"))) | S13: =IF(B13="","",SUMIFS(Ventes!$G$6:$G$505,Ventes!$F$6:$F$505,B13,Ventes!$M$6:$M$505,"Livrée et payée")) | T13: =IF(OR(B13="",C13="Service"),"",N(Q13)+N(R13)-N(S13)) | V13: =IF(OR(B13="",C13="Service",Q13=""),"",IF(T13<=N(U13),"Réapprovisionner","OK"))
J14: =IF(I14="","",N(E14)+N(F14)+N(G14)+N(H14)) | K14: =IF(I14="","",I14-J14) | L14: =IF(OR(I14="",N(I14)=0),"",K14/I14) | M14: =IF(OR(I14="",N(E14)=0),"",I14/E14) | N14: =IF(I14="","",MAX(0,K14)) | O14: =IF(I14="","",MAX(0,K14*Paramètres!$B$11)) | P14: =IF(I14="","",IF(K14<=0,"Vente à perte",IF(AND(M14<>"",M14<2),"Marge faible (< x2)","Marge saine"))) | S14: =IF(B14="","",SUMIFS(Ventes!$G$6:$G$505,Ventes!$F$6:$F$505,B14,Ventes!$M$6:$M$505,"Livrée et payée")) | T14: =IF(OR(B14="",C14="Service"),"",N(Q14)+N(R14)-N(S14)) | V14: =IF(OR(B14="",C14="Service",Q14=""),"",IF(T14<=N(U14),"Réapprovisionner","OK"))
J15: =IF(I15="","",N(E15)+N(F15)+N(G15)+N(H15)) | K15: =IF(I15="","",I15-J15) | L15: =IF(OR(I15="",N(I15)=0),"",K15/I15) | M15: =IF(OR(I15="",N(E15)=0),"",I15/E15) | N15: =IF(I15="","",MAX(0,K15)) | O15: =IF(I15="","",MAX(0,K15*Paramètres!$B$11)) | P15: =IF(I15="","",IF(K15<=0,"Vente à perte",IF(AND(M15<>"",M15<2),"Marge faible (< x2)","Marge saine"))) | S15: =IF(B15="","",SUMIFS(Ventes!$G$6:$G$505,Ventes!$F$6:$F$505,B15,Ventes!$M$6:$M$505,"Livrée et payée")) | T15: =IF(OR(B15="",C15="Service"),"",N(Q15)+N(R15)-N(S15)) | V15: =IF(OR(B15="",C15="Service",Q15=""),"",IF(T15<=N(U15),"Réapprovisionner","OK"))
J16: =IF(I16="","",N(E16)+N(F16)+N(G16)+N(H16)) | K16: =IF(I16="","",I16-J16) | L16: =IF(OR(I16="",N(I16)=0),"",K16/I16) | M16: =IF(OR(I16="",N(E16)=0),"",I16/E16) | N16: =IF(I16="","",MAX(0,K16)) | O16: =IF(I16="","",MAX(0,K16*Paramètres!$B$11)) | P16: =IF(I16="","",IF(K16<=0,"Vente à perte",IF(AND(M16<>"",M16<2),"Marge faible (< x2)","Marge saine"))) | S16: =IF(B16="","",SUMIFS(Ventes!$G$6:$G$505,Ventes!$F$6:$F$505,B16,Ventes!$M$6:$M$505,"Livrée et payée")) | T16: =IF(OR(B16="",C16="Service"),"",N(Q16)+N(R16)-N(S16)) | V16: =IF(OR(B16="",C16="Service",Q16=""),"",IF(T16<=N(U16),"Réapprovisionner","OK"))
J17: =IF(I17="","",N(E17)+N(F17)+N(G17)+N(H17)) | K17: =IF(I17="","",I17-J17) | L17: =IF(OR(I17="",N(I17)=0),"",K17/I17) | M17: =IF(OR(I17="",N(E17)=0),"",I17/E17) | N17: =IF(I17="","",MAX(0,K17)) | O17: =IF(I17="","",MAX(0,K17*Paramètres!$B$11)) | P17: =IF(I17="","",IF(K17<=0,"Vente à perte",IF(AND(M17<>"",M17<2),"Marge faible (< x2)","Marge saine"))) | S17: =IF(B17="","",SUMIFS(Ventes!$G$6:$G$505,Ventes!$F$6:$F$505,B17,Ventes!$M$6:$M$505,"Livrée et payée")) | T17: =IF(OR(B17="",C17="Service"),"",N(Q17)+N(R17)-N(S17)) | V17: =IF(OR(B17="",C17="Service",Q17=""),"",IF(T17<=N(U17),"Réapprovisionner","OK"))
J18: =IF(I18="","",N(E18)+N(F18)+N(G18)+N(H18)) | K18: =IF(I18="","",I18-J18) | L18: =IF(OR(I18="",N(I18)=0),"",K18/I18) | M18: =IF(OR(I18="",N(E18)=0),"",I18/E18) | N18: =IF(I18="","",MAX(0,K18)) | O18: =IF(I18="","",MAX(0,K18*Paramètres!$B$11)) | P18: =IF(I18="","",IF(K18<=0,"Vente à perte",IF(AND(M18<>"",M18<2),"Marge faible (< x2)","Marge saine"))) | S18: =IF(B18="","",SUMIFS(Ventes!$G$6:$G$505,Ventes!$F$6:$F$505,B18,Ventes!$M$6:$M$505,"Livrée et payée")) | T18: =IF(OR(B18="",C18="Service"),"",N(Q18)+N(R18)-N(S18)) | V18: =IF(OR(B18="",C18="Service",Q18=""),"",IF(T18<=N(U18),"Réapprovisionner","OK"))
J19: =IF(I19="","",N(E19)+N(F19)+N(G19)+N(H19)) | K19: =IF(I19="","",I19-J19) | L19: =IF(OR(I19="",N(I19)=0),"",K19/I19) | M19: =IF(OR(I19="",N(E19)=0),"",I19/E19) | N19: =IF(I19="","",MAX(0,K19)) | O19: =IF(I19="","",MAX(0,K19*Paramètres!$B$11)) | P19: =IF(I19="","",IF(K19<=0,"Vente à perte",IF(AND(M19<>"",M19<2),"Marge faible (< x2)","Marge saine"))) | S19: =IF(B19="","",SUMIFS(Ventes!$G$6:$G$505,Ventes!$F$6:$F$505,B19,Ventes!$M$6:$M$505,"Livrée et payée")) | T19: =IF(OR(B19="",C19="Service"),"",N(Q19)+N(R19)-N(S19)) | V19: =IF(OR(B19="",C19="Service",Q19=""),"",IF(T19<=N(U19),"Réapprovisionner","OK"))
J20: =IF(I20="","",N(E20)+N(F20)+N(G20)+N(H20)) | K20: =IF(I20="","",I20-J20) | L20: =IF(OR(I20="",N(I20)=0),"",K20/I20) | M20: =IF(OR(I20="",N(E20)=0),"",I20/E20) | N20: =IF(I20="","",MAX(0,K20)) | O20: =IF(I20="","",MAX(0,K20*Paramètres!$B$11)) | P20: =IF(I20="","",IF(K20<=0,"Vente à perte",IF(AND(M20<>"",M20<2),"Marge faible (< x2)","Marge saine"))) | S20: =IF(B20="","",SUMIFS(Ventes!$G$6:$G$505,Ventes!$F$6:$F$505,B20,Ventes!$M$6:$M$505,"Livrée et payée")) | T20: =IF(OR(B20="",C20="Service"),"",N(Q20)+N(R20)-N(S20)) | V20: =IF(OR(B20="",C20="Service",Q20=""),"",IF(T20<=N(U20),"Réapprovisionner","OK"))
J21: =IF(I21="","",N(E21)+N(F21)+N(G21)+N(H21)) | K21: =IF(I21="","",I21-J21) | L21: =IF(OR(I21="",N(I21)=0),"",K21/I21) | M21: =IF(OR(I21="",N(E21)=0),"",I21/E21) | N21: =IF(I21="","",MAX(0,K21)) | O21: =IF(I21="","",MAX(0,K21*Paramètres!$B$11)) | P21: =IF(I21="","",IF(K21<=0,"Vente à perte",IF(AND(M21<>"",M21<2),"Marge faible (< x2)","Marge saine"))) | S21: =IF(B21="","",SUMIFS(Ventes!$G$6:$G$505,Ventes!$F$6:$F$505,B21,Ventes!$M$6:$M$505,"Livrée et payée")) | T21: =IF(OR(B21="",C21="Service"),"",N(Q21)+N(R21)-N(S21)) | V21: =IF(OR(B21="",C21="Service",Q21=""),"",IF(T21<=N(U21),"Réapprovisionner","OK"))
... J55: =IF(I55="","",N(E55)+N(F55)+N(G55)+N(H55)) | K55: =IF(I55="","",I55-J55) | L55: =IF(OR(I55="",N(I55)=0),"",K55/I55) | M55: =IF(OR(I55="",N(E55)=0),"",I55/E55) | N55: =IF(I55="","",MAX(0,K55)) | O55: =IF(I55="","",MAX(0,K55*Paramètres!$B$11)) | P55: =IF(I55="","",IF(K55<=0,"Vente à perte",IF(AND(M55<>"",M55<2),"Marge faible (< x2)","Marge saine"))) | S55: =IF(B55="","",SUMIFS(Ventes!$G$6:$G$505,Ventes!$F$6:$F$505,B55,Ventes!$M$6:$M$505,"Livrée et payée")) | T55: =IF(OR(B55="",C55="Service"),"",N(Q55)+N(R55)-N(S55)) | V55: =IF(OR(B55="",C55="Service",Q55=""),"",IF(T55<=N(U55),"Réapprovisionner","OK"))

Sheet Grille produit
A1: Grille produit : ce produit va-t-il se vendre ?
A2: Note chaque critère de 0 à 2. Garde les produits qui font 9 ou plus sur 12, puis fais une publication test (chapitre 2).
A3: Cellules jaunes : à remplir · cellules grises : calculées automatiquement (ne pas modifier)
A5: Produit envisagé | B5: Règle un problème ou un désir fort | C5: Marge d’au moins x2 | D5: Facile à livrer | E5: Se montre bien en vidéo | F5: Pas disponible partout au même prix | G5: Donne envie de racheter | H5: Total / 12 | I5: Décision | J5: Messages reçus (publication test) | K5: Verdict du test
A6: Pagne wax 6 yards | B6: 2 | C6: 2 | D6: 2 | E6: 2 | F6: 1 | G6: 2 | H6: =IF(A6="","",SUM(B6:G6)) -> 11 | I6: =IF(A6="","",IF(H6>=9,"À tester",IF(H6>=7,"À retravailler","Écarter"))) -> À tester | J6: 12 | K6: =IF(OR(A6="",J6=""),"",IF(J6>=10,"Commander un petit stock","Changer d’angle, de photo ou de produit")) -> Commander un petit stock
A7: Montre connectée | B7: 1 | C7: 1 | D7: 2 | E7: 2 | F7: 0 | G7: 0 | H7: =IF(A7="","",SUM(B7:G7)) -> 6 | I7: =IF(A7="","",IF(H7>=9,"À tester",IF(H7>=7,"À retravailler","Écarter"))) -> Écarter | J7: 3 | K7: =IF(OR(A7="",J7=""),"",IF(J7>=10,"Commander un petit stock","Changer d’angle, de photo ou de produit")) -> Changer d’angle, de photo ou de produit
H8: =IF(A8="","",SUM(B8:G8)) | I8: =IF(A8="","",IF(H8>=9,"À tester",IF(H8>=7,"À retravailler","Écarter"))) | K8: =IF(OR(A8="",J8=""),"",IF(J8>=10,"Commander un petit stock","Changer d’angle, de photo ou de produit"))
H9: =IF(A9="","",SUM(B9:G9)) | I9: =IF(A9="","",IF(H9>=9,"À tester",IF(H9>=7,"À retravailler","Écarter"))) | K9: =IF(OR(A9="",J9=""),"",IF(J9>=10,"Commander un petit stock","Changer d’angle, de photo ou de produit"))
H10: =IF(A10="","",SUM(B10:G10)) | I10: =IF(A10="","",IF(H10>=9,"À tester",IF(H10>=7,"À retravailler","Écarter"))) | K10: =IF(OR(A10="",J10=""),"",IF(J10>=10,"Commander un petit stock","Changer d’angle, de photo ou de produit"))
H11: =IF(A11="","",SUM(B11:G11)) | I11: =IF(A11="","",IF(H11>=9,"À tester",IF(H11>=7,"À retravailler","Écarter"))) | K11: =IF(OR(A11="",J11=""),"",IF(J11>=10,"Commander un petit stock","Changer d’angle, de photo ou de produit"))
H12: =IF(A12="","",SUM(B12:G12)) | I12: =IF(A12="","",IF(H12>=9,"À tester",IF(H12>=7,"À retravailler","Écarter"))) | K12: =IF(OR(A12="",J12=""),"",IF(J12>=10,"Commander un petit stock","Changer d’angle, de photo ou de produit"))
H13: =IF(A13="","",SUM(B13:G13)) | I13: =IF(A13="","",IF(H13>=9,"À tester",IF(H13>=7,"À retravailler","Écarter"))) | K13: =IF(OR(A13="",J13=""),"",IF(J13>=10,"Commander un petit stock","Changer d’angle, de photo ou de produit"))
H14: =IF(A14="","",SUM(B14:G14)) | I14: =IF(A14="","",IF(H14>=9,"À tester",IF(H14>=7,"À retravailler","Écarter"))) | K14: =IF(OR(A14="",J14=""),"",IF(J14>=10,"Commander un petit stock","Changer d’angle, de photo ou de produit"))
H15: =IF(A15="","",SUM(B15:G15)) | I15: =IF(A15="","",IF(H15>=9,"À tester",IF(H15>=7,"À retravailler","Écarter"))) | K15: =IF(OR(A15="",J15=""),"",IF(J15>=10,"Commander un petit stock","Changer d’angle, de photo ou de produit"))
H16: =IF(A16="","",SUM(B16:G16)) | I16: =IF(A16="","",IF(H16>=9,"À tester",IF(H16>=7,"À retravailler","Écarter"))) | K16: =IF(OR(A16="",J16=""),"",IF(J16>=10,"Commander un petit stock","Changer d’angle, de photo ou de produit"))
H17: =IF(A17="","",SUM(B17:G17)) | I17: =IF(A17="","",IF(H17>=9,"À tester",IF(H17>=7,"À retravailler","Écarter"))) | K17: =IF(OR(A17="",J17=""),"",IF(J17>=10,"Commander un petit stock","Changer d’angle, de photo ou de produit"))
H18: =IF(A18="","",SUM(B18:G18)) | I18: =IF(A18="","",IF(H18>=9,"À tester",IF(H18>=7,"À retravailler","Écarter"))) | K18: =IF(OR(A18="",J18=""),"",IF(J18>=10,"Commander un petit stock","Changer d’angle, de photo ou de produit"))
H19: =IF(A19="","",SUM(B19:G19)) | I19: =IF(A19="","",IF(H19>=9,"À tester",IF(H19>=7,"À retravailler","Écarter"))) | K19: =IF(OR(A19="",J19=""),"",IF(J19>=10,"Commander un petit stock","Changer d’angle, de photo ou de produit"))
H20: =IF(A20="","",SUM(B20:G20)) | I20: =IF(A20="","",IF(H20>=9,"À tester",IF(H20>=7,"À retravailler","Écarter"))) | K20: =IF(OR(A20="",J20=""),"",IF(J20>=10,"Commander un petit stock","Changer d’angle, de photo ou de produit"))
A22: Règle du livre : une publication test qui génère au moins 10 messages sérieux justifie un petit stock. Sinon, change d’angle, de photo ou de produit.

Sheet Calcul marge
A1: Simulateur : vraie marge et rentabilité d’une pub
A2: Prérempli avec l’exemple du livre : remplace les cellules jaunes par tes chiffres.
A3: Cellules jaunes : à remplir · cellules grises : calculées automatiquement (ne pas modifier)
A5: 1. LE VRAI BÉNÉFICE PAR VENTE | D5: 2. CETTE PUB EST-ELLE RENTABLE ?
A6: Prix d’achat du produit (ou coût de revient du service) | B6: 4000 | D6: Budget dépensé (FCFA) | E6: 9000
A7: Emballage | B7: 200 | D7: Messages reçus | E7: 36
A8: Livraison payée par toi (si offerte) | B8: 1500 | D8: Ventes conclues | E8: 9
A9: Coût de pub moyen par vente | B9: 1000 | D9: Marge avant pub du produit | E9: =B14 -> 4200
A10: Frais de transfert ou divers | B10: 100 | D10: Coût par message | E10: =IF(E7=0,0,E6/E7) -> 250
A11: Prix de vente | B11: 10000 | D11: Taux de conversion | E11: =IF(E7=0,0,E8/E7) -> 0.25
A12: Coût total par vente | B12: =B6+B7+B8+B9+B10 -> 6800 | D12: Coût par vente | E12: =IF(E8=0,0,E6/E8) -> 1000
A13: Bénéfice réel par vente | B13: =B11-B12 -> 3200 | D13: Bénéfice par vente après pub | E13: =IF(E8=0,0,E9-E12) -> 3200
A14: Marge avant pub (plafond de pub par vente) | B14: =B11-(B6+B7+B8+B10) -> 4200 | D14: Bénéfice total de la pub | E14: =E8*E9-E6 -> 28800
A15: Seuil « augmenter » (coût par vente maximum) | B15: =B14*Paramètres!$B$11 -> 1400 | D15: Décision | E15: =IF(E8=0,IF(E6>=E9,"Couper","Attendre ou améliorer"),IF(E12<E9*Paramètres!$B$11,"Augmenter le budget de 20 à 30 %",IF(E12<=E9,"Améliorer : accroche, vidéo, réponses","Couper : change d’angle ou de produit"))) -> Augmenter le budget de 20 à 30 %
A16: Taux de bénéfice réel | B16: =IF(B11=0,0,B13/B11) -> 0.32
A17: Prix minimum pour un coefficient x2 | B17: =2*B6 -> 8000
A18: Prix minimum pour un coefficient x3 | B18: =3*B6 -> 12000
A19: Verdict | B19: =IF(B13<=0,"Tu perds de l’argent : revois prix ou coûts",IF(B11<2*B6,"Marge faible : vise au moins x2","Prix sain")) -> Prix sain
A21: Exemple du livre : prix 10 000, coût total 6 800, bénéfice réel 3 200 FCFA ; pub : 9 000 FCFA, 36 messages, 9 ventes → 1 000 FCFA par vente, on augmente.

Sheet Suivi pubs
A1: Suivi quotidien des pubs
A2: Remplis chaque soir. Les ventes, c’est toi qui les notes : Facebook ne sait pas qui a payé sur WhatsApp.
A3: Cellules jaunes : à remplir · cellules grises : calculées automatiquement (ne pas modifier)
A5: Date | B5: Nom de la pub | C5: Produit / service | D5: Version | E5: Dépensé (FCFA) | F5: Messages | G5: Ventes | H5: Coût par message | I5: Taux de conversion | J5: Coût par vente | K5: Marge avant pub | L5: Bénéfice après pub | M5: Lecture du jour | N5: Mois
A6: 46301 | B6: Pub A · le problème | C6: Pagne wax 6 yards | D6: A | E6: 1500 | F6: 7 | G6: 1 | H6: =IF(N(F6)>0,E6/F6,"") -> 214.28571 | I6: =IF(N(F6)>0,G6/F6,"") -> 0.14285714 | J6: =IF(N(G6)>0,E6/G6,"") -> 1500 | K6: =IF(C6="","",IFERROR(INDEX(Catalogue!$K$6:$K$55,MATCH(C6,Catalogue!$B$6:$B$55,0)),"")) -> 4200 | L6: =IF(OR(E6="",K6=""),"",N(G6)*K6-E6) -> 2700 | M6: =IF(OR(E6="",K6=""),"",IF(N(G6)=0,"Pas de vente aujourd’hui",IF(J6<K6*Paramètres!$B$11,"Rentable",IF(J6<=K6,"Juste rentable","Perte")))) -> Juste rentable | N6: =IF(A6="","",DATE(YEAR(A6),MONTH(A6),1)) -> 46296
A7: 46302 | B7: Pub A · le problème | C7: Pagne wax 6 yards | D7: A | E7: 1500 | F7: 8 | G7: 1 | H7: =IF(N(F7)>0,E7/F7,"") -> 187.5 | I7: =IF(N(F7)>0,G7/F7,"") -> 0.125 | J7: =IF(N(G7)>0,E7/G7,"") -> 1500 | K7: =IF(C7="","",IFERROR(INDEX(Catalogue!$K$6:$K$55,MATCH(C7,Catalogue!$B$6:$B$55,0)),"")) -> 4200 | L7: =IF(OR(E7="",K7=""),"",N(G7)*K7-E7) -> 2700 | M7: =IF(OR(E7="",K7=""),"",IF(N(G7)=0,"Pas de vente aujourd’hui",IF(J7<K7*Paramètres!$B$11,"Rentable",IF(J7<=K7,"Juste rentable","Perte")))) -> Juste rentable | N7: =IF(A7="","",DATE(YEAR(A7),MONTH(A7),1)) -> 46296
A8: 46303 | B8: Pub A · le problème | C8: Pagne wax 6 yards | D8: A | E8: 1500 | F8: 6 | G8: 1 | H8: =IF(N(F8)>0,E8/F8,"") -> 250 | I8: =IF(N(F8)>0,G8/F8,"") -> 0.16666667 | J8: =IF(N(G8)>0,E8/G8,"") -> 1500 | K8: =IF(C8="","",IFERROR(INDEX(Catalogue!$K$6:$K$55,MATCH(C8,Catalogue!$B$6:$B$55,0)),"")) -> 4200 | L8: =IF(OR(E8="",K8=""),"",N(G8)*K8-E8) -> 2700 | M8: =IF(OR(E8="",K8=""),"",IF(N(G8)=0,"Pas de vente aujourd’hui",IF(J8<K8*Paramètres!$B$11,"Rentable",IF(J8<=K8,"Juste rentable","Perte")))) -> Juste rentable | N8: =IF(A8="","",DATE(YEAR(A8),MONTH(A8),1)) -> 46296
A9: 46304 | B9: Pub A · le problème | C9: Pagne wax 6 yards | D9: A | E9: 1500 | F9: 9 | G9: 2 | H9: =IF(N(F9)>0,E9/F9,"") -> 166.66667 | I9: =IF(N(F9)>0,G9/F9,"") -> 0.22222222 | J9: =IF(N(G9)>0,E9/G9,"") -> 750 | K9: =IF(C9="","",IFERROR(INDEX(Catalogue!$K$6:$K$55,MATCH(C9,Catalogue!$B$6:$B$55,0)),"")) -> 4200 | L9: =IF(OR(E9="",K9=""),"",N(G9)*K9-E9) -> 6900 | M9: =IF(OR(E9="",K9=""),"",IF(N(G9)=0,"Pas de vente aujourd’hui",IF(J9<K9*Paramètres!$B$11,"Rentable",IF(J9<=K9,"Juste rentable","Perte")))) -> Rentable | N9: =IF(A9="","",DATE(YEAR(A9),MONTH(A9),1)) -> 46296
A10: 46305 | B10: Pub A · le problème | C10: Pagne wax 6 yards | D10: A | E10: 1500 | F10: 7 | G10: 1 | H10: =IF(N(F10)>0,E10/F10,"") -> 214.28571 | I10: =IF(N(F10)>0,G10/F10,"") -> 0.14285714 | J10: =IF(N(G10)>0,E10/G10,"") -> 1500 | K10: =IF(C10="","",IFERROR(INDEX(Catalogue!$K$6:$K$55,MATCH(C10,Catalogue!$B$6:$B$55,0)),"")) -> 4200 | L10: =IF(OR(E10="",K10=""),"",N(G10)*K10-E10) -> 2700 | M10: =IF(OR(E10="",K10=""),"",IF(N(G10)=0,"Pas de vente aujourd’hui",IF(J10<K10*Paramètres!$B$11,"Rentable",IF(J10<=K10,"Juste rentable","Perte")))) -> Juste rentable | N10: =IF(A10="","",DATE(YEAR(A10),MONTH(A10),1)) -> 46296
A11: 46301 | B11: Pub B · témoignage | C11: Pagne wax 6 yards | D11: B | E11: 1500 | F11: 4 | G11: 0 | H11: =IF(N(F11)>0,E11/F11,"") -> 375 | I11: =IF(N(F11)>0,G11/F11,"") -> 0 | J11: =IF(N(G11)>0,E11/G11,"") | K11: =IF(C11="","",IFERROR(INDEX(Catalogue!$K$6:$K$55,MATCH(C11,Catalogue!$B$6:$B$55,0)),"")) -> 4200 | L11: =IF(OR(E11="",K11=""),"",N(G11)*K11-E11) -> -1500 | M11: =IF(OR(E11="",K11=""),"",IF(N(G11)=0,"Pas de vente aujourd’hui",IF(J11<K11*Paramètres!$B$11,"Rentable",IF(J11<=K11,"Juste rentable","Perte")))) -> Pas de vente aujourd’hui | N11: =IF(A11="","",DATE(YEAR(A11),MONTH(A11),1)) -> 46296
A12: 46302 | B12: Pub B · témoignage | C12: Pagne wax 6 yards | D12: B | E12: 1500 | F12: 3 | G12: 1 | H12: =IF(N(F12)>0,E12/F12,"") -> 500 | I12: =IF(N(F12)>0,G12/F12,"") -> 0.33333333 | J12: =IF(N(G12)>0,E12/G12,"") -> 1500 | K12: =IF(C12="","",IFERROR(INDEX(Catalogue!$K$6:$K$55,MATCH(C12,Catalogue!$B$6:$B$55,0)),"")) -> 4200 | L12: =IF(OR(E12="",K12=""),"",N(G12)*K12-E12) -> 2700 | M12: =IF(OR(E12="",K12=""),"",IF(N(G12)=0,"Pas de vente aujourd’hui",IF(J12<K12*Paramètres!$B$11,"Rentable",IF(J12<=K12,"Juste rentable","Perte")))) -> Juste rentable | N12: =IF(A12="","",DATE(YEAR(A12),MONTH(A12),1)) -> 46296
A13: 46303 | B13: Pub B · témoignage | C13: Pagne wax 6 yards | D13: B | E13: 1500 | F13: 5 | G13: 0 | H13: =IF(N(F13)>0,E13/F13,"") -> 300 | I13: =IF(N(F13)>0,G13/F13,"") -> 0 | J13: =IF(N(G13)>0,E13/G13,"") | K13: =IF(C13="","",IFERROR(INDEX(Catalogue!$K$6:$K$55,MATCH(C13,Catalogue!$B$6:$B$55,0)),"")) -> 4200 | L13: =IF(OR(E13="",K13=""),"",N(G13)*K13-E13) -> -1500 | M13: =IF(OR(E13="",K13=""),"",IF(N(G13)=0,"Pas de vente aujourd’hui",IF(J13<K13*Paramètres!$B$11,"Rentable",IF(J13<=K13,"Juste rentable","Perte")))) -> Pas de vente aujourd’hui | N13: =IF(A13="","",DATE(YEAR(A13),MONTH(A13),1)) -> 46296
A14: 46285 | B14: Pub test septembre | C14: Foulard assorti | D14: A | E14: 2000 | F14: 4 | G14: 1 | H14: =IF(N(F14)>0,E14/F14,"") -> 500 | I14: =IF(N(F14)>0,G14/F14,"") -> 0.25 | J14: =IF(N(G14)>0,E14/G14,"") -> 2000 | K14: =IF(C14="","",IFERROR(INDEX(Catalogue!$K$6:$K$55,MATCH(C14,Catalogue!$B$6:$B$55,0)),"")) -> 2150 | L14: =IF(OR(E14="",K14=""),"",N(G14)*K14-E14) -> 150 | M14: =IF(OR(E14="",K14=""),"",IF(N(G14)=0,"Pas de vente aujourd’hui",IF(J14<K14*Paramètres!$B$11,"Rentable",IF(J14<=K14,"Juste rentable","Perte")))) -> Juste rentable | N14: =IF(A14="","",DATE(YEAR(A14),MONTH(A14),1)) -> 46266
A15: 46286 | B15: Pub test septembre | C15: Foulard assorti | D15: A | E15: 2000 | F15: 3 | G15: 0 | H15: =IF(N(F15)>0,E15/F15,"") -> 666.66667 | I15: =IF(N(F15)>0,G15/F15,"") -> 0 | J15: =IF(N(G15)>0,E15/G15,"") | K15: =IF(C15="","",IFERROR(INDEX(Catalogue!$K$6:$K$55,MATCH(C15,Catalogue!$B$6:$B$55,0)),"")) -> 2150 | L15: =IF(OR(E15="",K15=""),"",N(G15)*K15-E15) -> -2000 | M15: =IF(OR(E15="",K15=""),"",IF(N(G15)=0,"Pas de vente aujourd’hui",IF(J15<K15*Paramètres!$B$11,"Rentable",IF(J15<=K15,"Juste rentable","Perte")))) -> Pas de vente aujourd’hui | N15: =IF(A15="","",DATE(YEAR(A15),MONTH(A15),1)) -> 46266
A16: 46287 | B16: Pub test septembre | C16: Foulard assorti | D16: A | E16: 2000 | F16: 5 | G16: 0 | H16: =IF(N(F16)>0,E16/F16,"") -> 400 | I16: =IF(N(F16)>0,G16/F16,"") -> 0 | J16: =IF(N(G16)>0,E16/G16,"") | K16: =IF(C16="","",IFERROR(INDEX(Catalogue!$K$6:$K$55,MATCH(C16,Catalogue!$B$6:$B$55,0)),"")) -> 2150 | L16: =IF(OR(E16="",K16=""),"",N(G16)*K16-E16) -> -2000 | M16: =IF(OR(E16="",K16=""),"",IF(N(G16)=0,"Pas de vente aujourd’hui",IF(J16<K16*Paramètres!$B$11,"Rentable",IF(J16<=K16,"Juste rentable","Perte")))) -> Pas de vente aujourd’hui | N16: =IF(A16="","",DATE(YEAR(A16),MONTH(A16),1)) -> 46266
H17: =IF(N(F17)>0,E17/F17,"") | I17: =IF(N(F17)>0,G17/F17,"") | J17: =IF(N(G17)>0,E17/G17,"") | K17: =IF(C17="","",IFERROR(INDEX(Catalogue!$K$6:$K$55,MATCH(C17,Catalogue!$B$6:$B$55,0)),"")) | L17: =IF(OR(E17="",K17=""),"",N(G17)*K17-E17) | M17: =IF(OR(E17="",K17=""),"",IF(N(G17)=0,"Pas de vente aujourd’hui",IF(J17<K17*Paramètres!$B$11,"Rentable",IF(J17<=K17,"Juste rentable","Perte")))) | N17: =IF(A17="","",DATE(YEAR(A17),MONTH(A17),1))
H18: =IF(N(F18)>0,E18/F18,"") | I18: =IF(N(F18)>0,G18/F18,"") | J18: =IF(N(G18)>0,E18/G18,"") | K18: =IF(C18="","",IFERROR(INDEX(Catalogue!$K$6:$K$55,MATCH(C18,Catalogue!$B$6:$B$55,0)),"")) | L18: =IF(OR(E18="",K18=""),"",N(G18)*K18-E18) | M18: =IF(OR(E18="",K18=""),"",IF(N(G18)=0,"Pas de vente aujourd’hui",IF(J18<K18*Paramètres!$B$11,"Rentable",IF(J18<=K18,"Juste rentable","Perte")))) | N18: =IF(A18="","",DATE(YEAR(A18),MONTH(A18),1))
H19: =IF(N(F19)>0,E19/F19,"") | I19: =IF(N(F19)>0,G19/F19,"") | J19: =IF(N(G19)>0,E19/G19,"") | K19: =IF(C19="","",IFERROR(INDEX(Catalogue!$K$6:$K$55,MATCH(C19,Catalogue!$B$6:$B$55,0)),"")) | L19: =IF(OR(E19="",K19=""),"",N(G19)*K19-E19) | M19: =IF(OR(E19="",K19=""),"",IF(N(G19)=0,"Pas de vente aujourd’hui",IF(J19<K19*Paramètres!$B$11,"Rentable",IF(J19<=K19,"Juste rentable","Perte")))) | N19: =IF(A19="","",DATE(YEAR(A19),MONTH(A19),1))
H20: =IF(N(F20)>0,E20/F20,"") | I20: =IF(N(F20)>0,G20/F20,"") | J20: =IF(N(G20)>0,E20/G20,"") | K20: =IF(C20="","",IFERROR(INDEX(Catalogue!$K$6:$K$55,MATCH(C20,Catalogue!$B$6:$B$55,0)),"")) | L20: =IF(OR(E20="",K20=""),"",N(G20)*K20-E20) | M20: =IF(OR(E20="",K20=""),"",IF(N(G20)=0,"Pas de vente aujourd’hui",IF(J20<K20*Paramètres!$B$11,"Rentable",IF(J20<=K20,"Juste rentable","Perte")))) | N20: =IF(A20="","",DATE(YEAR(A20),MONTH(A20),1))
H21: =IF(N(F21)>0,E21/F21,"") | I21: =IF(N(F21)>0,G21/F21,"") | J21: =IF(N(G21)>0,E21/G21,"") | K21: =IF(C21="","",IFERROR(INDEX(Catalogue!$K$6:$K$55,MATCH(C21,Catalogue!$B$6:$B$55,0)),"")) | L21: =IF(OR(E21="",K21=""),"",N(G21)*K21-E21) | M21: =IF(OR(E21="",K21=""),"",IF(N(G21)=0,"Pas de vente aujourd’hui",IF(J21<K21*Paramètres!$B$11,"Rentable",IF(J21<=K21,"Juste rentable","Perte")))) | N21: =IF(A21="","",DATE(YEAR(A21),MONTH(A21),1))
H22: =IF(N(F22)>0,E22/F22,"") | I22: =IF(N(F22)>0,G22/F22,"") | J22: =IF(N(G22)>0,E22/G22,"") | K22: =IF(C22="","",IFERROR(INDEX(Catalogue!$K$6:$K$55,MATCH(C22,Catalogue!$B$6:$B$55,0)),"")) | L22: =IF(OR(E22="",K22=""),"",N(G22)*K22-E22) | M22: =IF(OR(E22="",K22=""),"",IF(N(G22)=0,"Pas de vente aujourd’hui",IF(J22<K22*Paramètres!$B$11,"Rentable",IF(J22<=K22,"Juste rentable","Perte")))) | N22: =IF(A22="","",DATE(YEAR(A22),MONTH(A22),1))
H23: =IF(N(F23)>0,E23/F23,"") | I23: =IF(N(F23)>0,G23/F23,"") | J23: =IF(N(G23)>0,E23/G23,"") | K23: =IF(C23="","",IFERROR(INDEX(Catalogue!$K$6:$K$55,MATCH(C23,Catalogue!$B$6:$B$55,0)),"")) | L23: =IF(OR(E23="",K23=""),"",N(G23)*K23-E23) | M23: =IF(OR(E23="",K23=""),"",IF(N(G23)=0,"Pas de vente aujourd’hui",IF(J23<K23*Paramètres!$B$11,"Rentable",IF(J23<=K23,"Juste rentable","Perte")))) | N23: =IF(A23="","",DATE(YEAR(A23),MONTH(A23),1))
H24: =IF(N(F24)>0,E24/F24,"") | I24: =IF(N(F24)>0,G24/F24,"") | J24: =IF(N(G24)>0,E24/G24,"") | K24: =IF(C24="","",IFERROR(INDEX(Catalogue!$K$6:$K$55,MATCH(C24,Catalogue!$B$6:$B$55,0)),"")) | L24: =IF(OR(E24="",K24=""),"",N(G24)*K24-E24) | M24: =IF(OR(E24="",K24=""),"",IF(N(G24)=0,"Pas de vente aujourd’hui",IF(J24<K24*Paramètres!$B$11,"Rentable",IF(J24<=K24,"Juste rentable","Perte")))) | N24: =IF(A24="","",DATE(YEAR(A24),MONTH(A24),1))
H25: =IF(N(F25)>0,E25/F25,"") | I25: =IF(N(F25)>0,G25/F25,"") | J25: =IF(N(G25)>0,E25/G25,"") | K25: =IF(C25="","",IFERROR(INDEX(Catalogue!$K$6:$K$55,MATCH(C25,Catalogue!$B$6:$B$55,0)),"")) | L25: =IF(OR(E25="",K25=""),"",N(G25)*K25-E25) | M25: =IF(OR(E25="",K25=""),"",IF(N(G25)=0,"Pas de vente aujourd’hui",IF(J25<K25*Paramètres!$B$11,"Rentable",IF(J25<=K25,"Juste rentable","Perte")))) | N25: =IF(A25="","",DATE(YEAR(A25),MONTH(A25),1))
H26: =IF(N(F26)>0,E26/F26,"") | I26: =IF(N(F26)>0,G26/F26,"") | J26: =IF(N(G26)>0,E26/G26,"") | K26: =IF(C26="","",IFERROR(INDEX(Catalogue!$K$6:$K$55,MATCH(C26,Catalogue!$B$6:$B$55,0)),"")) | L26: =IF(OR(E26="",K26=""),"",N(G26)*K26-E26) | M26: =IF(OR(E26="",K26=""),"",IF(N(G26)=0,"Pas de vente aujourd’hui",IF(J26<K26*Paramètres!$B$11,"Rentable",IF(J26<=K26,"Juste rentable","Perte")))) | N26: =IF(A26="","",DATE(YEAR(A26),MONTH(A26),1))
H27: =IF(N(F27)>0,E27/F27,"") | I27: =IF(N(F27)>0,G27/F27,"") | J27: =IF(N(G27)>0,E27/G27,"") | K27: =IF(C27="","",IFERROR(INDEX(Catalogue!$K$6:$K$55,MATCH(C27,Catalogue!$B$6:$B$55,0)),"")) | L27: =IF(OR(E27="",K27=""),"",N(G27)*K27-E27) | M27: =IF(OR(E27="",K27=""),"",IF(N(G27)=0,"Pas de vente aujourd’hui",IF(J27<K27*Paramètres!$B$11,"Rentable",IF(J27<=K27,"Juste rentable","Perte")))) | N27: =IF(A27="","",DATE(YEAR(A27),MONTH(A27),1))
H28: =IF(N(F28)>0,E28/F28,"") | I28: =IF(N(F28)>0,G28/F28,"") | J28: =IF(N(G28)>0,E28/G28,"") | K28: =IF(C28="","",IFERROR(INDEX(Catalogue!$K$6:$K$55,MATCH(C28,Catalogue!$B$6:$B$55,0)),"")) | L28: =IF(OR(E28="",K28=""),"",N(G28)*K28-E28) | M28: =IF(OR(E28="",K28=""),"",IF(N(G28)=0,"Pas de vente aujourd’hui",IF(J28<K28*Paramètres!$B$11,"Rentable",IF(J28<=K28,"Juste rentable","Perte")))) | N28: =IF(A28="","",DATE(YEAR(A28),MONTH(A28),1))
... H370: =IF(N(F370)>0,E370/F370,"") | I370: =IF(N(F370)>0,G370/F370,"") | J370: =IF(N(G370)>0,E370/G370,"") | K370: =IF(C370="","",IFERROR(INDEX(Catalogue!$K$6:$K$55,MATCH(C370,Catalogue!$B$6:$B$55,0)),"")) | L370: =IF(OR(E370="",K370=""),"",N(G370)*K370-E370) | M370: =IF(OR(E370="",K370=""),"",IF(N(G370)=0,"Pas de vente aujourd’hui",IF(J370<K370*Paramètres!$B$11,"Rentable",IF(J370<=K370,"Juste rentable","Perte")))) | N370: =IF(A370="","",DATE(YEAR(A370),MONTH(A370),1))

Sheet Synthèse pubs
A1: Synthèse et décision par pub
A2: Écris le nom exact de chaque pub (comme dans Suivi pubs). La décision suit la règle du chapitre 8, après 3 à 4 jours.
A3: Cellules jaunes : à remplir · cellules grises : calculées automatiquement (ne pas modifier)
A5: Nom de la pub | B5: Produit / service | C5: Jours de diffusion | D5: Dépensé total | E5: Messages | F5: Ventes | G5: Coût par message | H5: Taux de conversion | I5: Coût par vente | J5: Marge avant pub | K5: Bénéfice total | L5: Décision | M5: Diagnostic
A6: Pub A · le problème | B6: =IF(A6="","",IFERROR(INDEX('Suivi pubs'!$C$6:$C$370,MATCH(A6,'Suivi pubs'!$B$6:$B$370,0)),"Nom introuvable")) -> Pagne wax 6 yards | C6: =IF(A6="","",COUNTIFS('Suivi pubs'!$B$6:$B$370,A6)) -> 5 | D6: =IF(A6="","",SUMIFS('Suivi pubs'!$E$6:$E$370,'Suivi pubs'!$B$6:$B$370,A6)) -> 7500 | E6: =IF(A6="","",SUMIFS('Suivi pubs'!$F$6:$F$370,'Suivi pubs'!$B$6:$B$370,A6)) -> 37 | F6: =IF(A6="","",SUMIFS('Suivi pubs'!$G$6:$G$370,'Suivi pubs'!$B$6:$B$370,A6)) -> 6 | G6: =IF(OR(A6="",N(E6)=0),"",D6/E6) -> 202.7027 | H6: =IF(OR(A6="",N(E6)=0),"",F6/E6) -> 0.16216216 | I6: =IF(OR(A6="",N(F6)=0),"",D6/F6) -> 1250 | J6: =IF(A6="","",IFERROR(INDEX(Catalogue!$K$6:$K$55,MATCH(B6,Catalogue!$B$6:$B$55,0)),"")) -> 4200 | K6: =IF(OR(A6="",J6=""),"",F6*J6-D6) -> 17700 | L6: =IF(OR(A6="",J6=""),"",IF(C6<Paramètres!$B$12,"Trop tôt : laisse tourner 3 à 4 jours",IF(F6=0,IF(D6>=J6,"Couper","Améliorer (aucune vente)"),IF(I6<J6*Paramètres!$B$11,"Augmenter (+20 à 30 %)",IF(I6<=J6,"Améliorer","Couper"))))) -> Augmenter (+20 à 30 %) | M6: =IF(OR(A6="",C6=0),"",IF(E6=0,"Pas de messages : revois l’accroche, le visuel ou le ciblage (chapitre 7)",IF(H6<Paramètres!$B$13,"Beaucoup de messages, peu de ventes : conversation, prix ou confiance (chapitre 9)","Conversion correcte : continue de tester de nouvelles versions"))) -> Conversion correcte : continue de tester de nouvelles versions
A7: Pub B · témoignage | B7: =IF(A7="","",IFERROR(INDEX('Suivi pubs'!$C$6:$C$370,MATCH(A7,'Suivi pubs'!$B$6:$B$370,0)),"Nom introuvable")) -> Pagne wax 6 yards | C7: =IF(A7="","",COUNTIFS('Suivi pubs'!$B$6:$B$370,A7)) -> 3 | D7: =IF(A7="","",SUMIFS('Suivi pubs'!$E$6:$E$370,'Suivi pubs'!$B$6:$B$370,A7)) -> 4500 | E7: =IF(A7="","",SUMIFS('Suivi pubs'!$F$6:$F$370,'Suivi pubs'!$B$6:$B$370,A7)) -> 12 | F7: =IF(A7="","",SUMIFS('Suivi pubs'!$G$6:$G$370,'Suivi pubs'!$B$6:$B$370,A7)) -> 1 | G7: =IF(OR(A7="",N(E7)=0),"",D7/E7) -> 375 | H7: =IF(OR(A7="",N(E7)=0),"",F7/E7) -> 0.083333333 | I7: =IF(OR(A7="",N(F7)=0),"",D7/F7) -> 4500 | J7: =IF(A7="","",IFERROR(INDEX(Catalogue!$K$6:$K$55,MATCH(B7,Catalogue!$B$6:$B$55,0)),"")) -> 4200 | K7: =IF(OR(A7="",J7=""),"",F7*J7-D7) -> -300 | L7: =IF(OR(A7="",J7=""),"",IF(C7<Paramètres!$B$12,"Trop tôt : laisse tourner 3 à 4 jours",IF(F7=0,IF(D7>=J7,"Couper","Améliorer (aucune vente)"),IF(I7<J7*Paramètres!$B$11,"Augmenter (+20 à 30 %)",IF(I7<=J7,"Améliorer","Couper"))))) -> Couper | M7: =IF(OR(A7="",C7=0),"",IF(E7=0,"Pas de messages : revois l’accroche, le visuel ou le ciblage (chapitre 7)",IF(H7<Paramètres!$B$13,"Beaucoup de messages, peu de ventes : conversation, prix ou confiance (chapitre 9)","Conversion correcte : continue de tester de nouvelles versions"))) -> Beaucoup de messages, peu de ventes : conversation, prix ou confiance (chapitre 9)
A8: Pub test septembre | B8: =IF(A8="","",IFERROR(INDEX('Suivi pubs'!$C$6:$C$370,MATCH(A8,'Suivi pubs'!$B$6:$B$370,0)),"Nom introuvable")) -> Foulard assorti | C8: =IF(A8="","",COUNTIFS('Suivi pubs'!$B$6:$B$370,A8)) -> 3 | D8: =IF(A8="","",SUMIFS('Suivi pubs'!$E$6:$E$370,'Suivi pubs'!$B$6:$B$370,A8)) -> 6000 | E8: =IF(A8="","",SUMIFS('Suivi pubs'!$F$6:$F$370,'Suivi pubs'!$B$6:$B$370,A8)) -> 12 | F8: =IF(A8="","",SUMIFS('Suivi pubs'!$G$6:$G$370,'Suivi pubs'!$B$6:$B$370,A8)) -> 1 | G8: =IF(OR(A8="",N(E8)=0),"",D8/E8) -> 500 | H8: =IF(OR(A8="",N(E8)=0),"",F8/E8) -> 0.083333333 | I8: =IF(OR(A8="",N(F8)=0),"",D8/F8) -> 6000 | J8: =IF(A8="","",IFERROR(INDEX(Catalogue!$K$6:$K$55,MATCH(B8,Catalogue!$B$6:$B$55,0)),"")) -> 2150 | K8: =IF(OR(A8="",J8=""),"",F8*J8-D8) -> -3850 | L8: =IF(OR(A8="",J8=""),"",IF(C8<Paramètres!$B$12,"Trop tôt : laisse tourner 3 à 4 jours",IF(F8=0,IF(D8>=J8,"Couper","Améliorer (aucune vente)"),IF(I8<J8*Paramètres!$B$11,"Augmenter (+20 à 30 %)",IF(I8<=J8,"Améliorer","Couper"))))) -> Couper | M8: =IF(OR(A8="",C8=0),"",IF(E8=0,"Pas de messages : revois l’accroche, le visuel ou le ciblage (chapitre 7)",IF(H8<Paramètres!$B$13,"Beaucoup de messages, peu de ventes : conversation, prix ou confiance (chapitre 9)","Conversion correcte : continue de tester de nouvelles versions"))) -> Beaucoup de messages, peu de ventes : conversation, prix ou confiance (chapitre 9)
B9: =IF(A9="","",IFERROR(INDEX('Suivi pubs'!$C$6:$C$370,MATCH(A9,'Suivi pubs'!$B$6:$B$370,0)),"Nom introuvable")) | C9: =IF(A9="","",COUNTIFS('Suivi pubs'!$B$6:$B$370,A9)) | D9: =IF(A9="","",SUMIFS('Suivi pubs'!$E$6:$E$370,'Suivi pubs'!$B$6:$B$370,A9)) | E9: =IF(A9="","",SUMIFS('Suivi pubs'!$F$6:$F$370,'Suivi pubs'!$B$6:$B$370,A9)) | F9: =IF(A9="","",SUMIFS('Suivi pubs'!$G$6:$G$370,'Suivi pubs'!$B$6:$B$370,A9)) | G9: =IF(OR(A9="",N(E9)=0),"",D9/E9) | H9: =IF(OR(A9="",N(E9)=0),"",F9/E9) | I9: =IF(OR(A9="",N(F9)=0),"",D9/F9) | J9: =IF(A9="","",IFERROR(INDEX(Catalogue!$K$6:$K$55,MATCH(B9,Catalogue!$B$6:$B$55,0)),"")) | K9: =IF(OR(A9="",J9=""),"",F9*J9-D9) | L9: =IF(OR(A9="",J9=""),"",IF(C9<Paramètres!$B$12,"Trop tôt : laisse tourner 3 à 4 jours",IF(F9=0,IF(D9>=J9,"Couper","Améliorer (aucune vente)"),IF(I9<J9*Paramètres!$B$11,"Augmenter (+20 à 30 %)",IF(I9<=J9,"Améliorer","Couper"))))) | M9: =IF(OR(A9="",C9=0),"",IF(E9=0,"Pas de messages : revois l’accroche, le visuel ou le ciblage (chapitre 7)",IF(H9<Paramètres!$B$13,"Beaucoup de messages, peu de ventes : conversation, prix ou confiance (chapitre 9)","Conversion correcte : continue de tester de nouvelles versions")))
B10: =IF(A10="","",IFERROR(INDEX('Suivi pubs'!$C$6:$C$370,MATCH(A10,'Suivi pubs'!$B$6:$B$370,0)),"Nom introuvable")) | C10: =IF(A10="","",COUNTIFS('Suivi pubs'!$B$6:$B$370,A10)) | D10: =IF(A10="","",SUMIFS('Suivi pubs'!$E$6:$E$370,'Suivi pubs'!$B$6:$B$370,A10)) | E10: =IF(A10="","",SUMIFS('Suivi pubs'!$F$6:$F$370,'Suivi pubs'!$B$6:$B$370,A10)) | F10: =IF(A10="","",SUMIFS('Suivi pubs'!$G$6:$G$370,'Suivi pubs'!$B$6:$B$370,A10)) | G10: =IF(OR(A10="",N(E10)=0),"",D10/E10) | H10: =IF(OR(A10="",N(E10)=0),"",F10/E10) | I10: =IF(OR(A10="",N(F10)=0),"",D10/F10) | J10: =IF(A10="","",IFERROR(INDEX(Catalogue!$K$6:$K$55,MATCH(B10,Catalogue!$B$6:$B$55,0)),"")) | K10: =IF(OR(A10="",J10=""),"",F10*J10-D10) | L10: =IF(OR(A10="",J10=""),"",IF(C10<Paramètres!$B$12,"Trop tôt : laisse tourner 3 à 4 jours",IF(F10=0,IF(D10>=J10,"Couper","Améliorer (aucune vente)"),IF(I10<J10*Paramètres!$B$11,"Augmenter (+20 à 30 %)",IF(I10<=J10,"Améliorer","Couper"))))) | M10: =IF(OR(A10="",C10=0),"",IF(E10=0,"Pas de messages : revois l’accroche, le visuel ou le ciblage (chapitre 7)",IF(H10<Paramètres!$B$13,"Beaucoup de messages, peu de ventes : conversation, prix ou confiance (chapitre 9)","Conversion correcte : continue de tester de nouvelles versions")))
B11: =IF(A11="","",IFERROR(INDEX('Suivi pubs'!$C$6:$C$370,MATCH(A11,'Suivi pubs'!$B$6:$B$370,0)),"Nom introuvable")) | C11: =IF(A11="","",COUNTIFS('Suivi pubs'!$B$6:$B$370,A11)) | D11: =IF(A11="","",SUMIFS('Suivi pubs'!$E$6:$E$370,'Suivi pubs'!$B$6:$B$370,A11)) | E11: =IF(A11="","",SUMIFS('Suivi pubs'!$F$6:$F$370,'Suivi pubs'!$B$6:$B$370,A11)) | F11: =IF(A11="","",SUMIFS('Suivi pubs'!$G$6:$G$370,'Suivi pubs'!$B$6:$B$370,A11)) | G11: =IF(OR(A11="",N(E11)=0),"",D11/E11) | H11: =IF(OR(A11="",N(E11)=0),"",F11/E11) | I11: =IF(OR(A11="",N(F11)=0),"",D11/F11) | J11: =IF(A11="","",IFERROR(INDEX(Catalogue!$K$6:$K$55,MATCH(B11,Catalogue!$B$6:$B$55,0)),"")) | K11: =IF(OR(A11="",J11=""),"",F11*J11-D11) | L11: =IF(OR(A11="",J11=""),"",IF(C11<Paramètres!$B$12,"Trop tôt : laisse tourner 3 à 4 jours",IF(F11=0,IF(D11>=J11,"Couper","Améliorer (aucune vente)"),IF(I11<J11*Paramètres!$B$11,"Augmenter (+20 à 30 %)",IF(I11<=J11,"Améliorer","Couper"))))) | M11: =IF(OR(A11="",C11=0),"",IF(E11=0,"Pas de messages : revois l’accroche, le visuel ou le ciblage (chapitre 7)",IF(H11<Paramètres!$B$13,"Beaucoup de messages, peu de ventes : conversation, prix ou confiance (chapitre 9)","Conversion correcte : continue de tester de nouvelles versions")))
B12: =IF(A12="","",IFERROR(INDEX('Suivi pubs'!$C$6:$C$370,MATCH(A12,'Suivi pubs'!$B$6:$B$370,0)),"Nom introuvable")) | C12: =IF(A12="","",COUNTIFS('Suivi pubs'!$B$6:$B$370,A12)) | D12: =IF(A12="","",SUMIFS('Suivi pubs'!$E$6:$E$370,'Suivi pubs'!$B$6:$B$370,A12)) | E12: =IF(A12="","",SUMIFS('Suivi pubs'!$F$6:$F$370,'Suivi pubs'!$B$6:$B$370,A12)) | F12: =IF(A12="","",SUMIFS('Suivi pubs'!$G$6:$G$370,'Suivi pubs'!$B$6:$B$370,A12)) | G12: =IF(OR(A12="",N(E12)=0),"",D12/E12) | H12: =IF(OR(A12="",N(E12)=0),"",F12/E12) | I12: =IF(OR(A12="",N(F12)=0),"",D12/F12) | J12: =IF(A12="","",IFERROR(INDEX(Catalogue!$K$6:$K$55,MATCH(B12,Catalogue!$B$6:$B$55,0)),"")) | K12: =IF(OR(A12="",J12=""),"",F12*J12-D12) | L12: =IF(OR(A12="",J12=""),"",IF(C12<Paramètres!$B$12,"Trop tôt : laisse tourner 3 à 4 jours",IF(F12=0,IF(D12>=J12,"Couper","Améliorer (aucune vente)"),IF(I12<J12*Paramètres!$B$11,"Augmenter (+20 à 30 %)",IF(I12<=J12,"Améliorer","Couper"))))) | M12: =IF(OR(A12="",C12=0),"",IF(E12=0,"Pas de messages : revois l’accroche, le visuel ou le ciblage (chapitre 7)",IF(H12<Paramètres!$B$13,"Beaucoup de messages, peu de ventes : conversation, prix ou confiance (chapitre 9)","Conversion correcte : continue de tester de nouvelles versions")))
B13: =IF(A13="","",IFERROR(INDEX('Suivi pubs'!$C$6:$C$370,MATCH(A13,'Suivi pubs'!$B$6:$B$370,0)),"Nom introuvable")) | C13: =IF(A13="","",COUNTIFS('Suivi pubs'!$B$6:$B$370,A13)) | D13: =IF(A13="","",SUMIFS('Suivi pubs'!$E$6:$E$370,'Suivi pubs'!$B$6:$B$370,A13)) | E13: =IF(A13="","",SUMIFS('Suivi pubs'!$F$6:$F$370,'Suivi pubs'!$B$6:$B$370,A13)) | F13: =IF(A13="","",SUMIFS('Suivi pubs'!$G$6:$G$370,'Suivi pubs'!$B$6:$B$370,A13)) | G13: =IF(OR(A13="",N(E13)=0),"",D13/E13) | H13: =IF(OR(A13="",N(E13)=0),"",F13/E13) | I13: =IF(OR(A13="",N(F13)=0),"",D13/F13) | J13: =IF(A13="","",IFERROR(INDEX(Catalogue!$K$6:$K$55,MATCH(B13,Catalogue!$B$6:$B$55,0)),"")) | K13: =IF(OR(A13="",J13=""),"",F13*J13-D13) | L13: =IF(OR(A13="",J13=""),"",IF(C13<Paramètres!$B$12,"Trop tôt : laisse tourner 3 à 4 jours",IF(F13=0,IF(D13>=J13,"Couper","Améliorer (aucune vente)"),IF(I13<J13*Paramètres!$B$11,"Augmenter (+20 à 30 %)",IF(I13<=J13,"Améliorer","Couper"))))) | M13: =IF(OR(A13="",C13=0),"",IF(E13=0,"Pas de messages : revois l’accroche, le visuel ou le ciblage (chapitre 7)",IF(H13<Paramètres!$B$13,"Beaucoup de messages, peu de ventes : conversation, prix ou confiance (chapitre 9)","Conversion correcte : continue de tester de nouvelles versions")))
B14: =IF(A14="","",IFERROR(INDEX('Suivi pubs'!$C$6:$C$370,MATCH(A14,'Suivi pubs'!$B$6:$B$370,0)),"Nom introuvable")) | C14: =IF(A14="","",COUNTIFS('Suivi pubs'!$B$6:$B$370,A14)) | D14: =IF(A14="","",SUMIFS('Suivi pubs'!$E$6:$E$370,'Suivi pubs'!$B$6:$B$370,A14)) | E14: =IF(A14="","",SUMIFS('Suivi pubs'!$F$6:$F$370,'Suivi pubs'!$B$6:$B$370,A14)) | F14: =IF(A14="","",SUMIFS('Suivi pubs'!$G$6:$G$370,'Suivi pubs'!$B$6:$B$370,A14)) | G14: =IF(OR(A14="",N(E14)=0),"",D14/E14) | H14: =IF(OR(A14="",N(E14)=0),"",F14/E14) | I14: =IF(OR(A14="",N(F14)=0),"",D14/F14) | J14: =IF(A14="","",IFERROR(INDEX(Catalogue!$K$6:$K$55,MATCH(B14,Catalogue!$B$6:$B$55,0)),"")) | K14: =IF(OR(A14="",J14=""),"",F14*J14-D14) | L14: =IF(OR(A14="",J14=""),"",IF(C14<Paramètres!$B$12,"Trop tôt : laisse tourner 3 à 4 jours",IF(F14=0,IF(D14>=J14,"Couper","Améliorer (aucune vente)"),IF(I14<J14*Paramètres!$B$11,"Augmenter (+20 à 30 %)",IF(I14<=J14,"Améliorer","Couper"))))) | M14: =IF(OR(A14="",C14=0),"",IF(E14=0,"Pas de messages : revois l’accroche, le visuel ou le ciblage (chapitre 7)",IF(H14<Paramètres!$B$13,"Beaucoup de messages, peu de ventes : conversation, prix ou confiance (chapitre 9)","Conversion correcte : continue de tester de nouvelles versions")))
B15: =IF(A15="","",IFERROR(INDEX('Suivi pubs'!$C$6:$C$370,MATCH(A15,'Suivi pubs'!$B$6:$B$370,0)),"Nom introuvable")) | C15: =IF(A15="","",COUNTIFS('Suivi pubs'!$B$6:$B$370,A15)) | D15: =IF(A15="","",SUMIFS('Suivi pubs'!$E$6:$E$370,'Suivi pubs'!$B$6:$B$370,A15)) | E15: =IF(A15="","",SUMIFS('Suivi pubs'!$F$6:$F$370,'Suivi pubs'!$B$6:$B$370,A15)) | F15: =IF(A15="","",SUMIFS('Suivi pubs'!$G$6:$G$370,'Suivi pubs'!$B$6:$B$370,A15)) | G15: =IF(OR(A15="",N(E15)=0),"",D15/E15) | H15: =IF(OR(A15="",N(E15)=0),"",F15/E15) | I15: =IF(OR(A15="",N(F15)=0),"",D15/F15) | J15: =IF(A15="","",IFERROR(INDEX(Catalogue!$K$6:$K$55,MATCH(B15,Catalogue!$B$6:$B$55,0)),"")) | K15: =IF(OR(A15="",J15=""),"",F15*J15-D15) | L15: =IF(OR(A15="",J15=""),"",IF(C15<Paramètres!$B$12,"Trop tôt : laisse tourner 3 à 4 jours",IF(F15=0,IF(D15>=J15,"Couper","Améliorer (aucune vente)"),IF(I15<J15*Paramètres!$B$11,"Augmenter (+20 à 30 %)",IF(I15<=J15,"Améliorer","Couper"))))) | M15: =IF(OR(A15="",C15=0),"",IF(E15=0,"Pas de messages : revois l’accroche, le visuel ou le ciblage (chapitre 7)",IF(H15<Paramètres!$B$13,"Beaucoup de messages, peu de ventes : conversation, prix ou confiance (chapitre 9)","Conversion correcte : continue de tester de nouvelles versions")))
B16: =IF(A16="","",IFERROR(INDEX('Suivi pubs'!$C$6:$C$370,MATCH(A16,'Suivi pubs'!$B$6:$B$370,0)),"Nom introuvable")) | C16: =IF(A16="","",COUNTIFS('Suivi pubs'!$B$6:$B$370,A16)) | D16: =IF(A16="","",SUMIFS('Suivi pubs'!$E$6:$E$370,'Suivi pubs'!$B$6:$B$370,A16)) | E16: =IF(A16="","",SUMIFS('Suivi pubs'!$F$6:$F$370,'Suivi pubs'!$B$6:$B$370,A16)) | F16: =IF(A16="","",SUMIFS('Suivi pubs'!$G$6:$G$370,'Suivi pubs'!$B$6:$B$370,A16)) | G16: =IF(OR(A16="",N(E16)=0),"",D16/E16) | H16: =IF(OR(A16="",N(E16)=0),"",F16/E16) | I16: =IF(OR(A16="",N(F16)=0),"",D16/F16) | J16: =IF(A16="","",IFERROR(INDEX(Catalogue!$K$6:$K$55,MATCH(B16,Catalogue!$B$6:$B$55,0)),"")) | K16: =IF(OR(A16="",J16=""),"",F16*J16-D16) | L16: =IF(OR(A16="",J16=""),"",IF(C16<Paramètres!$B$12,"Trop tôt : laisse tourner 3 à 4 jours",IF(F16=0,IF(D16>=J16,"Couper","Améliorer (aucune vente)"),IF(I16<J16*Paramètres!$B$11,"Augmenter (+20 à 30 %)",IF(I16<=J16,"Améliorer","Couper"))))) | M16: =IF(OR(A16="",C16=0),"",IF(E16=0,"Pas de messages : revois l’accroche, le visuel ou le ciblage (chapitre 7)",IF(H16<Paramètres!$B$13,"Beaucoup de messages, peu de ventes : conversation, prix ou confiance (chapitre 9)","Conversion correcte : continue de tester de nouvelles versions")))
B17: =IF(A17="","",IFERROR(INDEX('Suivi pubs'!$C$6:$C$370,MATCH(A17,'Suivi pubs'!$B$6:$B$370,0)),"Nom introuvable")) | C17: =IF(A17="","",COUNTIFS('Suivi pubs'!$B$6:$B$370,A17)) | D17: =IF(A17="","",SUMIFS('Suivi pubs'!$E$6:$E$370,'Suivi pubs'!$B$6:$B$370,A17)) | E17: =IF(A17="","",SUMIFS('Suivi pubs'!$F$6:$F$370,'Suivi pubs'!$B$6:$B$370,A17)) | F17: =IF(A17="","",SUMIFS('Suivi pubs'!$G$6:$G$370,'Suivi pubs'!$B$6:$B$370,A17)) | G17: =IF(OR(A17="",N(E17)=0),"",D17/E17) | H17: =IF(OR(A17="",N(E17)=0),"",F17/E17) | I17: =IF(OR(A17="",N(F17)=0),"",D17/F17) | J17: =IF(A17="","",IFERROR(INDEX(Catalogue!$K$6:$K$55,MATCH(B17,Catalogue!$B$6:$B$55,0)),"")) | K17: =IF(OR(A17="",J17=""),"",F17*J17-D17) | L17: =IF(OR(A17="",J17=""),"",IF(C17<Paramètres!$B$12,"Trop tôt : laisse tourner 3 à 4 jours",IF(F17=0,IF(D17>=J17,"Couper","Améliorer (aucune vente)"),IF(I17<J17*Paramètres!$B$11,"Augmenter (+20 à 30 %)",IF(I17<=J17,"Améliorer","Couper"))))) | M17: =IF(OR(A17="",C17=0),"",IF(E17=0,"Pas de messages : revois l’accroche, le visuel ou le ciblage (chapitre 7)",IF(H17<Paramètres!$B$13,"Beaucoup de messages, peu de ventes : conversation, prix ou confiance (chapitre 9)","Conversion correcte : continue de tester de nouvelles versions")))
B18: =IF(A18="","",IFERROR(INDEX('Suivi pubs'!$C$6:$C$370,MATCH(A18,'Suivi pubs'!$B$6:$B$370,0)),"Nom introuvable")) | C18: =IF(A18="","",COUNTIFS('Suivi pubs'!$B$6:$B$370,A18)) | D18: =IF(A18="","",SUMIFS('Suivi pubs'!$E$6:$E$370,'Suivi pubs'!$B$6:$B$370,A18)) | E18: =IF(A18="","",SUMIFS('Suivi pubs'!$F$6:$F$370,'Suivi pubs'!$B$6:$B$370,A18)) | F18: =IF(A18="","",SUMIFS('Suivi pubs'!$G$6:$G$370,'Suivi pubs'!$B$6:$B$370,A18)) | G18: =IF(OR(A18="",N(E18)=0),"",D18/E18) | H18: =IF(OR(A18="",N(E18)=0),"",F18/E18) | I18: =IF(OR(A18="",N(F18)=0),"",D18/F18) | J18: =IF(A18="","",IFERROR(INDEX(Catalogue!$K$6:$K$55,MATCH(B18,Catalogue!$B$6:$B$55,0)),"")) | K18: =IF(OR(A18="",J18=""),"",F18*J18-D18) | L18: =IF(OR(A18="",J18=""),"",IF(C18<Paramètres!$B$12,"Trop tôt : laisse tourner 3 à 4 jours",IF(F18=0,IF(D18>=J18,"Couper","Améliorer (aucune vente)"),IF(I18<J18*Paramètres!$B$11,"Augmenter (+20 à 30 %)",IF(I18<=J18,"Améliorer","Couper"))))) | M18: =IF(OR(A18="",C18=0),"",IF(E18=0,"Pas de messages : revois l’accroche, le visuel ou le ciblage (chapitre 7)",IF(H18<Paramètres!$B$13,"Beaucoup de messages, peu de ventes : conversation, prix ou confiance (chapitre 9)","Conversion correcte : continue de tester de nouvelles versions")))
B19: =IF(A19="","",IFERROR(INDEX('Suivi pubs'!$C$6:$C$370,MATCH(A19,'Suivi pubs'!$B$6:$B$370,0)),"Nom introuvable")) | C19: =IF(A19="","",COUNTIFS('Suivi pubs'!$B$6:$B$370,A19)) | D19: =IF(A19="","",SUMIFS('Suivi pubs'!$E$6:$E$370,'Suivi pubs'!$B$6:$B$370,A19)) | E19: =IF(A19="","",SUMIFS('Suivi pubs'!$F$6:$F$370,'Suivi pubs'!$B$6:$B$370,A19)) | F19: =IF(A19="","",SUMIFS('Suivi pubs'!$G$6:$G$370,'Suivi pubs'!$B$6:$B$370,A19)) | G19: =IF(OR(A19="",N(E19)=0),"",D19/E19) | H19: =IF(OR(A19="",N(E19)=0),"",F19/E19) | I19: =IF(OR(A19="",N(F19)=0),"",D19/F19) | J19: =IF(A19="","",IFERROR(INDEX(Catalogue!$K$6:$K$55,MATCH(B19,Catalogue!$B$6:$B$55,0)),"")) | K19: =IF(OR(A19="",J19=""),"",F19*J19-D19) | L19: =IF(OR(A19="",J19=""),"",IF(C19<Paramètres!$B$12,"Trop tôt : laisse tourner 3 à 4 jours",IF(F19=0,IF(D19>=J19,"Couper","Améliorer (aucune vente)"),IF(I19<J19*Paramètres!$B$11,"Augmenter (+20 à 30 %)",IF(I19<=J19,"Améliorer","Couper"))))) | M19: =IF(OR(A19="",C19=0),"",IF(E19=0,"Pas de messages : revois l’accroche, le visuel ou le ciblage (chapitre 7)",IF(H19<Paramètres!$B$13,"Beaucoup de messages, peu de ventes : conversation, prix ou confiance (chapitre 9)","Conversion correcte : continue de tester de nouvelles versions")))
B20: =IF(A20="","",IFERROR(INDEX('Suivi pubs'!$C$6:$C$370,MATCH(A20,'Suivi pubs'!$B$6:$B$370,0)),"Nom introuvable")) | C20: =IF(A20="","",COUNTIFS('Suivi pubs'!$B$6:$B$370,A20)) | D20: =IF(A20="","",SUMIFS('Suivi pubs'!$E$6:$E$370,'Suivi pubs'!$B$6:$B$370,A20)) | E20: =IF(A20="","",SUMIFS('Suivi pubs'!$F$6:$F$370,'Suivi pubs'!$B$6:$B$370,A20)) | F20: =IF(A20="","",SUMIFS('Suivi pubs'!$G$6:$G$370,'Suivi pubs'!$B$6:$B$370,A20)) | G20: =IF(OR(A20="",N(E20)=0),"",D20/E20) | H20: =IF(OR(A20="",N(E20)=0),"",F20/E20) | I20: =IF(OR(A20="",N(F20)=0),"",D20/F20) | J20: =IF(A20="","",IFERROR(INDEX(Catalogue!$K$6:$K$55,MATCH(B20,Catalogue!$B$6:$B$55,0)),"")) | K20: =IF(OR(A20="",J20=""),"",F20*J20-D20) | L20: =IF(OR(A20="",J20=""),"",IF(C20<Paramètres!$B$12,"Trop tôt : laisse tourner 3 à 4 jours",IF(F20=0,IF(D20>=J20,"Couper","Améliorer (aucune vente)"),IF(I20<J20*Paramètres!$B$11,"Augmenter (+20 à 30 %)",IF(I20<=J20,"Améliorer","Couper"))))) | M20: =IF(OR(A20="",C20=0),"",IF(E20=0,"Pas de messages : revois l’accroche, le visuel ou le ciblage (chapitre 7)",IF(H20<Paramètres!$B$13,"Beaucoup de messages, peu de ventes : conversation, prix ou confiance (chapitre 9)","Conversion correcte : continue de tester de nouvelles versions")))
... B35: =IF(A35="","",IFERROR(INDEX('Suivi pubs'!$C$6:$C$370,MATCH(A35,'Suivi pubs'!$B$6:$B$370,0)),"Nom introuvable")) | C35: =IF(A35="","",COUNTIFS('Suivi pubs'!$B$6:$B$370,A35)) | D35: =IF(A35="","",SUMIFS('Suivi pubs'!$E$6:$E$370,'Suivi pubs'!$B$6:$B$370,A35)) | E35: =IF(A35="","",SUMIFS('Suivi pubs'!$F$6:$F$370,'Suivi pubs'!$B$6:$B$370,A35)) | F35: =IF(A35="","",SUMIFS('Suivi pubs'!$G$6:$G$370,'Suivi pubs'!$B$6:$B$370,A35)) | G35: =IF(OR(A35="",N(E35)=0),"",D35/E35) | H35: =IF(OR(A35="",N(E35)=0),"",F35/E35) | I35: =IF(OR(A35="",N(F35)=0),"",D35/F35) | J35: =IF(A35="","",IFERROR(INDEX(Catalogue!$K$6:$K$55,MATCH(B35,Catalogue!$B$6:$B$55,0)),"")) | K35: =IF(OR(A35="",J35=""),"",F35*J35-D35) | L35: =IF(OR(A35="",J35=""),"",IF(C35<Paramètres!$B$12,"Trop tôt : laisse tourner 3 à 4 jours",IF(F35=0,IF(D35>=J35,"Couper","Améliorer (aucune vente)"),IF(I35<J35*Paramètres!$B$11,"Augmenter (+20 à 30 %)",IF(I35<=J35,"Améliorer","Couper"))))) | M35: =IF(OR(A35="",C35=0),"",IF(E35=0,"Pas de messages : revois l’accroche, le visuel ou le ciblage (chapitre 7)",IF(H35<Paramètres!$B$13,"Beaucoup de messages, peu de ventes : conversation, prix ou confiance (chapitre 9)","Conversion correcte : continue de tester de nouvelles versions")))
A37: Règle : coût par vente < 1/3 de la marge avant pub → augmenter ; entre 1/3 et la marge → améliorer ; au-delà de la marge → couper.

Sheet Ventes
A1: Journal des ventes et commandes
A2: Une ligne par commande. Laisse « Prix unitaire » vide pour appliquer le prix du catalogue. Statut « Livrée et payée » = vente comptée.
A3: Cellules jaunes : à remplir · cellules grises : calculées automatiquement (ne pas modifier)
A5: N° | B5: Date | C5: Client | D5: Téléphone | E5: Zone | F5: Produit / service | G5: Qté | H5: Prix unitaire (si différent) | I5: Prix appliqué | J5: Remise | K5: Montant net | L5: Paiement | M5: Statut | N5: Source | O5: Livraison payée (si différent) | P5: Livraison retenue | Q5: Coût produits | R5: Marge brute | S5: Avis demandé ? | T5: Mois | U5: Type client | W5: Note : la remise et la livraison s’appliquent à la commande entière. « Livraison payée (si différent) » : saisis 0 si le client paie la livraison.
A6: =IF(B6="","",ROW()-5) -> 1 | B6: 46270 | C6: Awa Ndiaye | D6: 77 111 22 33 | E6: Dakar Plateau | F6: Pagne wax 6 yards | G6: 1 | I6: =IF(F6="","",IF(H6="",IFERROR(INDEX(Catalogue!$I$6:$I$55,MATCH(F6,Catalogue!$B$6:$B$55,0)),0),H6)) -> 10000 | K6: =IF(F6="","",N(G6)*I6-N(J6)) -> 10000 | L6: Wave | M6: Livrée et payée | N6: Publication gratuite | P6: =IF(F6="","",IF(O6="",IFERROR(INDEX(Catalogue!$G$6:$G$55,MATCH(F6,Catalogue!$B$6:$B$55,0)),0),O6)) -> 1500 | Q6: =IF(F6="","",N(G6)*(IFERROR(INDEX(Catalogue!$E$6:$E$55,MATCH(F6,Catalogue!$B$6:$B$55,0)),0)+IFERROR(INDEX(Catalogue!$F$6:$F$55,MATCH(F6,Catalogue!$B$6:$B$55,0)),0)+IFERROR(INDEX(Catalogue!$H$6:$H$55,MATCH(F6,Catalogue!$B$6:$B$55,0)),0))) -> 4300 | R6: =IF(F6="","",IF(M6="Livrée et payée",K6-Q6-P6,IF(M6="Annulée",-N(P6),0))) -> 4200 | S6: Oui | T6: =IF(B6="","",DATE(YEAR(B6),MONTH(B6),1)) -> 46266 | U6: =IF(D6="","",IF(COUNTIF(D$6:D6,D6)=1,"Nouveau","Fidèle")) -> Nouveau
A7: =IF(B7="","",ROW()-5) -> 2 | B7: 46273 | C7: Mariama Ba | D7: 76 222 33 44 | E7: Pikine / Guédiawaye | F7: Foulard assorti | G7: 2 | I7: =IF(F7="","",IF(H7="",IFERROR(INDEX(Catalogue!$I$6:$I$55,MATCH(F7,Catalogue!$B$6:$B$55,0)),0),H7)) -> 3500 | K7: =IF(F7="","",N(G7)*I7-N(J7)) -> 7000 | L7: Orange Money | M7: Livrée et payée | N7: Groupe Facebook | P7: =IF(F7="","",IF(O7="",IFERROR(INDEX(Catalogue!$G$6:$G$55,MATCH(F7,Catalogue!$B$6:$B$55,0)),0),O7)) -> 0 | Q7: =IF(F7="","",N(G7)*(IFERROR(INDEX(Catalogue!$E$6:$E$55,MATCH(F7,Catalogue!$B$6:$B$55,0)),0)+IFERROR(INDEX(Catalogue!$F$6:$F$55,MATCH(F7,Catalogue!$B$6:$B$55,0)),0)+IFERROR(INDEX(Catalogue!$H$6:$H$55,MATCH(F7,Catalogue!$B$6:$B$55,0)),0))) -> 2700 | R7: =IF(F7="","",IF(M7="Livrée et payée",K7-Q7-P7,IF(M7="Annulée",-N(P7),0))) -> 4300 | S7: Oui | T7: =IF(B7="","",DATE(YEAR(B7),MONTH(B7),1)) -> 46266 | U7: =IF(D7="","",IF(COUNTIF(D$6:D7,D7)=1,"Nouveau","Fidèle")) -> Nouveau
A8: =IF(B8="","",ROW()-5) -> 3 | B8: 46277 | C8: Khady Fall | D8: 78 333 44 55 | E8: Rufisque | F8: Pagne wax 6 yards | G8: 1 | I8: =IF(F8="","",IF(H8="",IFERROR(INDEX(Catalogue!$I$6:$I$55,MATCH(F8,Catalogue!$B$6:$B$55,0)),0),H8)) -> 10000 | K8: =IF(F8="","",N(G8)*I8-N(J8)) -> 10000 | L8: Espèces à la livraison | M8: Livrée et payée | N8: Marketplace | P8: =IF(F8="","",IF(O8="",IFERROR(INDEX(Catalogue!$G$6:$G$55,MATCH(F8,Catalogue!$B$6:$B$55,0)),0),O8)) -> 1500 | Q8: =IF(F8="","",N(G8)*(IFERROR(INDEX(Catalogue!$E$6:$E$55,MATCH(F8,Catalogue!$B$6:$B$55,0)),0)+IFERROR(INDEX(Catalogue!$F$6:$F$55,MATCH(F8,Catalogue!$B$6:$B$55,0)),0)+IFERROR(INDEX(Catalogue!$H$6:$H$55,MATCH(F8,Catalogue!$B$6:$B$55,0)),0))) -> 4300 | R8: =IF(F8="","",IF(M8="Livrée et payée",K8-Q8-P8,IF(M8="Annulée",-N(P8),0))) -> 4200 | S8: Non | T8: =IF(B8="","",DATE(YEAR(B8),MONTH(B8),1)) -> 46266 | U8: =IF(D8="","",IF(COUNTIF(D$6:D8,D8)=1,"Nouveau","Fidèle")) -> Nouveau
A9: =IF(B9="","",ROW()-5) -> 4 | B9: 46283 | C9: Fatou Sow | D9: 77 444 55 66 | E9: Dakar banlieue | F9: Pack 3 pagnes | G9: 1 | I9: =IF(F9="","",IF(H9="",IFERROR(INDEX(Catalogue!$I$6:$I$55,MATCH(F9,Catalogue!$B$6:$B$55,0)),0),H9)) -> 27000 | J9: 1000 | K9: =IF(F9="","",N(G9)*I9-N(J9)) -> 26000 | L9: Acompte + solde | M9: Livrée et payée | N9: Bouche-à-oreille | P9: =IF(F9="","",IF(O9="",IFERROR(INDEX(Catalogue!$G$6:$G$55,MATCH(F9,Catalogue!$B$6:$B$55,0)),0),O9)) -> 1500 | Q9: =IF(F9="","",N(G9)*(IFERROR(INDEX(Catalogue!$E$6:$E$55,MATCH(F9,Catalogue!$B$6:$B$55,0)),0)+IFERROR(INDEX(Catalogue!$F$6:$F$55,MATCH(F9,Catalogue!$B$6:$B$55,0)),0)+IFERROR(INDEX(Catalogue!$H$6:$H$55,MATCH(F9,Catalogue!$B$6:$B$55,0)),0))) -> 12400 | R9: =IF(F9="","",IF(M9="Livrée et payée",K9-Q9-P9,IF(M9="Annulée",-N(P9),0))) -> 12100 | S9: Oui | T9: =IF(B9="","",DATE(YEAR(B9),MONTH(B9),1)) -> 46266 | U9: =IF(D9="","",IF(COUNTIF(D$6:D9,D9)=1,"Nouveau","Fidèle")) -> Nouveau
A10: =IF(B10="","",ROW()-5) -> 5 | B10: 46286 | C10: Aminata Diop | D10: 70 555 66 77 | E10: Thiès | F10: Foulard assorti | G10: 1 | I10: =IF(F10="","",IF(H10="",IFERROR(INDEX(Catalogue!$I$6:$I$55,MATCH(F10,Catalogue!$B$6:$B$55,0)),0),H10)) -> 3500 | K10: =IF(F10="","",N(G10)*I10-N(J10)) -> 3500 | L10: Wave | M10: Livrée et payée | N10: Publicité | P10: =IF(F10="","",IF(O10="",IFERROR(INDEX(Catalogue!$G$6:$G$55,MATCH(F10,Catalogue!$B$6:$B$55,0)),0),O10)) -> 0 | Q10: =IF(F10="","",N(G10)*(IFERROR(INDEX(Catalogue!$E$6:$E$55,MATCH(F10,Catalogue!$B$6:$B$55,0)),0)+IFERROR(INDEX(Catalogue!$F$6:$F$55,MATCH(F10,Catalogue!$B$6:$B$55,0)),0)+IFERROR(INDEX(Catalogue!$H$6:$H$55,MATCH(F10,Catalogue!$B$6:$B$55,0)),0))) -> 1350 | R10: =IF(F10="","",IF(M10="Livrée et payée",K10-Q10-P10,IF(M10="Annulée",-N(P10),0))) -> 2150 | S10: Non | T10: =IF(B10="","",DATE(YEAR(B10),MONTH(B10),1)) -> 46266 | U10: =IF(D10="","",IF(COUNTIF(D$6:D10,D10)=1,"Nouveau","Fidèle")) -> Nouveau
A11: =IF(B11="","",ROW()-5) -> 6 | B11: 46288 | C11: Ndèye Sarr | D11: 76 666 77 88 | E11: Dakar Plateau | F11: Pagne wax 6 yards | G11: 1 | I11: =IF(F11="","",IF(H11="",IFERROR(INDEX(Catalogue!$I$6:$I$55,MATCH(F11,Catalogue!$B$6:$B$55,0)),0),H11)) -> 10000 | K11: =IF(F11="","",N(G11)*I11-N(J11)) -> 10000 | L11: Espèces à la livraison | M11: Annulée | N11: Publicité | P11: =IF(F11="","",IF(O11="",IFERROR(INDEX(Catalogue!$G$6:$G$55,MATCH(F11,Catalogue!$B$6:$B$55,0)),0),O11)) -> 1500 | Q11: =IF(F11="","",N(G11)*(IFERROR(INDEX(Catalogue!$E$6:$E$55,MATCH(F11,Catalogue!$B$6:$B$55,0)),0)+IFERROR(INDEX(Catalogue!$F$6:$F$55,MATCH(F11,Catalogue!$B$6:$B$55,0)),0)+IFERROR(INDEX(Catalogue!$H$6:$H$55,MATCH(F11,Catalogue!$B$6:$B$55,0)),0))) -> 4300 | R11: =IF(F11="","",IF(M11="Livrée et payée",K11-Q11-P11,IF(M11="Annulée",-N(P11),0))) -> -1500 | S11: Non | T11: =IF(B11="","",DATE(YEAR(B11),MONTH(B11),1)) -> 46266 | U11: =IF(D11="","",IF(COUNTIF(D$6:D11,D11)=1,"Nouveau","Fidèle")) -> Nouveau
A12: =IF(B12="","",ROW()-5) -> 7 | B12: 46291 | C12: Awa Ndiaye | D12: 77 111 22 33 | E12: Dakar Plateau | F12: Conseil style à domicile | G12: 1 | I12: =IF(F12="","",IF(H12="",IFERROR(INDEX(Catalogue!$I$6:$I$55,MATCH(F12,Catalogue!$B$6:$B$55,0)),0),H12)) -> 7500 | K12: =IF(F12="","",N(G12)*I12-N(J12)) -> 7500 | L12: Wave | M12: Livrée et payée | N12: Client fidèle | P12: =IF(F12="","",IF(O12="",IFERROR(INDEX(Catalogue!$G$6:$G$55,MATCH(F12,Catalogue!$B$6:$B$55,0)),0),O12)) -> 0 | Q12: =IF(F12="","",N(G12)*(IFERROR(INDEX(Catalogue!$E$6:$E$55,MATCH(F12,Catalogue!$B$6:$B$55,0)),0)+IFERROR(INDEX(Catalogue!$F$6:$F$55,MATCH(F12,Catalogue!$B$6:$B$55,0)),0)+IFERROR(INDEX(Catalogue!$H$6:$H$55,MATCH(F12,Catalogue!$B$6:$B$55,0)),0))) -> 2000 | R12: =IF(F12="","",IF(M12="Livrée et payée",K12-Q12-P12,IF(M12="Annulée",-N(P12),0))) -> 5500 | S12: Oui | T12: =IF(B12="","",DATE(YEAR(B12),MONTH(B12),1)) -> 46266 | U12: =IF(D12="","",IF(COUNTIF(D$6:D12,D12)=1,"Nouveau","Fidèle")) -> Fidèle
A13: =IF(B13="","",ROW()-5) -> 8 | B13: 46297 | C13: Mariama Ba | D13: 76 222 33 44 | E13: Pikine / Guédiawaye | F13: Pagne wax 6 yards | G13: 2 | I13: =IF(F13="","",IF(H13="",IFERROR(INDEX(Catalogue!$I$6:$I$55,MATCH(F13,Catalogue!$B$6:$B$55,0)),0),H13)) -> 10000 | K13: =IF(F13="","",N(G13)*I13-N(J13)) -> 20000 | L13: Orange Money | M13: Livrée et payée | N13: Client fidèle | P13: =IF(F13="","",IF(O13="",IFERROR(INDEX(Catalogue!$G$6:$G$55,MATCH(F13,Catalogue!$B$6:$B$55,0)),0),O13)) -> 1500 | Q13: =IF(F13="","",N(G13)*(IFERROR(INDEX(Catalogue!$E$6:$E$55,MATCH(F13,Catalogue!$B$6:$B$55,0)),0)+IFERROR(INDEX(Catalogue!$F$6:$F$55,MATCH(F13,Catalogue!$B$6:$B$55,0)),0)+IFERROR(INDEX(Catalogue!$H$6:$H$55,MATCH(F13,Catalogue!$B$6:$B$55,0)),0))) -> 8600 | R13: =IF(F13="","",IF(M13="Livrée et payée",K13-Q13-P13,IF(M13="Annulée",-N(P13),0))) -> 9900 | S13: Oui | T13: =IF(B13="","",DATE(YEAR(B13),MONTH(B13),1)) -> 46296 | U13: =IF(D13="","",IF(COUNTIF(D$6:D13,D13)=1,"Nouveau","Fidèle")) -> Fidèle
A14: =IF(B14="","",ROW()-5) -> 9 | B14: 46301 | C14: Coumba Gueye | D14: 77 777 88 99 | E14: Dakar banlieue | F14: Pagne wax 6 yards | G14: 1 | I14: =IF(F14="","",IF(H14="",IFERROR(INDEX(Catalogue!$I$6:$I$55,MATCH(F14,Catalogue!$B$6:$B$55,0)),0),H14)) -> 10000 | K14: =IF(F14="","",N(G14)*I14-N(J14)) -> 10000 | L14: Wave | M14: Livrée et payée | N14: Publicité | P14: =IF(F14="","",IF(O14="",IFERROR(INDEX(Catalogue!$G$6:$G$55,MATCH(F14,Catalogue!$B$6:$B$55,0)),0),O14)) -> 1500 | Q14: =IF(F14="","",N(G14)*(IFERROR(INDEX(Catalogue!$E$6:$E$55,MATCH(F14,Catalogue!$B$6:$B$55,0)),0)+IFERROR(INDEX(Catalogue!$F$6:$F$55,MATCH(F14,Catalogue!$B$6:$B$55,0)),0)+IFERROR(INDEX(Catalogue!$H$6:$H$55,MATCH(F14,Catalogue!$B$6:$B$55,0)),0))) -> 4300 | R14: =IF(F14="","",IF(M14="Livrée et payée",K14-Q14-P14,IF(M14="Annulée",-N(P14),0))) -> 4200 | S14: Oui | T14: =IF(B14="","",DATE(YEAR(B14),MONTH(B14),1)) -> 46296 | U14: =IF(D14="","",IF(COUNTIF(D$6:D14,D14)=1,"Nouveau","Fidèle")) -> Nouveau
A15: =IF(B15="","",ROW()-5) -> 10 | B15: 46301 | C15: Bineta Cissé | D15: 78 888 99 00 | E15: Pikine / Guédiawaye | F15: Pagne wax 6 yards | G15: 1 | I15: =IF(F15="","",IF(H15="",IFERROR(INDEX(Catalogue!$I$6:$I$55,MATCH(F15,Catalogue!$B$6:$B$55,0)),0),H15)) -> 10000 | K15: =IF(F15="","",N(G15)*I15-N(J15)) -> 10000 | L15: Espèces à la livraison | M15: Livrée et payée | N15: Publicité | P15: =IF(F15="","",IF(O15="",IFERROR(INDEX(Catalogue!$G$6:$G$55,MATCH(F15,Catalogue!$B$6:$B$55,0)),0),O15)) -> 1500 | Q15: =IF(F15="","",N(G15)*(IFERROR(INDEX(Catalogue!$E$6:$E$55,MATCH(F15,Catalogue!$B$6:$B$55,0)),0)+IFERROR(INDEX(Catalogue!$F$6:$F$55,MATCH(F15,Catalogue!$B$6:$B$55,0)),0)+IFERROR(INDEX(Catalogue!$H$6:$H$55,MATCH(F15,Catalogue!$B$6:$B$55,0)),0))) -> 4300 | R15: =IF(F15="","",IF(M15="Livrée et payée",K15-Q15-P15,IF(M15="Annulée",-N(P15),0))) -> 4200 | S15: Non | T15: =IF(B15="","",DATE(YEAR(B15),MONTH(B15),1)) -> 46296 | U15: =IF(D15="","",IF(COUNTIF(D$6:D15,D15)=1,"Nouveau","Fidèle")) -> Nouveau
A16: =IF(B16="","",ROW()-5) -> 11 | B16: 46302 | C16: Khady Fall | D16: 78 333 44 55 | E16: Rufisque | F16: Pack 3 pagnes | G16: 1 | I16: =IF(F16="","",IF(H16="",IFERROR(INDEX(Catalogue!$I$6:$I$55,MATCH(F16,Catalogue!$B$6:$B$55,0)),0),H16)) -> 27000 | J16: 1000 | K16: =IF(F16="","",N(G16)*I16-N(J16)) -> 26000 | L16: Acompte + solde | M16: Livrée et payée | N16: Publicité | P16: =IF(F16="","",IF(O16="",IFERROR(INDEX(Catalogue!$G$6:$G$55,MATCH(F16,Catalogue!$B$6:$B$55,0)),0),O16)) -> 1500 | Q16: =IF(F16="","",N(G16)*(IFERROR(INDEX(Catalogue!$E$6:$E$55,MATCH(F16,Catalogue!$B$6:$B$55,0)),0)+IFERROR(INDEX(Catalogue!$F$6:$F$55,MATCH(F16,Catalogue!$B$6:$B$55,0)),0)+IFERROR(INDEX(Catalogue!$H$6:$H$55,MATCH(F16,Catalogue!$B$6:$B$55,0)),0))) -> 12400 | R16: =IF(F16="","",IF(M16="Livrée et payée",K16-Q16-P16,IF(M16="Annulée",-N(P16),0))) -> 12100 | S16: Oui | T16: =IF(B16="","",DATE(YEAR(B16),MONTH(B16),1)) -> 46296 | U16: =IF(D16="","",IF(COUNTIF(D$6:D16,D16)=1,"Nouveau","Fidèle")) -> Fidèle
A17: =IF(B17="","",ROW()-5) -> 12 | B17: 46302 | C17: Aminata Diop | D17: 70 555 66 77 | E17: Thiès | F17: Pagne wax 6 yards | G17: 1 | I17: =IF(F17="","",IF(H17="",IFERROR(INDEX(Catalogue!$I$6:$I$55,MATCH(F17,Catalogue!$B$6:$B$55,0)),0),H17)) -> 10000 | K17: =IF(F17="","",N(G17)*I17-N(J17)) -> 10000 | L17: Wave | M17: Livrée et payée | N17: Publicité | P17: =IF(F17="","",IF(O17="",IFERROR(INDEX(Catalogue!$G$6:$G$55,MATCH(F17,Catalogue!$B$6:$B$55,0)),0),O17)) -> 1500 | Q17: =IF(F17="","",N(G17)*(IFERROR(INDEX(Catalogue!$E$6:$E$55,MATCH(F17,Catalogue!$B$6:$B$55,0)),0)+IFERROR(INDEX(Catalogue!$F$6:$F$55,MATCH(F17,Catalogue!$B$6:$B$55,0)),0)+IFERROR(INDEX(Catalogue!$H$6:$H$55,MATCH(F17,Catalogue!$B$6:$B$55,0)),0))) -> 4300 | R17: =IF(F17="","",IF(M17="Livrée et payée",K17-Q17-P17,IF(M17="Annulée",-N(P17),0))) -> 4200 | S17: Oui | T17: =IF(B17="","",DATE(YEAR(B17),MONTH(B17),1)) -> 46296 | U17: =IF(D17="","",IF(COUNTIF(D$6:D17,D17)=1,"Nouveau","Fidèle")) -> Fidèle
A18: =IF(B18="","",ROW()-5) -> 13 | B18: 46303 | C18: Fatou Sow | D18: 77 444 55 66 | E18: Dakar banlieue | F18: Foulard assorti | G18: 3 | I18: =IF(F18="","",IF(H18="",IFERROR(INDEX(Catalogue!$I$6:$I$55,MATCH(F18,Catalogue!$B$6:$B$55,0)),0),H18)) -> 3500 | K18: =IF(F18="","",N(G18)*I18-N(J18)) -> 10500 | L18: Orange Money | M18: Livrée et payée | N18: Statut WhatsApp | P18: =IF(F18="","",IF(O18="",IFERROR(INDEX(Catalogue!$G$6:$G$55,MATCH(F18,Catalogue!$B$6:$B$55,0)),0),O18)) -> 0 | Q18: =IF(F18="","",N(G18)*(IFERROR(INDEX(Catalogue!$E$6:$E$55,MATCH(F18,Catalogue!$B$6:$B$55,0)),0)+IFERROR(INDEX(Catalogue!$F$6:$F$55,MATCH(F18,Catalogue!$B$6:$B$55,0)),0)+IFERROR(INDEX(Catalogue!$H$6:$H$55,MATCH(F18,Catalogue!$B$6:$B$55,0)),0))) -> 4050 | R18: =IF(F18="","",IF(M18="Livrée et payée",K18-Q18-P18,IF(M18="Annulée",-N(P18),0))) -> 6450 | S18: Non | T18: =IF(B18="","",DATE(YEAR(B18),MONTH(B18),1)) -> 46296 | U18: =IF(D18="","",IF(COUNTIF(D$6:D18,D18)=1,"Nouveau","Fidèle")) -> Fidèle
A19: =IF(B19="","",ROW()-5) -> 14 | B19: 46303 | C19: Ndèye Sarr | D19: 76 666 77 88 | E19: Dakar Plateau | F19: Pagne wax 6 yards | G19: 1 | I19: =IF(F19="","",IF(H19="",IFERROR(INDEX(Catalogue!$I$6:$I$55,MATCH(F19,Catalogue!$B$6:$B$55,0)),0),H19)) -> 10000 | K19: =IF(F19="","",N(G19)*I19-N(J19)) -> 10000 | L19: Wave | M19: Livrée et payée | N19: Publicité | P19: =IF(F19="","",IF(O19="",IFERROR(INDEX(Catalogue!$G$6:$G$55,MATCH(F19,Catalogue!$B$6:$B$55,0)),0),O19)) -> 1500 | Q19: =IF(F19="","",N(G19)*(IFERROR(INDEX(Catalogue!$E$6:$E$55,MATCH(F19,Catalogue!$B$6:$B$55,0)),0)+IFERROR(INDEX(Catalogue!$F$6:$F$55,MATCH(F19,Catalogue!$B$6:$B$55,0)),0)+IFERROR(INDEX(Catalogue!$H$6:$H$55,MATCH(F19,Catalogue!$B$6:$B$55,0)),0))) -> 4300 | R19: =IF(F19="","",IF(M19="Livrée et payée",K19-Q19-P19,IF(M19="Annulée",-N(P19),0))) -> 4200 | S19: Oui | T19: =IF(B19="","",DATE(YEAR(B19),MONTH(B19),1)) -> 46296 | U19: =IF(D19="","",IF(COUNTIF(D$6:D19,D19)=1,"Nouveau","Fidèle")) -> Fidèle
A20: =IF(B20="","",ROW()-5) -> 15 | B20: 46304 | C20: Bineta Cissé | D20: 78 888 99 00 | E20: Pikine / Guédiawaye | F20: Pagne wax 6 yards | G20: 1 | I20: =IF(F20="","",IF(H20="",IFERROR(INDEX(Catalogue!$I$6:$I$55,MATCH(F20,Catalogue!$B$6:$B$55,0)),0),H20)) -> 10000 | K20: =IF(F20="","",N(G20)*I20-N(J20)) -> 10000 | L20: Espèces à la livraison | M20: Annulée | N20: Publicité | P20: =IF(F20="","",IF(O20="",IFERROR(INDEX(Catalogue!$G$6:$G$55,MATCH(F20,Catalogue!$B$6:$B$55,0)),0),O20)) -> 1500 | Q20: =IF(F20="","",N(G20)*(IFERROR(INDEX(Catalogue!$E$6:$E$55,MATCH(F20,Catalogue!$B$6:$B$55,0)),0)+IFERROR(INDEX(Catalogue!$F$6:$F$55,MATCH(F20,Catalogue!$B$6:$B$55,0)),0)+IFERROR(INDEX(Catalogue!$H$6:$H$55,MATCH(F20,Catalogue!$B$6:$B$55,0)),0))) -> 4300 | R20: =IF(F20="","",IF(M20="Livrée et payée",K20-Q20-P20,IF(M20="Annulée",-N(P20),0))) -> -1500 | S20: Non | T20: =IF(B20="","",DATE(YEAR(B20),MONTH(B20),1)) -> 46296 | U20: =IF(D20="","",IF(COUNTIF(D$6:D20,D20)=1,"Nouveau","Fidèle")) -> Fidèle
A21: =IF(B21="","",ROW()-5) -> 16 | B21: 46305 | C21: Awa Ndiaye | D21: 77 111 22 33 | E21: Dakar Plateau | F21: Pack 3 pagnes | G21: 1 | I21: =IF(F21="","",IF(H21="",IFERROR(INDEX(Catalogue!$I$6:$I$55,MATCH(F21,Catalogue!$B$6:$B$55,0)),0),H21)) -> 27000 | J21: 1000 | K21: =IF(F21="","",N(G21)*I21-N(J21)) -> 26000 | L21: Wave | M21: Livrée et payée | N21: Client fidèle | P21: =IF(F21="","",IF(O21="",IFERROR(INDEX(Catalogue!$G$6:$G$55,MATCH(F21,Catalogue!$B$6:$B$55,0)),0),O21)) -> 1500 | Q21: =IF(F21="","",N(G21)*(IFERROR(INDEX(Catalogue!$E$6:$E$55,MATCH(F21,Catalogue!$B$6:$B$55,0)),0)+IFERROR(INDEX(Catalogue!$F$6:$F$55,MATCH(F21,Catalogue!$B$6:$B$55,0)),0)+IFERROR(INDEX(Catalogue!$H$6:$H$55,MATCH(F21,Catalogue!$B$6:$B$55,0)),0))) -> 12400 | R21: =IF(F21="","",IF(M21="Livrée et payée",K21-Q21-P21,IF(M21="Annulée",-N(P21),0))) -> 12100 | S21: Oui | T21: =IF(B21="","",DATE(YEAR(B21),MONTH(B21),1)) -> 46296 | U21: =IF(D21="","",IF(COUNTIF(D$6:D21,D21)=1,"Nouveau","Fidèle")) -> Fidèle
A22: =IF(B22="","",ROW()-5) -> 17 | B22: 46304 | C22: Fatou Sow | D22: 77 444 55 66 | E22: Dakar banlieue | F22: Pagne wax 6 yards | G22: 1 | I22: =IF(F22="","",IF(H22="",IFERROR(INDEX(Catalogue!$I$6:$I$55,MATCH(F22,Catalogue!$B$6:$B$55,0)),0),H22)) -> 10000 | K22: =IF(F22="","",N(G22)*I22-N(J22)) -> 10000 | L22: Wave | M22: Livrée et payée | N22: Publicité | P22: =IF(F22="","",IF(O22="",IFERROR(INDEX(Catalogue!$G$6:$G$55,MATCH(F22,Catalogue!$B$6:$B$55,0)),0),O22)) -> 1500 | Q22: =IF(F22="","",N(G22)*(IFERROR(INDEX(Catalogue!$E$6:$E$55,MATCH(F22,Catalogue!$B$6:$B$55,0)),0)+IFERROR(INDEX(Catalogue!$F$6:$F$55,MATCH(F22,Catalogue!$B$6:$B$55,0)),0)+IFERROR(INDEX(Catalogue!$H$6:$H$55,MATCH(F22,Catalogue!$B$6:$B$55,0)),0))) -> 4300 | R22: =IF(F22="","",IF(M22="Livrée et payée",K22-Q22-P22,IF(M22="Annulée",-N(P22),0))) -> 4200 | S22: Oui | T22: =IF(B22="","",DATE(YEAR(B22),MONTH(B22),1)) -> 46296 | U22: =IF(D22="","",IF(COUNTIF(D$6:D22,D22)=1,"Nouveau","Fidèle")) -> Fidèle
A23: =IF(B23="","",ROW()-5) -> 18 | B23: 46305 | C23: Aminata Diop | D23: 70 555 66 77 | E23: Thiès | F23: Pagne wax 6 yards | G23: 1 | I23: =IF(F23="","",IF(H23="",IFERROR(INDEX(Catalogue!$I$6:$I$55,MATCH(F23,Catalogue!$B$6:$B$55,0)),0),H23)) -> 10000 | K23: =IF(F23="","",N(G23)*I23-N(J23)) -> 10000 | L23: Orange Money | M23: Livrée et payée | N23: Publicité | P23: =IF(F23="","",IF(O23="",IFERROR(INDEX(Catalogue!$G$6:$G$55,MATCH(F23,Catalogue!$B$6:$B$55,0)),0),O23)) -> 1500 | Q23: =IF(F23="","",N(G23)*(IFERROR(INDEX(Catalogue!$E$6:$E$55,MATCH(F23,Catalogue!$B$6:$B$55,0)),0)+IFERROR(INDEX(Catalogue!$F$6:$F$55,MATCH(F23,Catalogue!$B$6:$B$55,0)),0)+IFERROR(INDEX(Catalogue!$H$6:$H$55,MATCH(F23,Catalogue!$B$6:$B$55,0)),0))) -> 4300 | R23: =IF(F23="","",IF(M23="Livrée et payée",K23-Q23-P23,IF(M23="Annulée",-N(P23),0))) -> 4200 | S23: Non | T23: =IF(B23="","",DATE(YEAR(B23),MONTH(B23),1)) -> 46296 | U23: =IF(D23="","",IF(COUNTIF(D$6:D23,D23)=1,"Nouveau","Fidèle")) -> Fidèle
A24: =IF(B24="","",ROW()-5) -> 19 | B24: 46305 | C24: Coumba Gueye | D24: 77 777 88 99 | E24: Dakar banlieue | F24: Conseil style à domicile | G24: 1 | I24: =IF(F24="","",IF(H24="",IFERROR(INDEX(Catalogue!$I$6:$I$55,MATCH(F24,Catalogue!$B$6:$B$55,0)),0),H24)) -> 7500 | K24: =IF(F24="","",N(G24)*I24-N(J24)) -> 7500 | L24: Wave | M24: Livrée et payée | N24: Direct vidéo | P24: =IF(F24="","",IF(O24="",IFERROR(INDEX(Catalogue!$G$6:$G$55,MATCH(F24,Catalogue!$B$6:$B$55,0)),0),O24)) -> 0 | Q24: =IF(F24="","",N(G24)*(IFERROR(INDEX(Catalogue!$E$6:$E$55,MATCH(F24,Catalogue!$B$6:$B$55,0)),0)+IFERROR(INDEX(Catalogue!$F$6:$F$55,MATCH(F24,Catalogue!$B$6:$B$55,0)),0)+IFERROR(INDEX(Catalogue!$H$6:$H$55,MATCH(F24,Catalogue!$B$6:$B$55,0)),0))) -> 2000 | R24: =IF(F24="","",IF(M24="Livrée et payée",K24-Q24-P24,IF(M24="Annulée",-N(P24),0))) -> 5500 | S24: Non | T24: =IF(B24="","",DATE(YEAR(B24),MONTH(B24),1)) -> 46296 | U24: =IF(D24="","",IF(COUNTIF(D$6:D24,D24)=1,"Nouveau","Fidèle")) -> Fidèle
A25: =IF(B25="","",ROW()-5) -> 20 | B25: 46307 | C25: Mariama Ba | D25: 76 222 33 44 | E25: Pikine / Guédiawaye | F25: Foulard assorti | G25: 1 | I25: =IF(F25="","",IF(H25="",IFERROR(INDEX(Catalogue!$I$6:$I$55,MATCH(F25,Catalogue!$B$6:$B$55,0)),0),H25)) -> 3500 | K25: =IF(F25="","",N(G25)*I25-N(J25)) -> 3500 | L25: Wave | M25: En attente | N25: Client fidèle | P25: =IF(F25="","",IF(O25="",IFERROR(INDEX(Catalogue!$G$6:$G$55,MATCH(F25,Catalogue!$B$6:$B$55,0)),0),O25)) -> 0 | Q25: =IF(F25="","",N(G25)*(IFERROR(INDEX(Catalogue!$E$6:$E$55,MATCH(F25,Catalogue!$B$6:$B$55,0)),0)+IFERROR(INDEX(Catalogue!$F$6:$F$55,MATCH(F25,Catalogue!$B$6:$B$55,0)),0)+IFERROR(INDEX(Catalogue!$H$6:$H$55,MATCH(F25,Catalogue!$B$6:$B$55,0)),0))) -> 1350 | R25: =IF(F25="","",IF(M25="Livrée et payée",K25-Q25-P25,IF(M25="Annulée",-N(P25),0))) -> 0 | S25: Non | T25: =IF(B25="","",DATE(YEAR(B25),MONTH(B25),1)) -> 46296 | U25: =IF(D25="","",IF(COUNTIF(D$6:D25,D25)=1,"Nouveau","Fidèle")) -> Fidèle
A26: =IF(B26="","",ROW()-5) | I26: =IF(F26="","",IF(H26="",IFERROR(INDEX(Catalogue!$I$6:$I$55,MATCH(F26,Catalogue!$B$6:$B$55,0)),0),H26)) | K26: =IF(F26="","",N(G26)*I26-N(J26)) | P26: =IF(F26="","",IF(O26="",IFERROR(INDEX(Catalogue!$G$6:$G$55,MATCH(F26,Catalogue!$B$6:$B$55,0)),0),O26)) | Q26: =IF(F26="","",N(G26)*(IFERROR(INDEX(Catalogue!$E$6:$E$55,MATCH(F26,Catalogue!$B$6:$B$55,0)),0)+IFERROR(INDEX(Catalogue!$F$6:$F$55,MATCH(F26,Catalogue!$B$6:$B$55,0)),0)+IFERROR(INDEX(Catalogue!$H$6:$H$55,MATCH(F26,Catalogue!$B$6:$B$55,0)),0))) | R26: =IF(F26="","",IF(M26="Livrée et payée",K26-Q26-P26,IF(M26="Annulée",-N(P26),0))) | T26: =IF(B26="","",DATE(YEAR(B26),MONTH(B26),1)) | U26: =IF(D26="","",IF(COUNTIF(D$6:D26,D26)=1,"Nouveau","Fidèle"))
A27: =IF(B27="","",ROW()-5) | I27: =IF(F27="","",IF(H27="",IFERROR(INDEX(Catalogue!$I$6:$I$55,MATCH(F27,Catalogue!$B$6:$B$55,0)),0),H27)) | K27: =IF(F27="","",N(G27)*I27-N(J27)) | P27: =IF(F27="","",IF(O27="",IFERROR(INDEX(Catalogue!$G$6:$G$55,MATCH(F27,Catalogue!$B$6:$B$55,0)),0),O27)) | Q27: =IF(F27="","",N(G27)*(IFERROR(INDEX(Catalogue!$E$6:$E$55,MATCH(F27,Catalogue!$B$6:$B$55,0)),0)+IFERROR(INDEX(Catalogue!$F$6:$F$55,MATCH(F27,Catalogue!$B$6:$B$55,0)),0)+IFERROR(INDEX(Catalogue!$H$6:$H$55,MATCH(F27,Catalogue!$B$6:$B$55,0)),0))) | R27: =IF(F27="","",IF(M27="Livrée et payée",K27-Q27-P27,IF(M27="Annulée",-N(P27),0))) | T27: =IF(B27="","",DATE(YEAR(B27),MONTH(B27),1)) | U27: =IF(D27="","",IF(COUNTIF(D$6:D27,D27)=1,"Nouveau","Fidèle"))
A28: =IF(B28="","",ROW()-5) | I28: =IF(F28="","",IF(H28="",IFERROR(INDEX(Catalogue!$I$6:$I$55,MATCH(F28,Catalogue!$B$6:$B$55,0)),0),H28)) | K28: =IF(F28="","",N(G28)*I28-N(J28)) | P28: =IF(F28="","",IF(O28="",IFERROR(INDEX(Catalogue!$G$6:$G$55,MATCH(F28,Catalogue!$B$6:$B$55,0)),0),O28)) | Q28: =IF(F28="","",N(G28)*(IFERROR(INDEX(Catalogue!$E$6:$E$55,MATCH(F28,Catalogue!$B$6:$B$55,0)),0)+IFERROR(INDEX(Catalogue!$F$6:$F$55,MATCH(F28,Catalogue!$B$6:$B$55,0)),0)+IFERROR(INDEX(Catalogue!$H$6:$H$55,MATCH(F28,Catalogue!$B$6:$B$55,0)),0))) | R28: =IF(F28="","",IF(M28="Livrée et payée",K28-Q28-P28,IF(M28="Annulée",-N(P28),0))) | T28: =IF(B28="","",DATE(YEAR(B28),MONTH(B28),1)) | U28: =IF(D28="","",IF(COUNTIF(D$6:D28,D28)=1,"Nouveau","Fidèle"))
A29: =IF(B29="","",ROW()-5) | I29: =IF(F29="","",IF(H29="",IFERROR(INDEX(Catalogue!$I$6:$I$55,MATCH(F29,Catalogue!$B$6:$B$55,0)),0),H29)) | K29: =IF(F29="","",N(G29)*I29-N(J29)) | P29: =IF(F29="","",IF(O29="",IFERROR(INDEX(Catalogue!$G$6:$G$55,MATCH(F29,Catalogue!$B$6:$B$55,0)),0),O29)) | Q29: =IF(F29="","",N(G29)*(IFERROR(INDEX(Catalogue!$E$6:$E$55,MATCH(F29,Catalogue!$B$6:$B$55,0)),0)+IFERROR(INDEX(Catalogue!$F$6:$F$55,MATCH(F29,Catalogue!$B$6:$B$55,0)),0)+IFERROR(INDEX(Catalogue!$H$6:$H$55,MATCH(F29,Catalogue!$B$6:$B$55,0)),0))) | R29: =IF(F29="","",IF(M29="Livrée et payée",K29-Q29-P29,IF(M29="Annulée",-N(P29),0))) | T29: =IF(B29="","",DATE(YEAR(B29),MONTH(B29),1)) | U29: =IF(D29="","",IF(COUNTIF(D$6:D29,D29)=1,"Nouveau","Fidèle"))
A30: =IF(B30="","",ROW()-5) | I30: =IF(F30="","",IF(H30="",IFERROR(INDEX(Catalogue!$I$6:$I$55,MATCH(F30,Catalogue!$B$6:$B$55,0)),0),H30)) | K30: =IF(F30="","",N(G30)*I30-N(J30)) | P30: =IF(F30="","",IF(O30="",IFERROR(INDEX(Catalogue!$G$6:$G$55,MATCH(F30,Catalogue!$B$6:$B$55,0)),0),O30)) | Q30: =IF(F30="","",N(G30)*(IFERROR(INDEX(Catalogue!$E$6:$E$55,MATCH(F30,Catalogue!$B$6:$B$55,0)),0)+IFERROR(INDEX(Catalogue!$F$6:$F$55,MATCH(F30,Catalogue!$B$6:$B$55,0)),0)+IFERROR(INDEX(Catalogue!$H$6:$H$55,MATCH(F30,Catalogue!$B$6:$B$55,0)),0))) | R30: =IF(F30="","",IF(M30="Livrée et payée",K30-Q30-P30,IF(M30="Annulée",-N(P30),0))) | T30: =IF(B30="","",DATE(YEAR(B30),MONTH(B30),1)) | U30: =IF(D30="","",IF(COUNTIF(D$6:D30,D30)=1,"Nouveau","Fidèle"))
A31: =IF(B31="","",ROW()-5) | I31: =IF(F31="","",IF(H31="",IFERROR(INDEX(Catalogue!$I$6:$I$55,MATCH(F31,Catalogue!$B$6:$B$55,0)),0),H31)) | K31: =IF(F31="","",N(G31)*I31-N(J31)) | P31: =IF(F31="","",IF(O31="",IFERROR(INDEX(Catalogue!$G$6:$G$55,MATCH(F31,Catalogue!$B$6:$B$55,0)),0),O31)) | Q31: =IF(F31="","",N(G31)*(IFERROR(INDEX(Catalogue!$E$6:$E$55,MATCH(F31,Catalogue!$B$6:$B$55,0)),0)+IFERROR(INDEX(Catalogue!$F$6:$F$55,MATCH(F31,Catalogue!$B$6:$B$55,0)),0)+IFERROR(INDEX(Catalogue!$H$6:$H$55,MATCH(F31,Catalogue!$B$6:$B$55,0)),0))) | R31: =IF(F31="","",IF(M31="Livrée et payée",K31-Q31-P31,IF(M31="Annulée",-N(P31),0))) | T31: =IF(B31="","",DATE(YEAR(B31),MONTH(B31),1)) | U31: =IF(D31="","",IF(COUNTIF(D$6:D31,D31)=1,"Nouveau","Fidèle"))
A32: =IF(B32="","",ROW()-5) | I32: =IF(F32="","",IF(H32="",IFERROR(INDEX(Catalogue!$I$6:$I$55,MATCH(F32,Catalogue!$B$6:$B$55,0)),0),H32)) | K32: =IF(F32="","",N(G32)*I32-N(J32)) | P32: =IF(F32="","",IF(O32="",IFERROR(INDEX(Catalogue!$G$6:$G$55,MATCH(F32,Catalogue!$B$6:$B$55,0)),0),O32)) | Q32: =IF(F32="","",N(G32)*(IFERROR(INDEX(Catalogue!$E$6:$E$55,MATCH(F32,Catalogue!$B$6:$B$55,0)),0)+IFERROR(INDEX(Catalogue!$F$6:$F$55,MATCH(F32,Catalogue!$B$6:$B$55,0)),0)+IFERROR(INDEX(Catalogue!$H$6:$H$55,MATCH(F32,Catalogue!$B$6:$B$55,0)),0))) | R32: =IF(F32="","",IF(M32="Livrée et payée",K32-Q32-P32,IF(M32="Annulée",-N(P32),0))) | T32: =IF(B32="","",DATE(YEAR(B32),MONTH(B32),1)) | U32: =IF(D32="","",IF(COUNTIF(D$6:D32,D32)=1,"Nouveau","Fidèle"))
A33: =IF(B33="","",ROW()-5) | I33: =IF(F33="","",IF(H33="",IFERROR(INDEX(Catalogue!$I$6:$I$55,MATCH(F33,Catalogue!$B$6:$B$55,0)),0),H33)) | K33: =IF(F33="","",N(G33)*I33-N(J33)) | P33: =IF(F33="","",IF(O33="",IFERROR(INDEX(Catalogue!$G$6:$G$55,MATCH(F33,Catalogue!$B$6:$B$55,0)),0),O33)) | Q33: =IF(F33="","",N(G33)*(IFERROR(INDEX(Catalogue!$E$6:$E$55,MATCH(F33,Catalogue!$B$6:$B$55,0)),0)+IFERROR(INDEX(Catalogue!$F$6:$F$55,MATCH(F33,Catalogue!$B$6:$B$55,0)),0)+IFERROR(INDEX(Catalogue!$H$6:$H$55,MATCH(F33,Catalogue!$B$6:$B$55,0)),0))) | R33: =IF(F33="","",IF(M33="Livrée et payée",K33-Q33-P33,IF(M33="Annulée",-N(P33),0))) | T33: =IF(B33="","",DATE(YEAR(B33),MONTH(B33),1)) | U33: =IF(D33="","",IF(COUNTIF(D$6:D33,D33)=1,"Nouveau","Fidèle"))
A34: =IF(B34="","",ROW()-5) | I34: =IF(F34="","",IF(H34="",IFERROR(INDEX(Catalogue!$I$6:$I$55,MATCH(F34,Catalogue!$B$6:$B$55,0)),0),H34)) | K34: =IF(F34="","",N(G34)*I34-N(J34)) | P34: =IF(F34="","",IF(O34="",IFERROR(INDEX(Catalogue!$G$6:$G$55,MATCH(F34,Catalogue!$B$6:$B$55,0)),0),O34)) | Q34: =IF(F34="","",N(G34)*(IFERROR(INDEX(Catalogue!$E$6:$E$55,MATCH(F34,Catalogue!$B$6:$B$55,0)),0)+IFERROR(INDEX(Catalogue!$F$6:$F$55,MATCH(F34,Catalogue!$B$6:$B$55,0)),0)+IFERROR(INDEX(Catalogue!$H$6:$H$55,MATCH(F34,Catalogue!$B$6:$B$55,0)),0))) | R34: =IF(F34="","",IF(M34="Livrée et payée",K34-Q34-P34,IF(M34="Annulée",-N(P34),0))) | T34: =IF(B34="","",DATE(YEAR(B34),MONTH(B34),1)) | U34: =IF(D34="","",IF(COUNTIF(D$6:D34,D34)=1,"Nouveau","Fidèle"))
A35: =IF(B35="","",ROW()-5) | I35: =IF(F35="","",IF(H35="",IFERROR(INDEX(Catalogue!$I$6:$I$55,MATCH(F35,Catalogue!$B$6:$B$55,0)),0),H35)) | K35: =IF(F35="","",N(G35)*I35-N(J35)) | P35: =IF(F35="","",IF(O35="",IFERROR(INDEX(Catalogue!$G$6:$G$55,MATCH(F35,Catalogue!$B$6:$B$55,0)),0),O35)) | Q35: =IF(F35="","",N(G35)*(IFERROR(INDEX(Catalogue!$E$6:$E$55,MATCH(F35,Catalogue!$B$6:$B$55,0)),0)+IFERROR(INDEX(Catalogue!$F$6:$F$55,MATCH(F35,Catalogue!$B$6:$B$55,0)),0)+IFERROR(INDEX(Catalogue!$H$6:$H$55,MATCH(F35,Catalogue!$B$6:$B$55,0)),0))) | R35: =IF(F35="","",IF(M35="Livrée et payée",K35-Q35-P35,IF(M35="Annulée",-N(P35),0))) | T35: =IF(B35="","",DATE(YEAR(B35),MONTH(B35),1)) | U35: =IF(D35="","",IF(COUNTIF(D$6:D35,D35)=1,"Nouveau","Fidèle"))
A36: =IF(B36="","",ROW()-5) | I36: =IF(F36="","",IF(H36="",IFERROR(INDEX(Catalogue!$I$6:$I$55,MATCH(F36,Catalogue!$B$6:$B$55,0)),0),H36)) | K36: =IF(F36="","",N(G36)*I36-N(J36)) | P36: =IF(F36="","",IF(O36="",IFERROR(INDEX(Catalogue!$G$6:$G$55,MATCH(F36,Catalogue!$B$6:$B$55,0)),0),O36)) | Q36: =IF(F36="","",N(G36)*(IFERROR(INDEX(Catalogue!$E$6:$E$55,MATCH(F36,Catalogue!$B$6:$B$55,0)),0)+IFERROR(INDEX(Catalogue!$F$6:$F$55,MATCH(F36,Catalogue!$B$6:$B$55,0)),0)+IFERROR(INDEX(Catalogue!$H$6:$H$55,MATCH(F36,Catalogue!$B$6:$B$55,0)),0))) | R36: =IF(F36="","",IF(M36="Livrée et payée",K36-Q36-P36,IF(M36="Annulée",-N(P36),0))) | T36: =IF(B36="","",DATE(YEAR(B36),MONTH(B36),1)) | U36: =IF(D36="","",IF(COUNTIF(D$6:D36,D36)=1,"Nouveau","Fidèle"))
A37: =IF(B37="","",ROW()-5) | I37: =IF(F37="","",IF(H37="",IFERROR(INDEX(Catalogue!$I$6:$I$55,MATCH(F37,Catalogue!$B$6:$B$55,0)),0),H37)) | K37: =IF(F37="","",N(G37)*I37-N(J37)) | P37: =IF(F37="","",IF(O37="",IFERROR(INDEX(Catalogue!$G$6:$G$55,MATCH(F37,Catalogue!$B$6:$B$55,0)),0),O37)) | Q37: =IF(F37="","",N(G37)*(IFERROR(INDEX(Catalogue!$E$6:$E$55,MATCH(F37,Catalogue!$B$6:$B$55,0)),0)+IFERROR(INDEX(Catalogue!$F$6:$F$55,MATCH(F37,Catalogue!$B$6:$B$55,0)),0)+IFERROR(INDEX(Catalogue!$H$6:$H$55,MATCH(F37,Catalogue!$B$6:$B$55,0)),0))) | R37: =IF(F37="","",IF(M37="Livrée et payée",K37-Q37-P37,IF(M37="Annulée",-N(P37),0))) | T37: =IF(B37="","",DATE(YEAR(B37),MONTH(B37),1)) | U37: =IF(D37="","",IF(COUNTIF(D$6:D37,D37)=1,"Nouveau","Fidèle"))
... A505: =IF(B505="","",ROW()-5) | I505: =IF(F505="","",IF(H505="",IFERROR(INDEX(Catalogue!$I$6:$I$55,MATCH(F505,Catalogue!$B$6:$B$55,0)),0),H505)) | K505: =IF(F505="","",N(G505)*I505-N(J505)) | P505: =IF(F505="","",IF(O505="",IFERROR(INDEX(Catalogue!$G$6:$G$55,MATCH(F505,Catalogue!$B$6:$B$55,0)),0),O505)) | Q505: =IF(F505="","",N(G505)*(IFERROR(INDEX(Catalogue!$E$6:$E$55,MATCH(F505,Catalogue!$B$6:$B$55,0)),0)+IFERROR(INDEX(Catalogue!$F$6:$F$55,MATCH(F505,Catalogue!$B$6:$B$55,0)),0)+IFERROR(INDEX(Catalogue!$H$6:$H$55,MATCH(F505,Catalogue!$B$6:$B$55,0)),0))) | R505: =IF(F505="","",IF(M505="Livrée et payée",K505-Q505-P505,IF(M505="Annulée",-N(P505),0))) | T505: =IF(B505="","",DATE(YEAR(B505),MONTH(B505),1)) | U505: =IF(D505="","",IF(COUNTIF(D$6:D505,D505)=1,"Nouveau","Fidèle"))

Sheet Clients
A1: Liste des clients
A2: Saisis le téléphone exactement comme dans Ventes. Le reste se calcule seul. Segments : nouveau, fidèle (2 achats), VIP (3 et plus), à relancer (plus de 60 jours).
A3: Cellules jaunes : à remplir · cellules grises : calculées automatiquement (ne pas modifier)
A5: Téléphone | B5: Nom | C5: Zone | D5: Commandes livrées | E5: Montant total | F5: Dernière commande | G5: Jours depuis | H5: Annulations | I5: Segment | J5: Paiement avant livraison ? | K5: Notes
A6: 77 111 22 33 | B6: Awa Ndiaye | C6: Dakar Plateau | D6: =IF(A6="","",COUNTIFS(Ventes!$D$6:$D$505,A6,Ventes!$M$6:$M$505,"Livrée et payée")) -> 3 | E6: =IF(A6="","",SUMIFS(Ventes!$K$6:$K$505,Ventes!$D$6:$D$505,A6,Ventes!$M$6:$M$505,"Livrée et payée")) -> 43500 | F6: =IF(A6="","",IF(D6=0,"",_xlfn.MAXIFS(Ventes!$B$6:$B$505,Ventes!$D$6:$D$505,A6,Ventes!$M$6:$M$505,"Livrée et payée"))) -> 46305 | G6: =IF(OR(A6="",F6=""),"",TODAY()-F6) -> 4 | H6: =IF(A6="","",COUNTIFS(Ventes!$D$6:$D$505,A6,Ventes!$M$6:$M$505,"Annulée")) -> 0 | I6: =IF(A6="","",IF(D6=0,"Prospect",IF(G6>60,"À relancer",IF(D6>=3,"VIP",IF(D6=2,"Fidèle","Nouveau"))))) -> VIP | J6: =IF(A6="","",IF(H6>=1,"Oui (a déjà annulé)","Non")) -> Non
A7: 76 222 33 44 | B7: Mariama Ba | C7: Pikine / Guédiawaye | D7: =IF(A7="","",COUNTIFS(Ventes!$D$6:$D$505,A7,Ventes!$M$6:$M$505,"Livrée et payée")) -> 2 | E7: =IF(A7="","",SUMIFS(Ventes!$K$6:$K$505,Ventes!$D$6:$D$505,A7,Ventes!$M$6:$M$505,"Livrée et payée")) -> 27000 | F7: =IF(A7="","",IF(D7=0,"",_xlfn.MAXIFS(Ventes!$B$6:$B$505,Ventes!$D$6:$D$505,A7,Ventes!$M$6:$M$505,"Livrée et payée"))) -> 46297 | G7: =IF(OR(A7="",F7=""),"",TODAY()-F7) -> 12 | H7: =IF(A7="","",COUNTIFS(Ventes!$D$6:$D$505,A7,Ventes!$M$6:$M$505,"Annulée")) -> 0 | I7: =IF(A7="","",IF(D7=0,"Prospect",IF(G7>60,"À relancer",IF(D7>=3,"VIP",IF(D7=2,"Fidèle","Nouveau"))))) -> Fidèle | J7: =IF(A7="","",IF(H7>=1,"Oui (a déjà annulé)","Non")) -> Non
A8: 78 333 44 55 | B8: Khady Fall | C8: Rufisque | D8: =IF(A8="","",COUNTIFS(Ventes!$D$6:$D$505,A8,Ventes!$M$6:$M$505,"Livrée et payée")) -> 2 | E8: =IF(A8="","",SUMIFS(Ventes!$K$6:$K$505,Ventes!$D$6:$D$505,A8,Ventes!$M$6:$M$505,"Livrée et payée")) -> 36000 | F8: =IF(A8="","",IF(D8=0,"",_xlfn.MAXIFS(Ventes!$B$6:$B$505,Ventes!$D$6:$D$505,A8,Ventes!$M$6:$M$505,"Livrée et payée"))) -> 46302 | G8: =IF(OR(A8="",F8=""),"",TODAY()-F8) -> 7 | H8: =IF(A8="","",COUNTIFS(Ventes!$D$6:$D$505,A8,Ventes!$M$6:$M$505,"Annulée")) -> 0 | I8: =IF(A8="","",IF(D8=0,"Prospect",IF(G8>60,"À relancer",IF(D8>=3,"VIP",IF(D8=2,"Fidèle","Nouveau"))))) -> Fidèle | J8: =IF(A8="","",IF(H8>=1,"Oui (a déjà annulé)","Non")) -> Non
A9: 77 444 55 66 | B9: Fatou Sow | C9: Dakar banlieue | D9: =IF(A9="","",COUNTIFS(Ventes!$D$6:$D$505,A9,Ventes!$M$6:$M$505,"Livrée et payée")) -> 3 | E9: =IF(A9="","",SUMIFS(Ventes!$K$6:$K$505,Ventes!$D$6:$D$505,A9,Ventes!$M$6:$M$505,"Livrée et payée")) -> 46500 | F9: =IF(A9="","",IF(D9=0,"",_xlfn.MAXIFS(Ventes!$B$6:$B$505,Ventes!$D$6:$D$505,A9,Ventes!$M$6:$M$505,"Livrée et payée"))) -> 46304 | G9: =IF(OR(A9="",F9=""),"",TODAY()-F9) -> 5 | H9: =IF(A9="","",COUNTIFS(Ventes!$D$6:$D$505,A9,Ventes!$M$6:$M$505,"Annulée")) -> 0 | I9: =IF(A9="","",IF(D9=0,"Prospect",IF(G9>60,"À relancer",IF(D9>=3,"VIP",IF(D9=2,"Fidèle","Nouveau"))))) -> VIP | J9: =IF(A9="","",IF(H9>=1,"Oui (a déjà annulé)","Non")) -> Non
A10: 70 555 66 77 | B10: Aminata Diop | C10: Thiès | D10: =IF(A10="","",COUNTIFS(Ventes!$D$6:$D$505,A10,Ventes!$M$6:$M$505,"Livrée et payée")) -> 3 | E10: =IF(A10="","",SUMIFS(Ventes!$K$6:$K$505,Ventes!$D$6:$D$505,A10,Ventes!$M$6:$M$505,"Livrée et payée")) -> 23500 | F10: =IF(A10="","",IF(D10=0,"",_xlfn.MAXIFS(Ventes!$B$6:$B$505,Ventes!$D$6:$D$505,A10,Ventes!$M$6:$M$505,"Livrée et payée"))) -> 46305 | G10: =IF(OR(A10="",F10=""),"",TODAY()-F10) -> 4 | H10: =IF(A10="","",COUNTIFS(Ventes!$D$6:$D$505,A10,Ventes!$M$6:$M$505,"Annulée")) -> 0 | I10: =IF(A10="","",IF(D10=0,"Prospect",IF(G10>60,"À relancer",IF(D10>=3,"VIP",IF(D10=2,"Fidèle","Nouveau"))))) -> VIP | J10: =IF(A10="","",IF(H10>=1,"Oui (a déjà annulé)","Non")) -> Non
A11: 76 666 77 88 | B11: Ndèye Sarr | C11: Dakar Plateau | D11: =IF(A11="","",COUNTIFS(Ventes!$D$6:$D$505,A11,Ventes!$M$6:$M$505,"Livrée et payée")) -> 1 | E11: =IF(A11="","",SUMIFS(Ventes!$K$6:$K$505,Ventes!$D$6:$D$505,A11,Ventes!$M$6:$M$505,"Livrée et payée")) -> 10000 | F11: =IF(A11="","",IF(D11=0,"",_xlfn.MAXIFS(Ventes!$B$6:$B$505,Ventes!$D$6:$D$505,A11,Ventes!$M$6:$M$505,"Livrée et payée"))) -> 46303 | G11: =IF(OR(A11="",F11=""),"",TODAY()-F11) -> 6 | H11: =IF(A11="","",COUNTIFS(Ventes!$D$6:$D$505,A11,Ventes!$M$6:$M$505,"Annulée")) -> 1 | I11: =IF(A11="","",IF(D11=0,"Prospect",IF(G11>60,"À relancer",IF(D11>=3,"VIP",IF(D11=2,"Fidèle","Nouveau"))))) -> Nouveau | J11: =IF(A11="","",IF(H11>=1,"Oui (a déjà annulé)","Non")) -> Oui (a déjà annulé)
A12: 77 777 88 99 | B12: Coumba Gueye | C12: Dakar banlieue | D12: =IF(A12="","",COUNTIFS(Ventes!$D$6:$D$505,A12,Ventes!$M$6:$M$505,"Livrée et payée")) -> 2 | E12: =IF(A12="","",SUMIFS(Ventes!$K$6:$K$505,Ventes!$D$6:$D$505,A12,Ventes!$M$6:$M$505,"Livrée et payée")) -> 17500 | F12: =IF(A12="","",IF(D12=0,"",_xlfn.MAXIFS(Ventes!$B$6:$B$505,Ventes!$D$6:$D$505,A12,Ventes!$M$6:$M$505,"Livrée et payée"))) -> 46305 | G12: =IF(OR(A12="",F12=""),"",TODAY()-F12) -> 4 | H12: =IF(A12="","",COUNTIFS(Ventes!$D$6:$D$505,A12,Ventes!$M$6:$M$505,"Annulée")) -> 0 | I12: =IF(A12="","",IF(D12=0,"Prospect",IF(G12>60,"À relancer",IF(D12>=3,"VIP",IF(D12=2,"Fidèle","Nouveau"))))) -> Fidèle | J12: =IF(A12="","",IF(H12>=1,"Oui (a déjà annulé)","Non")) -> Non
A13: 78 888 99 00 | B13: Bineta Cissé | C13: Pikine / Guédiawaye | D13: =IF(A13="","",COUNTIFS(Ventes!$D$6:$D$505,A13,Ventes!$M$6:$M$505,"Livrée et payée")) -> 1 | E13: =IF(A13="","",SUMIFS(Ventes!$K$6:$K$505,Ventes!$D$6:$D$505,A13,Ventes!$M$6:$M$505,"Livrée et payée")) -> 10000 | F13: =IF(A13="","",IF(D13=0,"",_xlfn.MAXIFS(Ventes!$B$6:$B$505,Ventes!$D$6:$D$505,A13,Ventes!$M$6:$M$505,"Livrée et payée"))) -> 46301 | G13: =IF(OR(A13="",F13=""),"",TODAY()-F13) -> 8 | H13: =IF(A13="","",COUNTIFS(Ventes!$D$6:$D$505,A13,Ventes!$M$6:$M$505,"Annulée")) -> 1 | I13: =IF(A13="","",IF(D13=0,"Prospect",IF(G13>60,"À relancer",IF(D13>=3,"VIP",IF(D13=2,"Fidèle","Nouveau"))))) -> Nouveau | J13: =IF(A13="","",IF(H13>=1,"Oui (a déjà annulé)","Non")) -> Oui (a déjà annulé)
D14: =IF(A14="","",COUNTIFS(Ventes!$D$6:$D$505,A14,Ventes!$M$6:$M$505,"Livrée et payée")) | E14: =IF(A14="","",SUMIFS(Ventes!$K$6:$K$505,Ventes!$D$6:$D$505,A14,Ventes!$M$6:$M$505,"Livrée et payée")) | F14: =IF(A14="","",IF(D14=0,"",_xlfn.MAXIFS(Ventes!$B$6:$B$505,Ventes!$D$6:$D$505,A14,Ventes!$M$6:$M$505,"Livrée et payée"))) | G14: =IF(OR(A14="",F14=""),"",TODAY()-F14) | H14: =IF(A14="","",COUNTIFS(Ventes!$D$6:$D$505,A14,Ventes!$M$6:$M$505,"Annulée")) | I14: =IF(A14="","",IF(D14=0,"Prospect",IF(G14>60,"À relancer",IF(D14>=3,"VIP",IF(D14=2,"Fidèle","Nouveau"))))) | J14: =IF(A14="","",IF(H14>=1,"Oui (a déjà annulé)","Non"))
D15: =IF(A15="","",COUNTIFS(Ventes!$D$6:$D$505,A15,Ventes!$M$6:$M$505,"Livrée et payée")) | E15: =IF(A15="","",SUMIFS(Ventes!$K$6:$K$505,Ventes!$D$6:$D$505,A15,Ventes!$M$6:$M$505,"Livrée et payée")) | F15: =IF(A15="","",IF(D15=0,"",_xlfn.MAXIFS(Ventes!$B$6:$B$505,Ventes!$D$6:$D$505,A15,Ventes!$M$6:$M$505,"Livrée et payée"))) | G15: =IF(OR(A15="",F15=""),"",TODAY()-F15) | H15: =IF(A15="","",COUNTIFS(Ventes!$D$6:$D$505,A15,Ventes!$M$6:$M$505,"Annulée")) | I15: =IF(A15="","",IF(D15=0,"Prospect",IF(G15>60,"À relancer",IF(D15>=3,"VIP",IF(D15=2,"Fidèle","Nouveau"))))) | J15: =IF(A15="","",IF(H15>=1,"Oui (a déjà annulé)","Non"))
D16: =IF(A16="","",COUNTIFS(Ventes!$D$6:$D$505,A16,Ventes!$M$6:$M$505,"Livrée et payée")) | E16: =IF(A16="","",SUMIFS(Ventes!$K$6:$K$505,Ventes!$D$6:$D$505,A16,Ventes!$M$6:$M$505,"Livrée et payée")) | F16: =IF(A16="","",IF(D16=0,"",_xlfn.MAXIFS(Ventes!$B$6:$B$505,Ventes!$D$6:$D$505,A16,Ventes!$M$6:$M$505,"Livrée et payée"))) | G16: =IF(OR(A16="",F16=""),"",TODAY()-F16) | H16: =IF(A16="","",COUNTIFS(Ventes!$D$6:$D$505,A16,Ventes!$M$6:$M$505,"Annulée")) | I16: =IF(A16="","",IF(D16=0,"Prospect",IF(G16>60,"À relancer",IF(D16>=3,"VIP",IF(D16=2,"Fidèle","Nouveau"))))) | J16: =IF(A16="","",IF(H16>=1,"Oui (a déjà annulé)","Non"))
D17: =IF(A17="","",COUNTIFS(Ventes!$D$6:$D$505,A17,Ventes!$M$6:$M$505,"Livrée et payée")) | E17: =IF(A17="","",SUMIFS(Ventes!$K$6:$K$505,Ventes!$D$6:$D$505,A17,Ventes!$M$6:$M$505,"Livrée et payée")) | F17: =IF(A17="","",IF(D17=0,"",_xlfn.MAXIFS(Ventes!$B$6:$B$505,Ventes!$D$6:$D$505,A17,Ventes!$M$6:$M$505,"Livrée et payée"))) | G17: =IF(OR(A17="",F17=""),"",TODAY()-F17) | H17: =IF(A17="","",COUNTIFS(Ventes!$D$6:$D$505,A17,Ventes!$M$6:$M$505,"Annulée")) | I17: =IF(A17="","",IF(D17=0,"Prospect",IF(G17>60,"À relancer",IF(D17>=3,"VIP",IF(D17=2,"Fidèle","Nouveau"))))) | J17: =IF(A17="","",IF(H17>=1,"Oui (a déjà annulé)","Non"))
D18: =IF(A18="","",COUNTIFS(Ventes!$D$6:$D$505,A18,Ventes!$M$6:$M$505,"Livrée et payée")) | E18: =IF(A18="","",SUMIFS(Ventes!$K$6:$K$505,Ventes!$D$6:$D$505,A18,Ventes!$M$6:$M$505,"Livrée et payée")) | F18: =IF(A18="","",IF(D18=0,"",_xlfn.MAXIFS(Ventes!$B$6:$B$505,Ventes!$D$6:$D$505,A18,Ventes!$M$6:$M$505,"Livrée et payée"))) | G18: =IF(OR(A18="",F18=""),"",TODAY()-F18) | H18: =IF(A18="","",COUNTIFS(Ventes!$D$6:$D$505,A18,Ventes!$M$6:$M$505,"Annulée")) | I18: =IF(A18="","",IF(D18=0,"Prospect",IF(G18>60,"À relancer",IF(D18>=3,"VIP",IF(D18=2,"Fidèle","Nouveau"))))) | J18: =IF(A18="","",IF(H18>=1,"Oui (a déjà annulé)","Non"))
D19: =IF(A19="","",COUNTIFS(Ventes!$D$6:$D$505,A19,Ventes!$M$6:$M$505,"Livrée et payée")) | E19: =IF(A19="","",SUMIFS(Ventes!$K$6:$K$505,Ventes!$D$6:$D$505,A19,Ventes!$M$6:$M$505,"Livrée et payée")) | F19: =IF(A19="","",IF(D19=0,"",_xlfn.MAXIFS(Ventes!$B$6:$B$505,Ventes!$D$6:$D$505,A19,Ventes!$M$6:$M$505,"Livrée et payée"))) | G19: =IF(OR(A19="",F19=""),"",TODAY()-F19) | H19: =IF(A19="","",COUNTIFS(Ventes!$D$6:$D$505,A19,Ventes!$M$6:$M$505,"Annulée")) | I19: =IF(A19="","",IF(D19=0,"Prospect",IF(G19>60,"À relancer",IF(D19>=3,"VIP",IF(D19=2,"Fidèle","Nouveau"))))) | J19: =IF(A19="","",IF(H19>=1,"Oui (a déjà annulé)","Non"))
D20: =IF(A20="","",COUNTIFS(Ventes!$D$6:$D$505,A20,Ventes!$M$6:$M$505,"Livrée et payée")) | E20: =IF(A20="","",SUMIFS(Ventes!$K$6:$K$505,Ventes!$D$6:$D$505,A20,Ventes!$M$6:$M$505,"Livrée et payée")) | F20: =IF(A20="","",IF(D20=0,"",_xlfn.MAXIFS(Ventes!$B$6:$B$505,Ventes!$D$6:$D$505,A20,Ventes!$M$6:$M$505,"Livrée et payée"))) | G20: =IF(OR(A20="",F20=""),"",TODAY()-F20) | H20: =IF(A20="","",COUNTIFS(Ventes!$D$6:$D$505,A20,Ventes!$M$6:$M$505,"Annulée")) | I20: =IF(A20="","",IF(D20=0,"Prospect",IF(G20>60,"À relancer",IF(D20>=3,"VIP",IF(D20=2,"Fidèle","Nouveau"))))) | J20: =IF(A20="","",IF(H20>=1,"Oui (a déjà annulé)","Non"))
D21: =IF(A21="","",COUNTIFS(Ventes!$D$6:$D$505,A21,Ventes!$M$6:$M$505,"Livrée et payée")) | E21: =IF(A21="","",SUMIFS(Ventes!$K$6:$K$505,Ventes!$D$6:$D$505,A21,Ventes!$M$6:$M$505,"Livrée et payée")) | F21: =IF(A21="","",IF(D21=0,"",_xlfn.MAXIFS(Ventes!$B$6:$B$505,Ventes!$D$6:$D$505,A21,Ventes!$M$6:$M$505,"Livrée et payée"))) | G21: =IF(OR(A21="",F21=""),"",TODAY()-F21) | H21: =IF(A21="","",COUNTIFS(Ventes!$D$6:$D$505,A21,Ventes!$M$6:$M$505,"Annulée")) | I21: =IF(A21="","",IF(D21=0,"Prospect",IF(G21>60,"À relancer",IF(D21>=3,"VIP",IF(D21=2,"Fidèle","Nouveau"))))) | J21: =IF(A21="","",IF(H21>=1,"Oui (a déjà annulé)","Non"))
D22: =IF(A22="","",COUNTIFS(Ventes!$D$6:$D$505,A22,Ventes!$M$6:$M$505,"Livrée et payée")) | E22: =IF(A22="","",SUMIFS(Ventes!$K$6:$K$505,Ventes!$D$6:$D$505,A22,Ventes!$M$6:$M$505,"Livrée et payée")) | F22: =IF(A22="","",IF(D22=0,"",_xlfn.MAXIFS(Ventes!$B$6:$B$505,Ventes!$D$6:$D$505,A22,Ventes!$M$6:$M$505,"Livrée et payée"))) | G22: =IF(OR(A22="",F22=""),"",TODAY()-F22) | H22: =IF(A22="","",COUNTIFS(Ventes!$D$6:$D$505,A22,Ventes!$M$6:$M$505,"Annulée")) | I22: =IF(A22="","",IF(D22=0,"Prospect",IF(G22>60,"À relancer",IF(D22>=3,"VIP",IF(D22=2,"Fidèle","Nouveau"))))) | J22: =IF(A22="","",IF(H22>=1,"Oui (a déjà annulé)","Non"))
D23: =IF(A23="","",COUNTIFS(Ventes!$D$6:$D$505,A23,Ventes!$M$6:$M$505,"Livrée et payée")) | E23: =IF(A23="","",SUMIFS(Ventes!$K$6:$K$505,Ventes!$D$6:$D$505,A23,Ventes!$M$6:$M$505,"Livrée et payée")) | F23: =IF(A23="","",IF(D23=0,"",_xlfn.MAXIFS(Ventes!$B$6:$B$505,Ventes!$D$6:$D$505,A23,Ventes!$M$6:$M$505,"Livrée et payée"))) | G23: =IF(OR(A23="",F23=""),"",TODAY()-F23) | H23: =IF(A23="","",COUNTIFS(Ventes!$D$6:$D$505,A23,Ventes!$M$6:$M$505,"Annulée")) | I23: =IF(A23="","",IF(D23=0,"Prospect",IF(G23>60,"À relancer",IF(D23>=3,"VIP",IF(D23=2,"Fidèle","Nouveau"))))) | J23: =IF(A23="","",IF(H23>=1,"Oui (a déjà annulé)","Non"))
D24: =IF(A24="","",COUNTIFS(Ventes!$D$6:$D$505,A24,Ventes!$M$6:$M$505,"Livrée et payée")) | E24: =IF(A24="","",SUMIFS(Ventes!$K$6:$K$505,Ventes!$D$6:$D$505,A24,Ventes!$M$6:$M$505,"Livrée et payée")) | F24: =IF(A24="","",IF(D24=0,"",_xlfn.MAXIFS(Ventes!$B$6:$B$505,Ventes!$D$6:$D$505,A24,Ventes!$M$6:$M$505,"Livrée et payée"))) | G24: =IF(OR(A24="",F24=""),"",TODAY()-F24) | H24: =IF(A24="","",COUNTIFS(Ventes!$D$6:$D$505,A24,Ventes!$M$6:$M$505,"Annulée")) | I24: =IF(A24="","",IF(D24=0,"Prospect",IF(G24>60,"À relancer",IF(D24>=3,"VIP",IF(D24=2,"Fidèle","Nouveau"))))) | J24: =IF(A24="","",IF(H24>=1,"Oui (a déjà annulé)","Non"))
D25: =IF(A25="","",COUNTIFS(Ventes!$D$6:$D$505,A25,Ventes!$M$6:$M$505,"Livrée et payée")) | E25: =IF(A25="","",SUMIFS(Ventes!$K$6:$K$505,Ventes!$D$6:$D$505,A25,Ventes!$M$6:$M$505,"Livrée et payée")) | F25: =IF(A25="","",IF(D25=0,"",_xlfn.MAXIFS(Ventes!$B$6:$B$505,Ventes!$D$6:$D$505,A25,Ventes!$M$6:$M$505,"Livrée et payée"))) | G25: =IF(OR(A25="",F25=""),"",TODAY()-F25) | H25: =IF(A25="","",COUNTIFS(Ventes!$D$6:$D$505,A25,Ventes!$M$6:$M$505,"Annulée")) | I25: =IF(A25="","",IF(D25=0,"Prospect",IF(G25>60,"À relancer",IF(D25>=3,"VIP",IF(D25=2,"Fidèle","Nouveau"))))) | J25: =IF(A25="","",IF(H25>=1,"Oui (a déjà annulé)","Non"))
... D305: =IF(A305="","",COUNTIFS(Ventes!$D$6:$D$505,A305,Ventes!$M$6:$M$505,"Livrée et payée")) | E305: =IF(A305="","",SUMIFS(Ventes!$K$6:$K$505,Ventes!$D$6:$D$505,A305,Ventes!$M$6:$M$505,"Livrée et payée")) | F305: =IF(A305="","",IF(D305=0,"",_xlfn.MAXIFS(Ventes!$B$6:$B$505,Ventes!$D$6:$D$505,A305,Ventes!$M$6:$M$505,"Livrée et payée"))) | G305: =IF(OR(A305="",F305=""),"",TODAY()-F305) | H305: =IF(A305="","",COUNTIFS(Ventes!$D$6:$D$505,A305,Ventes!$M$6:$M$505,"Annulée")) | I305: =IF(A305="","",IF(D305=0,"Prospect",IF(G305>60,"À relancer",IF(D305>=3,"VIP",IF(D305=2,"Fidèle","Nouveau"))))) | J305: =IF(A305="","",IF(H305>=1,"Oui (a déjà annulé)","Non"))

Sheet Dépenses
A1: Autres dépenses du business
A2: Hors publicité (déjà suivie dans Suivi pubs) et hors coût des produits (déjà dans Ventes).
A3: Cellules jaunes : à remplir · cellules grises : calculées automatiquement (ne pas modifier)
A5: Date | B5: Catégorie | C5: Description | D5: Montant (FCFA) | E5: Mois
A6: 46268 | B6: Emballages en gros | C6: Sachets et cartes de remerciement | D6: 6000 | E6: =IF(A6="","",DATE(YEAR(A6),MONTH(A6),1)) -> 46266
A7: 46275 | B7: Internet et crédit | C7: Forfait data du mois | D7: 3000 | E7: =IF(A7="","",DATE(YEAR(A7),MONTH(A7),1)) -> 46266
A8: 46296 | B8: Emballages en gros | C8: Sachets kraft avec logo | D8: 5000 | E8: =IF(A8="","",DATE(YEAR(A8),MONTH(A8),1)) -> 46296
A9: 46297 | B9: Internet et crédit | C9: Forfait data du mois | D9: 3000 | E9: =IF(A9="","",DATE(YEAR(A9),MONTH(A9),1)) -> 46296
A10: 46299 | B10: Transport / achats | C10: Taxi pour réassort au marché | D10: 4000 | E10: =IF(A10="","",DATE(YEAR(A10),MONTH(A10),1)) -> 46296
E11: =IF(A11="","",DATE(YEAR(A11),MONTH(A11),1))
E12: =IF(A12="","",DATE(YEAR(A12),MONTH(A12),1))
E13: =IF(A13="","",DATE(YEAR(A13),MONTH(A13),1))
E14: =IF(A14="","",DATE(YEAR(A14),MONTH(A14),1))
E15: =IF(A15="","",DATE(YEAR(A15),MONTH(A15),1))
E16: =IF(A16="","",DATE(YEAR(A16),MONTH(A16),1))
E17: =IF(A17="","",DATE(YEAR(A17),MONTH(A17),1))
E18: =IF(A18="","",DATE(YEAR(A18),MONTH(A18),1))
E19: =IF(A19="","",DATE(YEAR(A19),MONTH(A19),1))
E20: =IF(A20="","",DATE(YEAR(A20),MONTH(A20),1))
E21: =IF(A21="","",DATE(YEAR(A21),MONTH(A21),1))
E22: =IF(A22="","",DATE(YEAR(A22),MONTH(A22),1))
... E205: =IF(A205="","",DATE(YEAR(A205),MONTH(A205),1))

Sheet Bilan annuel
A1: Bilan annuel
A2: Les 12 mois de l’année choisie dans Paramètres (cellule B7).
A3: Cellules jaunes : à remplir · cellules grises : calculées automatiquement (ne pas modifier)
A5: Mois | B5: Chiffre d’affaires | C5: Ventes | D5: Pub | E5: Marge brute | F5: Autres dépenses | G5: Bénéfice net | H5: Nouveaux clients | I5: Coût par vente pub
A6: =DATE(Paramètres!$B$7,1,1) -> 46023 | B6: =SUMIFS(Ventes!$K$6:$K$505,Ventes!$T$6:$T$505,$A6,Ventes!$M$6:$M$505,"Livrée et payée") -> 0 | C6: =COUNTIFS(Ventes!$T$6:$T$505,$A6,Ventes!$M$6:$M$505,"Livrée et payée") -> 0 | D6: =SUMIFS('Suivi pubs'!$E$6:$E$370,'Suivi pubs'!$N$6:$N$370,$A6) -> 0 | E6: =SUMIFS(Ventes!$R$6:$R$505,Ventes!$T$6:$T$505,$A6) -> 0 | F6: =SUMIFS(Dépenses!$D$6:$D$205,Dépenses!$E$6:$E$205,$A6) -> 0 | G6: =E6-D6-F6 -> 0 | H6: =COUNTIFS(Ventes!$T$6:$T$505,$A6,Ventes!$M$6:$M$505,"Livrée et payée",Ventes!$U$6:$U$505,"Nouveau") -> 0 | I6: =IF(SUMIFS('Suivi pubs'!$G$6:$G$370,'Suivi pubs'!$N$6:$N$370,$A6)=0,0,D6/SUMIFS('Suivi pubs'!$G$6:$G$370,'Suivi pubs'!$N$6:$N$370,$A6)) -> 0
A7: =DATE(Paramètres!$B$7,2,1) -> 46054 | B7: =SUMIFS(Ventes!$K$6:$K$505,Ventes!$T$6:$T$505,$A7,Ventes!$M$6:$M$505,"Livrée et payée") -> 0 | C7: =COUNTIFS(Ventes!$T$6:$T$505,$A7,Ventes!$M$6:$M$505,"Livrée et payée") -> 0 | D7: =SUMIFS('Suivi pubs'!$E$6:$E$370,'Suivi pubs'!$N$6:$N$370,$A7) -> 0 | E7: =SUMIFS(Ventes!$R$6:$R$505,Ventes!$T$6:$T$505,$A7) -> 0 | F7: =SUMIFS(Dépenses!$D$6:$D$205,Dépenses!$E$6:$E$205,$A7) -> 0 | G7: =E7-D7-F7 -> 0 | H7: =COUNTIFS(Ventes!$T$6:$T$505,$A7,Ventes!$M$6:$M$505,"Livrée et payée",Ventes!$U$6:$U$505,"Nouveau") -> 0 | I7: =IF(SUMIFS('Suivi pubs'!$G$6:$G$370,'Suivi pubs'!$N$6:$N$370,$A7)=0,0,D7/SUMIFS('Suivi pubs'!$G$6:$G$370,'Suivi pubs'!$N$6:$N$370,$A7)) -> 0
A8: =DATE(Paramètres!$B$7,3,1) -> 46082 | B8: =SUMIFS(Ventes!$K$6:$K$505,Ventes!$T$6:$T$505,$A8,Ventes!$M$6:$M$505,"Livrée et payée") -> 0 | C8: =COUNTIFS(Ventes!$T$6:$T$505,$A8,Ventes!$M$6:$M$505,"Livrée et payée") -> 0 | D8: =SUMIFS('Suivi pubs'!$E$6:$E$370,'Suivi pubs'!$N$6:$N$370,$A8) -> 0 | E8: =SUMIFS(Ventes!$R$6:$R$505,Ventes!$T$6:$T$505,$A8) -> 0 | F8: =SUMIFS(Dépenses!$D$6:$D$205,Dépenses!$E$6:$E$205,$A8) -> 0 | G8: =E8-D8-F8 -> 0 | H8: =COUNTIFS(Ventes!$T$6:$T$505,$A8,Ventes!$M$6:$M$505,"Livrée et payée",Ventes!$U$6:$U$505,"Nouveau") -> 0 | I8: =IF(SUMIFS('Suivi pubs'!$G$6:$G$370,'Suivi pubs'!$N$6:$N$370,$A8)=0,0,D8/SUMIFS('Suivi pubs'!$G$6:$G$370,'Suivi pubs'!$N$6:$N$370,$A8)) -> 0
A9: =DATE(Paramètres!$B$7,4,1) -> 46113 | B9: =SUMIFS(Ventes!$K$6:$K$505,Ventes!$T$6:$T$505,$A9,Ventes!$M$6:$M$505,"Livrée et payée") -> 0 | C9: =COUNTIFS(Ventes!$T$6:$T$505,$A9,Ventes!$M$6:$M$505,"Livrée et payée") -> 0 | D9: =SUMIFS('Suivi pubs'!$E$6:$E$370,'Suivi pubs'!$N$6:$N$370,$A9) -> 0 | E9: =SUMIFS(Ventes!$R$6:$R$505,Ventes!$T$6:$T$505,$A9) -> 0 | F9: =SUMIFS(Dépenses!$D$6:$D$205,Dépenses!$E$6:$E$205,$A9) -> 0 | G9: =E9-D9-F9 -> 0 | H9: =COUNTIFS(Ventes!$T$6:$T$505,$A9,Ventes!$M$6:$M$505,"Livrée et payée",Ventes!$U$6:$U$505,"Nouveau") -> 0 | I9: =IF(SUMIFS('Suivi pubs'!$G$6:$G$370,'Suivi pubs'!$N$6:$N$370,$A9)=0,0,D9/SUMIFS('Suivi pubs'!$G$6:$G$370,'Suivi pubs'!$N$6:$N$370,$A9)) -> 0
A10: =DATE(Paramètres!$B$7,5,1) -> 46143 | B10: =SUMIFS(Ventes!$K$6:$K$505,Ventes!$T$6:$T$505,$A10,Ventes!$M$6:$M$505,"Livrée et payée") -> 0 | C10: =COUNTIFS(Ventes!$T$6:$T$505,$A10,Ventes!$M$6:$M$505,"Livrée et payée") -> 0 | D10: =SUMIFS('Suivi pubs'!$E$6:$E$370,'Suivi pubs'!$N$6:$N$370,$A10) -> 0 | E10: =SUMIFS(Ventes!$R$6:$R$505,Ventes!$T$6:$T$505,$A10) -> 0 | F10: =SUMIFS(Dépenses!$D$6:$D$205,Dépenses!$E$6:$E$205,$A10) -> 0 | G10: =E10-D10-F10 -> 0 | H10: =COUNTIFS(Ventes!$T$6:$T$505,$A10,Ventes!$M$6:$M$505,"Livrée et payée",Ventes!$U$6:$U$505,"Nouveau") -> 0 | I10: =IF(SUMIFS('Suivi pubs'!$G$6:$G$370,'Suivi pubs'!$N$6:$N$370,$A10)=0,0,D10/SUMIFS('Suivi pubs'!$G$6:$G$370,'Suivi pubs'!$N$6:$N$370,$A10)) -> 0
A11: =DATE(Paramètres!$B$7,6,1) -> 46174 | B11: =SUMIFS(Ventes!$K$6:$K$505,Ventes!$T$6:$T$505,$A11,Ventes!$M$6:$M$505,"Livrée et payée") -> 0 | C11: =COUNTIFS(Ventes!$T$6:$T$505,$A11,Ventes!$M$6:$M$505,"Livrée et payée") -> 0 | D11: =SUMIFS('Suivi pubs'!$E$6:$E$370,'Suivi pubs'!$N$6:$N$370,$A11) -> 0 | E11: =SUMIFS(Ventes!$R$6:$R$505,Ventes!$T$6:$T$505,$A11) -> 0 | F11: =SUMIFS(Dépenses!$D$6:$D$205,Dépenses!$E$6:$E$205,$A11) -> 0 | G11: =E11-D11-F11 -> 0 | H11: =COUNTIFS(Ventes!$T$6:$T$505,$A11,Ventes!$M$6:$M$505,"Livrée et payée",Ventes!$U$6:$U$505,"Nouveau") -> 0 | I11: =IF(SUMIFS('Suivi pubs'!$G$6:$G$370,'Suivi pubs'!$N$6:$N$370,$A11)=0,0,D11/SUMIFS('Suivi pubs'!$G$6:$G$370,'Suivi pubs'!$N$6:$N$370,$A11)) -> 0
A12: =DATE(Paramètres!$B$7,7,1) -> 46204 | B12: =SUMIFS(Ventes!$K$6:$K$505,Ventes!$T$6:$T$505,$A12,Ventes!$M$6:$M$505,"Livrée et payée") -> 0 | C12: =COUNTIFS(Ventes!$T$6:$T$505,$A12,Ventes!$M$6:$M$505,"Livrée et payée") -> 0 | D12: =SUMIFS('Suivi pubs'!$E$6:$E$370,'Suivi pubs'!$N$6:$N$370,$A12) -> 0 | E12: =SUMIFS(Ventes!$R$6:$R$505,Ventes!$T$6:$T$505,$A12) -> 0 | F12: =SUMIFS(Dépenses!$D$6:$D$205,Dépenses!$E$6:$E$205,$A12) -> 0 | G12: =E12-D12-F12 -> 0 | H12: =COUNTIFS(Ventes!$T$6:$T$505,$A12,Ventes!$M$6:$M$505,"Livrée et payée",Ventes!$U$6:$U$505,"Nouveau") -> 0 | I12: =IF(SUMIFS('Suivi pubs'!$G$6:$G$370,'Suivi pubs'!$N$6:$N$370,$A12)=0,0,D12/SUMIFS('Suivi pubs'!$G$6:$G$370,'Suivi pubs'!$N$6:$N$370,$A12)) -> 0
A13: =DATE(Paramètres!$B$7,8,1) -> 46235 | B13: =SUMIFS(Ventes!$K$6:$K$505,Ventes!$T$6:$T$505,$A13,Ventes!$M$6:$M$505,"Livrée et payée") -> 0 | C13: =COUNTIFS(Ventes!$T$6:$T$505,$A13,Ventes!$M$6:$M$505,"Livrée et payée") -> 0 | D13: =SUMIFS('Suivi pubs'!$E$6:$E$370,'Suivi pubs'!$N$6:$N$370,$A13) -> 0 | E13: =SUMIFS(Ventes!$R$6:$R$505,Ventes!$T$6:$T$505,$A13) -> 0 | F13: =SUMIFS(Dépenses!$D$6:$D$205,Dépenses!$E$6:$E$205,$A13) -> 0 | G13: =E13-D13-F13 -> 0 | H13: =COUNTIFS(Ventes!$T$6:$T$505,$A13,Ventes!$M$6:$M$505,"Livrée et payée",Ventes!$U$6:$U$505,"Nouveau") -> 0 | I13: =IF(SUMIFS('Suivi pubs'!$G$6:$G$370,'Suivi pubs'!$N$6:$N$370,$A13)=0,0,D13/SUMIFS('Suivi pubs'!$G$6:$G$370,'Suivi pubs'!$N$6:$N$370,$A13)) -> 0
A14: =DATE(Paramètres!$B$7,9,1) -> 46266 | B14: =SUMIFS(Ventes!$K$6:$K$505,Ventes!$T$6:$T$505,$A14,Ventes!$M$6:$M$505,"Livrée et payée") -> 64000 | C14: =COUNTIFS(Ventes!$T$6:$T$505,$A14,Ventes!$M$6:$M$505,"Livrée et payée") -> 6 | D14: =SUMIFS('Suivi pubs'!$E$6:$E$370,'Suivi pubs'!$N$6:$N$370,$A14) -> 6000 | E14: =SUMIFS(Ventes!$R$6:$R$505,Ventes!$T$6:$T$505,$A14) -> 30950 | F14: =SUMIFS(Dépenses!$D$6:$D$205,Dépenses!$E$6:$E$205,$A14) -> 9000 | G14: =E14-D14-F14 -> 15950 | H14: =COUNTIFS(Ventes!$T$6:$T$505,$A14,Ventes!$M$6:$M$505,"Livrée et payée",Ventes!$U$6:$U$505,"Nouveau") -> 5 | I14: =IF(SUMIFS('Suivi pubs'!$G$6:$G$370,'Suivi pubs'!$N$6:$N$370,$A14)=0,0,D14/SUMIFS('Suivi pubs'!$G$6:$G$370,'Suivi pubs'!$N$6:$N$370,$A14)) -> 6000
A15: =DATE(Paramètres!$B$7,10,1) -> 46296 | B15: =SUMIFS(Ventes!$K$6:$K$505,Ventes!$T$6:$T$505,$A15,Ventes!$M$6:$M$505,"Livrée et payée") -> 150000 | C15: =COUNTIFS(Ventes!$T$6:$T$505,$A15,Ventes!$M$6:$M$505,"Livrée et payée") -> 11 | D15: =SUMIFS('Suivi pubs'!$E$6:$E$370,'Suivi pubs'!$N$6:$N$370,$A15) -> 12000 | E15: =SUMIFS(Ventes!$R$6:$R$505,Ventes!$T$6:$T$505,$A15) -> 69750 | F15: =SUMIFS(Dépenses!$D$6:$D$205,Dépenses!$E$6:$E$205,$A15) -> 12000 | G15: =E15-D15-F15 -> 45750 | H15: =COUNTIFS(Ventes!$T$6:$T$505,$A15,Ventes!$M$6:$M$505,"Livrée et payée",Ventes!$U$6:$U$505,"Nouveau") -> 2 | I15: =IF(SUMIFS('Suivi pubs'!$G$6:$G$370,'Suivi pubs'!$N$6:$N$370,$A15)=0,0,D15/SUMIFS('Suivi pubs'!$G$6:$G$370,'Suivi pubs'!$N$6:$N$370,$A15)) -> 1714.2857
A16: =DATE(Paramètres!$B$7,11,1) -> 46327 | B16: =SUMIFS(Ventes!$K$6:$K$505,Ventes!$T$6:$T$505,$A16,Ventes!$M$6:$M$505,"Livrée et payée") -> 0 | C16: =COUNTIFS(Ventes!$T$6:$T$505,$A16,Ventes!$M$6:$M$505,"Livrée et payée") -> 0 | D16: =SUMIFS('Suivi pubs'!$E$6:$E$370,'Suivi pubs'!$N$6:$N$370,$A16) -> 0 | E16: =SUMIFS(Ventes!$R$6:$R$505,Ventes!$T$6:$T$505,$A16) -> 0 | F16: =SUMIFS(Dépenses!$D$6:$D$205,Dépenses!$E$6:$E$205,$A16) -> 0 | G16: =E16-D16-F16 -> 0 | H16: =COUNTIFS(Ventes!$T$6:$T$505,$A16,Ventes!$M$6:$M$505,"Livrée et payée",Ventes!$U$6:$U$505,"Nouveau") -> 0 | I16: =IF(SUMIFS('Suivi pubs'!$G$6:$G$370,'Suivi pubs'!$N$6:$N$370,$A16)=0,0,D16/SUMIFS('Suivi pubs'!$G$6:$G$370,'Suivi pubs'!$N$6:$N$370,$A16)) -> 0
A17: =DATE(Paramètres!$B$7,12,1) -> 46357 | B17: =SUMIFS(Ventes!$K$6:$K$505,Ventes!$T$6:$T$505,$A17,Ventes!$M$6:$M$505,"Livrée et payée") -> 0 | C17: =COUNTIFS(Ventes!$T$6:$T$505,$A17,Ventes!$M$6:$M$505,"Livrée et payée") -> 0 | D17: =SUMIFS('Suivi pubs'!$E$6:$E$370,'Suivi pubs'!$N$6:$N$370,$A17) -> 0 | E17: =SUMIFS(Ventes!$R$6:$R$505,Ventes!$T$6:$T$505,$A17) -> 0 | F17: =SUMIFS(Dépenses!$D$6:$D$205,Dépenses!$E$6:$E$205,$A17) -> 0 | G17: =E17-D17-F17 -> 0 | H17: =COUNTIFS(Ventes!$T$6:$T$505,$A17,Ventes!$M$6:$M$505,"Livrée et payée",Ventes!$U$6:$U$505,"Nouveau") -> 0 | I17: =IF(SUMIFS('Suivi pubs'!$G$6:$G$370,'Suivi pubs'!$N$6:$N$370,$A17)=0,0,D17/SUMIFS('Suivi pubs'!$G$6:$G$370,'Suivi pubs'!$N$6:$N$370,$A17)) -> 0
A18: TOTAL | B18: =SUM(B6:B17) -> 214000 | C18: =SUM(C6:C17) -> 17 | D18: =SUM(D6:D17) -> 18000 | E18: =SUM(E6:E17) -> 100700 | F18: =SUM(F6:F17) -> 21000 | G18: =SUM(G6:G17) -> 61700 | H18: =SUM(H6:H17) -> 7 | I18: —

Sheet Plan 30 jours
A1: Plan d’action de 30 jours
A2: Une action par jour. Coche « Oui » quand c’est fait. L’avancement se calcule seul.
A3: Cellules jaunes : à remplir · cellules grises : calculées automatiquement (ne pas modifier)
G4: PLAN DE CROISSANCE SUR 90 JOURS
A5: Jour | B5: Action | C5: Chapitre | D5: Fait ? | E5: Date | G5: Période | H5: Objectif | I5: Actions | J5: Fait ?
A6: 1 | B6: Faire l’auto-diagnostic et noter ton score | C6: 1 | D6: Oui | G6: Jours 1 à 30 | H6: Stabiliser | I6: Une pub rentable qui tourne, suivi des chiffres chaque jour, 20 clients dans ta liste
A7: 2 | B7: Remplir la grille produit et choisir ton produit | C7: 2 | D7: Oui | G7: Jours 31 à 60 | H7: Augmenter le panier | I7: Créer 2 packs, ajouter 1 produit complémentaire, lancer le parrainage
A8: 3 | B8: Calculer ta vraie marge et fixer ton prix | C8: 2 | D8: Oui | G8: Jours 61 à 90 | H8: Déléguer et accélérer | I8: Confier la livraison, augmenter le budget des pubs gagnantes, tester une nouvelle zone
A9: 4 | B9: Publier une publication test et compter les messages | C9: 2 | D9: Oui
A10: 5 | B10: Créer ou refaire ta page : nom, photo, couverture, description | C10: 3 | D10: Oui
A11: 6 | B11: Installer et configurer WhatsApp Business, le relier à la page | C11: 3 | D11: Oui
A12: 7 | B12: Sécuriser ton compte : double authentification, second administrateur | C12: 3 | D12: Oui
A13: 8 | B13: Récolter tes 5 premiers avis ou témoignages | C13: 3 | D13: Oui
A14: 9 | B14: Préparer et programmer 7 publications | C14: 4 | D14: Oui
A15: 10 | B15: Tourner 3 vidéos courtes de démonstration | C15: 4 | D15: Oui
A16: 11 | B16: Rejoindre 10 groupes et laisser 5 commentaires utiles | C16: 5 | D16: Oui
A17: 12 | B17: Publier 3 annonces sur Marketplace (si disponible) | C17: 5 | D17: Oui
A18: 13 | B18: Créer ton propre groupe de clients | C18: 5
A19: 14 | B19: Faire ton premier direct vidéo | C19: 4
A20: 15 | B20: Écrire 3 versions de ta pub avec la formule PPPA | C20: 7
A21: 16 | B21: Lancer ta première pub test, objectif « messages » | C21: 6
A22: 17 | B22: Enregistrer tes 7 réponses rapides | C22: 9
A23: 18 | B23: Ne rien toucher à la pub, noter les chiffres | C23: 8
A24: 19 | B24: Noter les chiffres, répondre à tous les messages en moins de 5 minutes | C24: 8, 9
A25: 20 | B25: Analyser : couper, améliorer ou augmenter | C25: 8
A26: 21 | B26: Créer ta liste de clients et ta liste de diffusion | C26: 10
A27: 22 | B27: Envoyer le message de suivi à tes clients récents | C27: 10
A28: 23 | B28: Lancer une nouvelle version de pub pour battre la meilleure | C28: 7
A29: 24 | B29: Créer ton premier pack | C29: 11
... A35: 30 | B35: Refaire l’auto-diagnostic et comparer avec le jour 1 | C35: 1
B37: Avancement du plan | D37: =COUNTIF(D6:D35,"Oui")/30 -> 0.4

Sheet Page pro
A1: Checklist « page pro » en 20 points
A2: Coche « Oui » pour chaque point en place. Ta page est ta vitrine (chapitre 3).
A3: Cellules jaunes : à remplir · cellules grises : calculées automatiquement (ne pas modifier)
A5: N° | B5: Point à vérifier | C5: En place ?
A6: 1 | B6: Nom de page court et clair | C6: Oui
A7: 2 | B7: Photo de profil nette et lisible | C7: Oui
A8: 3 | B8: Couverture avec promesse et contact
A9: 4 | B9: Description complète avec le modèle | C9: Oui
A10: 5 | B10: Bouton d’action WhatsApp ou message | C10: Oui
A11: 6 | B11: Numéro WhatsApp Business relié à la page
A12: 7 | B12: Une publication épinglée en haut de la page | C12: Oui
A13: 8 | B13: Au moins 5 avis ou témoignages visibles | C13: Oui
A14: 9 | B14: Au moins 3 vraies photos de produits prises par moi
A15: 10 | B15: Une vidéo où je me présente | C15: Oui
A16: 11 | B16: Une vidéo de livraison | C16: Oui
A17: 12 | B17: Zones et délais de livraison indiqués
A18: 13 | B18: Moyens de paiement indiqués | C18: Oui
A19: 14 | B19: WhatsApp Business : profil complet | C19: Oui
A20: 15 | B20: WhatsApp Business : catalogue rempli
A21: 16 | B21: WhatsApp Business : messages d’accueil et d’absence | C21: Oui
A22: 17 | B22: WhatsApp Business : 5 réponses rapides enregistrées | C22: Oui
A23: 18 | B23: Double authentification activée sur Facebook
A24: 19 | B24: Un deuxième administrateur de confiance ajouté | C24: Oui
A25: 20 | B25: Double vérification activée sur WhatsApp | C25: Oui
B27: Score de ta page | C27: =COUNTIF(C6:C25,"Oui") -> 14
B28: Verdict | C28: =IF(C27>=18,"Page pro : prête à vendre",IF(C27>=12,"Bonne base : complète les points manquants","Priorité : refais ta page avant toute pub")) -> Bonne base : complète les points manquants
